Workbook

Sheet README
A1: Prefs database - layered reconciliation
A2: Built 2026-08-21 from prefsTEST.xlsx (809 issue rows, 354 parent blocks) + the QOLpaste sheet (1,004 securities).
A4: WHAT THIS IS
A5: Your current required yield / normal price / discount / total-return-potential, next to recomputed values,
A6: one layer of change at a time. Each layer has its own delta column so you can accept or reject it on its own.
A8: L1 wiring fixed Same base yield, same penalty each row already used. Isolates pure bug impact.
A9: L2 penalties unified One scheme from the Inputs tab instead of the two that coexist today.
A10: L3 payment derived Annual amount = coupon x par everywhere, instead of 106 different formulas.
A11: NOTE: L3 moves nothing. In most rows the coupon column is itself defined as amount/par, so the two
A12: conventions cannot disagree - they are the same number twice. Standardizing here is a maintainability
A13: fix, not a correction. The independent check on coupon and amount is L5, against QuantumOnline.
A14: L4 market-cap ladder Base yield keyed off parent market cap instead of parent price.
... A45: Zero-Base Parents the 62 blocks whose valuation is broken because the parent did not quote

Sheet Inputs
A1: MASTER INPUTS
A2: Every yellow cell is an input. Edit it and the Reconciliation tab recalculates.
A4: Rates
A5: Treasury | B5: 0.04 | D5: Was 'T-Z'!E1 in the old workbook.
A6: SOFR | C6: <- needs value | D6: REPLACES the dead LIBOR cell (old value 0.75%). Needs a feed - see notes.
A8: Required-yield adjustments
A9: QDI switch | B9: -1 | D9: Sign on the QDI adjustment. -1 = QDI issues get a LOWER required yield.
A10: QDI adjustment (relative) | B10: 0.05 | D10: Applied as base x this x switch. 5% of base, not 5 points.
A12: Structure adjustment (absolute) | D12: Replaces the nested IFs. Add rows freely.
A13: PREFERRED | B13: 0
A14: BABY_BOND | B14: -0.005 | D14: Was "debt" -0.50%. The competing scheme used -0.75%.
A15: TRUPS | B15: -0.005 | D15: Was "tp"/"trups", inherited the debt adjustment.
A17: Coupon-type adjustment (absolute) | D17: New axis. All zero until you decide otherwise.
A18: FIXED | B18: 0
A19: FIX_TO_FLOAT | B19: 0
A20: FLOATER | B20: 0
A21: RESET | B21: 0
A22: VARIABLE | B22: 0
A23: CONVERTIBLE | B23: 0
A24: MAND_CONVERT | B24: 0
A26: Market-cap -> base yield ladder
A27: Upper bound ($mm) | B27: Base yield | D27: Replaces the old PARENT PRICE ladder: <=$10 -> 10%, $10-15 -> 9%, $15-20 -> 8.5%, >$20 -> 8%
A28: 250 | B28: 0.1
A29: 1000 | B29: 0.09
A30: 5000 | B30: 0.085
A31: 20000 | B31: 0.08
A32: 99999999 | B32: 0.075
A34: NOTES
A35: 1. Baseline columns (R/S/T/U as they sit today) are HARDCODED cached values from prefsTEST.xlsx.
A36: They cannot be recomputed here - they came from the RealTick RTD feed. Price is a snapshot from the same source.
A37: 2. Market cap is the cached RealTick value on each parent row, parsed from the "1.2 B" / "500 M" string.
A38: 62 parents show 0 because RealTick returned nothing for the parent at all. Those need a real market cap.
A39: 3. Every layer column IS a live formula against this tab. Retune a yellow cell and the deltas move.
A40: 4. Cumulative is deliberately NOT an adjustment - it is a display flag only.

Sheet Reconciliation
A1: CONTEXT | R1: AS IT SITS TODAY | V1: L1 wiring fixed | AB1: L2 penalties unified | AG1: L3 payment derived | AL1: L4 market-cap ladder | AT1: L5 facts refreshed | BC1: SUMMARY
A2: Sheet | B2: Src Row | C2: Symbol | D2: Parent | E2: Parent Name | F2: Mkt Cap ($mm) | G2: Structure | H2: Coupon Type | I2: QDI | J2: Freq | K2: Per/Yr | L2: Par (wb) | M2: Coupon (wb) | N2: Ann Amt (wb) | O2: Price | P2: Exception | Q2: Group Base | R2: R cur | S2: S cur | T2: T cur | U2: U cur | V2: hist adj | W2: R L1 | X2: S L1 | Y2: T L1 | Z2: U L1 | AA2: dU L1 | AB2: R L2 | AC2: S L2 | AD2: T L2 | AE2: U L2 | AF2: dU L2 | AG2: Ann Amt L3 | AH2: S L3 | AI2: T L3 | AJ2: U L3 | AK2: dU L3 | AL2: Base mktcap | AM2: Base override | AN2: Base eff | AO2: R L4 | AP2: S L4 | AQ2: T L4 | AR2: U L4 | AS2: dU L4 | AT2: Par QOL | AU2: Ann QOL | AV2: Par eff | AW2: Ann eff | AX2: R L5 | AY2: S L5 | AZ2: T L5 | BA2: U L5 | BB2: dU L5 | BC2: TOTAL dU | BD2: Flags
A3: A-C | B3: 7 | C3: AAIN | D3: AAIC | E3: na | G3: PREFERRED | H3: FIXED | I3: no | J3: Q | K3: 4 | L3: 25 | M3: 0.06 | N3: 1.5 | O3: 0 | P3: OK | Q3: 0 | R3: 0 | V3: 0 | W3: =IF(N(Q3)=0,"",Q3+IF(I3="yes",Q3*Inputs!$B$10*Inputs!$B$9,0)+V3) | X3: =IF(OR(N(W3)<=0,N(N3)=0,N(L3)=0),"",MIN(L3,N3/W3)) | Y3: =IF(OR(X3="",N(O3)=0),"",X3/O3-1) | Z3: =IF(OR(Y3="",N(O3)=0),"",Y3+N3/O3) | AA3: =IF(OR(Z3="",N(U3)=0),"",Z3-U3) | AB3: =IF(N(Q3)=0,"",Q3+IF(I3="yes",Q3*Inputs!$B$10*Inputs!$B$9,0)+IFERROR(INDEX(Inputs!$B$13:$B$15,MATCH(G3,Inputs!$A$13:$A$15,0)),0)+IFERROR(INDEX(Inputs!$B$18:$B$24,MATCH(H3,Inputs!$A$18:$A$24,0)),0)) | AC3: =IF(OR(N(AB3)<=0,N(N3)=0,N(L3)=0),"",MIN(L3,N3/AB3)) | AD3: =IF(OR(AC3="",N(O3)=0),"",AC3/O3-1) | AE3: =IF(OR(AD3="",N(O3)=0),"",AD3+N3/O3) | AF3: =IF(OR(AE3="",N(Z3)=0),"",AE3-Z3) | AG3: =IF(AND(N(M3)>0,N(L3)>0),M3*L3,N3) -> 1.5 | AH3: =IF(OR(N(AB3)<=0,N(AG3)=0,N(L3)=0),"",MIN(L3,AG3/AB3)) | AI3: =IF(OR(AH3="",N(O3)=0),"",AH3/O3-1) | AJ3: =IF(OR(AI3="",N(O3)=0),"",AI3+AG3/O3) | AK3: =IF(OR(AJ3="",N(AE3)=0),"",AJ3-AE3) | AL3: =IF(N(F3)=0,"",INDEX(Inputs!$B$28:$B$32,IFERROR(MATCH(F3,Inputs!$A$28:$A$32,1),0)+1)) | AN3: =IF(N(AM3)>0,AM3,AL3) | AO3: =IF(N(AN3)=0,"",AN3+IF(I3="yes",AN3*Inputs!$B$10*Inputs!$B$9,0)+IFERROR(INDEX(Inputs!$B$13:$B$15,MATCH(G3,Inputs!$A$13:$A$15,0)),0)+IFERROR(INDEX(Inputs!$B$18:$B$24,MATCH(H3,Inputs!$A$18:$A$24,0)),0)) | AP3: =IF(OR(N(AO3)<=0,N(AG3)=0,N(L3)=0),"",MIN(L3,AG3/AO3)) | AQ3: =IF(OR(AP3="",N(O3)=0),"",AP3/O3-1) | AR3: =IF(OR(AQ3="",N(O3)=0),"",AQ3+AG3/O3) | AS3: =IF(OR(AR3="",N(AJ3)=0),"",AR3-AJ3) | AV3: =IF(N(AT3)>0,AT3,L3) -> 25 | AW3: =IF(AND(N(M3)>0,N(AV3)>0),M3*AV3,IF(N(AU3)>0,AU3,N3)) -> 1.5 | AX3: =IF(N(AN3)=0,"",AN3+IF(I3="yes",AN3*Inputs!$B$10*Inputs!$B$9,0)+IFERROR(INDEX(Inputs!$B$13:$B$15,MATCH(G3,Inputs!$A$13:$A$15,0)),0)+IFERROR(INDEX(Inputs!$B$18:$B$24,MATCH(H3,Inputs!$A$18:$A$24,0)),0)) | AY3: =IF(OR(N(AX3)<=0,N(AW3)=0,N(AV3)=0),"",MIN(AV3,AW3/AX3)) | AZ3: =IF(OR(AY3="",N(O3)=0),"",AY3/O3-1) | BA3: =IF(OR(AZ3="",N(O3)=0),"",AZ3+AW3/O3) | BB3: =IF(OR(BA3="",N(AR3)=0),"",BA3-AR3) | BC3: =IF(OR(BA3="",N(U3)=0),"",BA3-U3) | BD3: NO PRICE; not in QOL paste - retire/rename?; group base = 0 (parent did not quote)
A4: A-C | B4: 11 | C4: ACP-A | D4: ACP | E4: ABRDN INCOME CREDIT STRATEGIES | F4: 637 | G4: PREFERRED | H4: FIXED | I4: yes | J4: Q | K4: 4 | L4: 25 | M4: 0.0525 | N4: 1.3125 | O4: 19.36 | P4: OK | Q4: 0.1 | R4: 0.095 | S4: 13.815789 | T4: -0.28637451 | U4: -0.21858009 | V4: 0 | W4: =IF(N(Q4)=0,"",Q4+IF(I4="yes",Q4*Inputs!$B$10*Inputs!$B$9,0)+V4) -> 0.095 | X4: =IF(OR(N(W4)<=0,N(N4)=0,N(L4)=0),"",MIN(L4,N4/W4)) -> 13.815789 | Y4: =IF(OR(X4="",N(O4)=0),"",X4/O4-1) -> -0.28637451 | Z4: =IF(OR(Y4="",N(O4)=0),"",Y4+N4/O4) -> -0.21858009 | AA4: =IF(OR(Z4="",N(U4)=0),"",Z4-U4) -> 0 | AB4: =IF(N(Q4)=0,"",Q4+IF(I4="yes",Q4*Inputs!$B$10*Inputs!$B$9,0)+IFERROR(INDEX(Inputs!$B$13:$B$15,MATCH(G4,Inputs!$A$13:$A$15,0)),0)+IFERROR(INDEX(Inputs!$B$18:$B$24,MATCH(H4,Inputs!$A$18:$A$24,0)),0)) -> 0.095 | AC4: =IF(OR(N(AB4)<=0,N(N4)=0,N(L4)=0),"",MIN(L4,N4/AB4)) -> 13.815789 | AD4: =IF(OR(AC4="",N(O4)=0),"",AC4/O4-1) -> -0.28637451 | AE4: =IF(OR(AD4="",N(O4)=0),"",AD4+N4/O4) -> -0.21858009 | AF4: =IF(OR(AE4="",N(Z4)=0),"",AE4-Z4) -> 0 | AG4: =IF(AND(N(M4)>0,N(L4)>0),M4*L4,N4) -> 1.3125 | AH4: =IF(OR(N(AB4)<=0,N(AG4)=0,N(L4)=0),"",MIN(L4,AG4/AB4)) -> 13.815789 | AI4: =IF(OR(AH4="",N(O4)=0),"",AH4/O4-1) -> -0.28637451 | AJ4: =IF(OR(AI4="",N(O4)=0),"",AI4+AG4/O4) -> -0.21858009 | AK4: =IF(OR(AJ4="",N(AE4)=0),"",AJ4-AE4) -> 0 | AL4: =IF(N(F4)=0,"",INDEX(Inputs!$B$28:$B$32,IFERROR(MATCH(F4,Inputs!$A$28:$A$32,1),0)+1)) -> 0.09 | AN4: =IF(N(AM4)>0,AM4,AL4) -> 0.09 | AO4: =IF(N(AN4)=0,"",AN4+IF(I4="yes",AN4*Inputs!$B$10*Inputs!$B$9,0)+IFERROR(INDEX(Inputs!$B$13:$B$15,MATCH(G4,Inputs!$A$13:$A$15,0)),0)+IFERROR(INDEX(Inputs!$B$18:$B$24,MATCH(H4,Inputs!$A$18:$A$24,0)),0)) -> 0.0855 | AP4: =IF(OR(N(AO4)<=0,N(AG4)=0,N(L4)=0),"",MIN(L4,AG4/AO4)) -> 15.350877 | AQ4: =IF(OR(AP4="",N(O4)=0),"",AP4/O4-1) -> -0.20708279 | AR4: =IF(OR(AQ4="",N(O4)=0),"",AQ4+AG4/O4) -> -0.13928837 | AS4: =IF(OR(AR4="",N(AJ4)=0),"",AR4-AJ4) -> 0.079291721 | AT4: 25 | AU4: 1.3125 | AV4: =IF(N(AT4)>0,AT4,L4) -> 25 | AW4: =IF(AND(N(M4)>0,N(AV4)>0),M4*AV4,IF(N(AU4)>0,AU4,N4)) -> 1.3125 | AX4: =IF(N(AN4)=0,"",AN4+IF(I4="yes",AN4*Inputs!$B$10*Inputs!$B$9,0)+IFERROR(INDEX(Inputs!$B$13:$B$15,MATCH(G4,Inputs!$A$13:$A$15,0)),0)+IFERROR(INDEX(Inputs!$B$18:$B$24,MATCH(H4,Inputs!$A$18:$A$24,0)),0)) -> 0.0855 | AY4: =IF(OR(N(AX4)<=0,N(AW4)=0,N(AV4)=0),"",MIN(AV4,AW4/AX4)) -> 15.350877 | AZ4: =IF(OR(AY4="",N(O4)=0),"",AY4/O4-1) -> -0.20708279 | BA4: =IF(OR(AZ4="",N(O4)=0),"",AZ4+AW4/O4) -> -0.13928837 | BB4: =IF(OR(BA4="",N(AR4)=0),"",BA4-AR4) -> 0 | BC4: =IF(OR(BA4="",N(U4)=0),"",BA4-U4) -> 0.079291721
A5: A-C | B5: 15 | C5: ACR-C | D5: ACR | E5: ACRES COMMERCIAL REALTY CORP COM NEW | F5: 104 | G5: PREFERRED | H5: FIXED | I5: yes | J5: Q | K5: 4 | L5: 25 | M5: 0.08625 | N5: 2.15625 | O5: 23.89 | P5: OK | Q5: 0.09 | R5: 0.0855 | S5: 25 | T5: 0.046462955 | U5: 0.13672039 | V5: 0 | W5: =IF(N(Q5)=0,"",Q5+IF(I5="yes",Q5*Inputs!$B$10*Inputs!$B$9,0)+V5) -> 0.0855 | X5: =IF(OR(N(W5)<=0,N(N5)=0,N(L5)=0),"",MIN(L5,N5/W5)) -> 25 | Y5: =IF(OR(X5="",N(O5)=0),"",X5/O5-1) -> 0.046462955 | Z5: =IF(OR(Y5="",N(O5)=0),"",Y5+N5/O5) -> 0.13672039 | AA5: =IF(OR(Z5="",N(U5)=0),"",Z5-U5) -> 0 | AB5: =IF(N(Q5)=0,"",Q5+IF(I5="yes",Q5*Inputs!$B$10*Inputs!$B$9,0)+IFERROR(INDEX(Inputs!$B$13:$B$15,MATCH(G5,Inputs!$A$13:$A$15,0)),0)+IFERROR(INDEX(Inputs!$B$18:$B$24,MATCH(H5,Inputs!$A$18:$A$24,0)),0)) -> 0.0855 | AC5: =IF(OR(N(AB5)<=0,N(N5)=0,N(L5)=0),"",MIN(L5,N5/AB5)) -> 25 | AD5: =IF(OR(AC5="",N(O5)=0),"",AC5/O5-1) -> 0.046462955 | AE5: =IF(OR(AD5="",N(O5)=0),"",AD5+N5/O5) -> 0.13672039 | AF5: =IF(OR(AE5="",N(Z5)=0),"",AE5-Z5) -> 0 | AG5: =IF(AND(N(M5)>0,N(L5)>0),M5*L5,N5) -> 2.15625 | AH5: =IF(OR(N(AB5)<=0,N(AG5)=0,N(L5)=0),"",MIN(L5,AG5/AB5)) -> 25 | AI5: =IF(OR(AH5="",N(O5)=0),"",AH5/O5-1) -> 0.046462955 | AJ5: =IF(OR(AI5="",N(O5)=0),"",AI5+AG5/O5) -> 0.13672039 | AK5: =IF(OR(AJ5="",N(AE5)=0),"",AJ5-AE5) -> 0 | AL5: =IF(N(F5)=0,"",INDEX(Inputs!$B$28:$B$32,IFERROR(MATCH(F5,Inputs!$A$28:$A$32,1),0)+1)) -> 0.1 | AN5: =IF(N(AM5)>0,AM5,AL5) -> 0.1 | AO5: =IF(N(AN5)=0,"",AN5+IF(I5="yes",AN5*Inputs!$B$10*Inputs!$B$9,0)+IFERROR(INDEX(Inputs!$B$13:$B$15,MATCH(G5,Inputs!$A$13:$A$15,0)),0)+IFERROR(INDEX(Inputs!$B$18:$B$24,MATCH(H5,Inputs!$A$18:$A$24,0)),0)) -> 0.095 | AP5: =IF(OR(N(AO5)<=0,N(AG5)=0,N(L5)=0),"",MIN(L5,AG5/AO5)) -> 22.697368 | AQ5: =IF(OR(AP5="",N(O5)=0),"",AP5/O5-1) -> -0.049921791 | AR5: =IF(OR(AQ5="",N(O5)=0),"",AQ5+AG5/O5) -> 0.040335639 | AS5: =IF(OR(AR5="",N(AJ5)=0),"",AR5-AJ5) -> -0.096384746 | AT5: 25 | AU5: 2.16 | AV5: =IF(N(AT5)>0,AT5,L5) -> 25 | AW5: =IF(AND(N(M5)>0,N(AV5)>0),M5*AV5,IF(N(AU5)>0,AU5,N5)) -> 2.15625 | AX5: =IF(N(AN5)=0,"",AN5+IF(I5="yes",AN5*Inputs!$B$10*Inputs!$B$9,0)+IFERROR(INDEX(Inputs!$B$13:$B$15,MATCH(G5,Inputs!$A$13:$A$15,0)),0)+IFERROR(INDEX(Inputs!$B$18:$B$24,MATCH(H5,Inputs!$A$18:$A$24,0)),0)) -> 0.095 | AY5: =IF(OR(N(AX5)<=0,N(AW5)=0,N(AV5)=0),"",MIN(AV5,AW5/AX5)) -> 22.697368 | AZ5: =IF(OR(AY5="",N(O5)=0),"",AY5/O5-1) -> -0.049921791 | BA5: =IF(OR(AZ5="",N(O5)=0),"",AZ5+AW5/O5) -> 0.040335639 | BB5: =IF(OR(BA5="",N(AR5)=0),"",BA5-AR5) -> 0 | BC5: =IF(OR(BA5="",N(U5)=0),"",BA5-U5) -> -0.096384746
A6: A-C | B6: 16 | C6: ACR-D | D6: ACR | E6: ACRES COMMERCIAL REALTY CORP COM NEW | F6: 104 | G6: PREFERRED | H6: FIXED | I6: yes | J6: Q | K6: 4 | L6: 25 | M6: 0.07875 | N6: 1.96875 | O6: 20.85 | P6: OK | Q6: 0.09 | R6: 0.0855 | S6: 23.026316 | T6: 0.10437965 | U6: 0.19880411 | V6: 0 | W6: =IF(N(Q6)=0,"",Q6+IF(I6="yes",Q6*Inputs!$B$10*Inputs!$B$9,0)+V6) -> 0.0855 | X6: =IF(OR(N(W6)<=0,N(N6)=0,N(L6)=0),"",MIN(L6,N6/W6)) -> 23.026316 | Y6: =IF(OR(X6="",N(O6)=0),"",X6/O6-1) -> 0.10437965 | Z6: =IF(OR(Y6="",N(O6)=0),"",Y6+N6/O6) -> 0.19880411 | AA6: =IF(OR(Z6="",N(U6)=0),"",Z6-U6) -> 0 | AB6: =IF(N(Q6)=0,"",Q6+IF(I6="yes",Q6*Inputs!$B$10*Inputs!$B$9,0)+IFERROR(INDEX(Inputs!$B$13:$B$15,MATCH(G6,Inputs!$A$13:$A$15,0)),0)+IFERROR(INDEX(Inputs!$B$18:$B$24,MATCH(H6,Inputs!$A$18:$A$24,0)),0)) -> 0.0855 | AC6: =IF(OR(N(AB6)<=0,N(N6)=0,N(L6)=0),"",MIN(L6,N6/AB6)) -> 23.026316 | AD6: =IF(OR(AC6="",N(O6)=0),"",AC6/O6-1) -> 0.10437965 | AE6: =IF(OR(AD6="",N(O6)=0),"",AD6+N6/O6) -> 0.19880411 | AF6: =IF(OR(AE6="",N(Z6)=0),"",AE6-Z6) -> 0 | AG6: =IF(AND(N(M6)>0,N(L6)>0),M6*L6,N6) -> 1.96875 | AH6: =IF(OR(N(AB6)<=0,N(AG6)=0,N(L6)=0),"",MIN(L6,AG6/AB6)) -> 23.026316 | AI6: =IF(OR(AH6="",N(O6)=0),"",AH6/O6-1) -> 0.10437965 | AJ6: =IF(OR(AI6="",N(O6)=0),"",AI6+AG6/O6) -> 0.19880411 | AK6: =IF(OR(AJ6="",N(AE6)=0),"",AJ6-AE6) -> 0 | AL6: =IF(N(F6)=0,"",INDEX(Inputs!$B$28:$B$32,IFERROR(MATCH(F6,Inputs!$A$28:$A$32,1),0)+1)) -> 0.1 | AN6: =IF(N(AM6)>0,AM6,AL6) -> 0.1 | AO6: =IF(N(AN6)=0,"",AN6+IF(I6="yes",AN6*Inputs!$B$10*Inputs!$B$9,0)+IFERROR(INDEX(Inputs!$B$13:$B$15,MATCH(G6,Inputs!$A$13:$A$15,0)),0)+IFERROR(INDEX(Inputs!$B$18:$B$24,MATCH(H6,Inputs!$A$18:$A$24,0)),0)) -> 0.095 | AP6: =IF(OR(N(AO6)<=0,N(AG6)=0,N(L6)=0),"",MIN(L6,AG6/AO6)) -> 20.723684 | AQ6: =IF(OR(AP6="",N(O6)=0),"",AP6/O6-1) -> -0.0060583112 | AR6: =IF(OR(AQ6="",N(O6)=0),"",AQ6+AG6/O6) -> 0.088366149 | AS6: =IF(OR(AR6="",N(AJ6)=0),"",AR6-AJ6) -> -0.11043797 | AT6: 25 | AU6: 1.96875 | AV6: =IF(N(AT6)>0,AT6,L6) -> 25 | AW6: =IF(AND(N(M6)>0,N(AV6)>0),M6*AV6,IF(N(AU6)>0,AU6,N6)) -> 1.96875 | AX6: =IF(N(AN6)=0,"",AN6+IF(I6="yes",AN6*Inputs!$B$10*Inputs!$B$9,0)+IFERROR(INDEX(Inputs!$B$13:$B$15,MATCH(G6,Inputs!$A$13:$A$15,0)),0)+IFERROR(INDEX(Inputs!$B$18:$B$24,MATCH(H6,Inputs!$A$18:$A$24,0)),0)) -> 0.095 | AY6: =IF(OR(N(AX6)<=0,N(AW6)=0,N(AV6)=0),"",MIN(AV6,AW6/AX6)) -> 20.723684 | AZ6: =IF(OR(AY6="",N(O6)=0),"",AY6/O6-1) -> -0.0060583112 | BA6: =IF(OR(AZ6="",N(O6)=0),"",AZ6+AW6/O6) -> 0.088366149 | BB6: =IF(OR(BA6="",N(AR6)=0),"",BA6-AR6) -> 0 | BC6: =IF(OR(BA6="",N(U6)=0),"",BA6-U6) -> -0.11043797
A7: A-C | B7: 19 | C7: ABR-D | D7: ABR | E7: ARBOR REALTY TRUST INC | F7: 966 | G7: PREFERRED | H7: FIXED | I7: no | J7: Q | K7: 4 | L7: 25 | M7: 0.06375 | N7: 1.59375 | O7: 15.94 | P7: OK | Q7: 0.1 | R7: 0.1 | S7: 15.9375 | T7: -0.00015683814 | U7: 0.099827478 | V7: 0 | W7: =IF(N(Q7)=0,"",Q7+IF(I7="yes",Q7*Inputs!$B$10*Inputs!$B$9,0)+V7) -> 0.1 | X7: =IF(OR(N(W7)<=0,N(N7)=0,N(L7)=0),"",MIN(L7,N7/W7)) -> 15.9375 | Y7: =IF(OR(X7="",N(O7)=0),"",X7/O7-1) -> -0.00015683814 | Z7: =IF(OR(Y7="",N(O7)=0),"",Y7+N7/O7) -> 0.099827478 | AA7: =IF(OR(Z7="",N(U7)=0),"",Z7-U7) -> 0 | AB7: =IF(N(Q7)=0,"",Q7+IF(I7="yes",Q7*Inputs!$B$10*Inputs!$B$9,0)+IFERROR(INDEX(Inputs!$B$13:$B$15,MATCH(G7,Inputs!$A$13:$A$15,0)),0)+IFERROR(INDEX(Inputs!$B$18:$B$24,MATCH(H7,Inputs!$A$18:$A$24,0)),0)) -> 0.1 | AC7: =IF(OR(N(AB7)<=0,N(N7)=0,N(L7)=0),"",MIN(L7,N7/AB7)) -> 15.9375 | AD7: =IF(OR(AC7="",N(O7)=0),"",AC7/O7-1) -> -0.00015683814 | AE7: =IF(OR(AD7="",N(O7)=0),"",AD7+N7/O7) -> 0.099827478 | AF7: =IF(OR(AE7="",N(Z7)=0),"",AE7-Z7) -> 0 | AG7: =IF(AND(N(M7)>0,N(L7)>0),M7*L7,N7) -> 1.59375 | AH7: =IF(OR(N(AB7)<=0,N(AG7)=0,N(L7)=0),"",MIN(L7,AG7/AB7)) -> 15.9375 | AI7: =IF(OR(AH7="",N(O7)=0),"",AH7/O7-1) -> -0.00015683814 | AJ7: =IF(OR(AI7="",N(O7)=0),"",AI7+AG7/O7) -> 0.099827478 | AK7: =IF(OR(AJ7="",N(AE7)=0),"",AJ7-AE7) -> 0 | AL7: =IF(N(F7)=0,"",INDEX(Inputs!$B$28:$B$32,IFERROR(MATCH(F7,Inputs!$A$28:$A$32,1),0)+1)) -> 0.09 | AN7: =IF(N(AM7)>0,AM7,AL7) -> 0.09 | AO7: =IF(N(AN7)=0,"",AN7+IF(I7="yes",AN7*Inputs!$B$10*Inputs!$B$9,0)+IFERROR(INDEX(Inputs!$B$13:$B$15,MATCH(G7,Inputs!$A$13:$A$15,0)),0)+IFERROR(INDEX(Inputs!$B$18:$B$24,MATCH(H7,Inputs!$A$18:$A$24,0)),0)) -> 0.09 | AP7: =IF(OR(N(AO7)<=0,N(AG7)=0,N(L7)=0),"",MIN(L7,AG7/AO7)) -> 17.708333 | AQ7: =IF(OR(AP7="",N(O7)=0),"",AP7/O7-1) -> 0.11093685 | AR7: =IF(OR(AQ7="",N(O7)=0),"",AQ7+AG7/O7) -> 0.21092116 | AS7: =IF(OR(AR7="",N(AJ7)=0),"",AR7-AJ7) -> 0.11109368 | AT7: 25 | AU7: 1.59375 | AV7: =IF(N(AT7)>0,AT7,L7) -> 25 | AW7: =IF(AND(N(M7)>0,N(AV7)>0),M7*AV7,IF(N(AU7)>0,AU7,N7)) -> 1.59375 | AX7: =IF(N(AN7)=0,"",AN7+IF(I7="yes",AN7*Inputs!$B$10*Inputs!$B$9,0)+IFERROR(INDEX(Inputs!$B$13:$B$15,MATCH(G7,Inputs!$A$13:$A$15,0)),0)+IFERROR(INDEX(Inputs!$B$18:$B$24,MATCH(H7,Inputs!$A$18:$A$24,0)),0)) -> 0.09 | AY7: =IF(OR(N(AX7)<=0,N(AW7)=0,N(AV7)=0),"",MIN(AV7,AW7/AX7)) -> 17.708333 | AZ7: =IF(OR(AY7="",N(O7)=0),"",AY7/O7-1) -> 0.11093685 | BA7: =IF(OR(AZ7="",N(O7)=0),"",AZ7+AW7/O7) -> 0.21092116 | BB7: =IF(OR(BA7="",N(AR7)=0),"",BA7-AR7) -> 0 | BC7: =IF(OR(BA7="",N(U7)=0),"",BA7-U7) -> 0.11109368
A8: A-C | B8: 20 | C8: ABR-E | D8: ABR | E8: ARBOR REALTY TRUST INC | F8: 966 | G8: PREFERRED | H8: FIXED | I8: no | J8: Q | K8: 4 | L8: 25 | M8: 0.0625 | N8: 1.5625 | O8: 15.75 | P8: OK | Q8: 0.1 | R8: 0.1 | S8: 15.625 | T8: -0.0079365079 | U8: 0.091269841 | V8: 0 | W8: =IF(N(Q8)=0,"",Q8+IF(I8="yes",Q8*Inputs!$B$10*Inputs!$B$9,0)+V8) -> 0.1 | X8: =IF(OR(N(W8)<=0,N(N8)=0,N(L8)=0),"",MIN(L8,N8/W8)) -> 15.625 | Y8: =IF(OR(X8="",N(O8)=0),"",X8/O8-1) -> -0.0079365079 | Z8: =IF(OR(Y8="",N(O8)=0),"",Y8+N8/O8) -> 0.091269841 | AA8: =IF(OR(Z8="",N(U8)=0),"",Z8-U8) -> 0 | AB8: =IF(N(Q8)=0,"",Q8+IF(I8="yes",Q8*Inputs!$B$10*Inputs!$B$9,0)+IFERROR(INDEX(Inputs!$B$13:$B$15,MATCH(G8,Inputs!$A$13:$A$15,0)),0)+IFERROR(INDEX(Inputs!$B$18:$B$24,MATCH(H8,Inputs!$A$18:$A$24,0)),0)) -> 0.1 | AC8: =IF(OR(N(AB8)<=0,N(N8)=0,N(L8)=0),"",MIN(L8,N8/AB8)) -> 15.625 | AD8: =IF(OR(AC8="",N(O8)=0),"",AC8/O8-1) -> -0.0079365079 | AE8: =IF(OR(AD8="",N(O8)=0),"",AD8+N8/O8) -> 0.091269841 | AF8: =IF(OR(AE8="",N(Z8)=0),"",AE8-Z8) -> 0 | AG8: =IF(AND(N(M8)>0,N(L8)>0),M8*L8,N8) -> 1.5625 | AH8: =IF(OR(N(AB8)<=0,N(AG8)=0,N(L8)=0),"",MIN(L8,AG8/AB8)) -> 15.625 | AI8: =IF(OR(AH8="",N(O8)=0),"",AH8/O8-1) -> -0.0079365079 | AJ8: =IF(OR(AI8="",N(O8)=0),"",AI8+AG8/O8) -> 0.091269841 | AK8: =IF(OR(AJ8="",N(AE8)=0),"",AJ8-AE8) -> 0 | AL8: =IF(N(F8)=0,"",INDEX(Inputs!$B$28:$B$32,IFERROR(MATCH(F8,Inputs!$A$28:$A$32,1),0)+1)) -> 0.09 | AN8: =IF(N(AM8)>0,AM8,AL8) -> 0.09 | AO8: =IF(N(AN8)=0,"",AN8+IF(I8="yes",AN8*Inputs!$B$10*Inputs!$B$9,0)+IFERROR(INDEX(Inputs!$B$13:$B$15,MATCH(G8,Inputs!$A$13:$A$15,0)),0)+IFERROR(INDEX(Inputs!$B$18:$B$24,MATCH(H8,Inputs!$A$18:$A$24,0)),0)) -> 0.09 | AP8: =IF(OR(N(AO8)<=0,N(AG8)=0,N(L8)=0),"",MIN(L8,AG8/AO8)) -> 17.361111 | AQ8: =IF(OR(AP8="",N(O8)=0),"",AP8/O8-1) -> 0.10229277 | AR8: =IF(OR(AQ8="",N(O8)=0),"",AQ8+AG8/O8) -> 0.20149912 | AS8: =IF(OR(AR8="",N(AJ8)=0),"",AR8-AJ8) -> 0.11022928 | AT8: 25 | AU8: 1.5625 | AV8: =IF(N(AT8)>0,AT8,L8) -> 25 | AW8: =IF(AND(N(M8)>0,N(AV8)>0),M8*AV8,IF(N(AU8)>0,AU8,N8)) -> 1.5625 | AX8: =IF(N(AN8)=0,"",AN8+IF(I8="yes",AN8*Inputs!$B$10*Inputs!$B$9,0)+IFERROR(INDEX(Inputs!$B$13:$B$15,MATCH(G8,Inputs!$A$13:$A$15,0)),0)+IFERROR(INDEX(Inputs!$B$18:$B$24,MATCH(H8,Inputs!$A$18:$A$24,0)),0)) -> 0.09 | AY8: =IF(OR(N(AX8)<=0,N(AW8)=0,N(AV8)=0),"",MIN(AV8,AW8/AX8)) -> 17.361111 | AZ8: =IF(OR(AY8="",N(O8)=0),"",AY8/O8-1) -> 0.10229277 | BA8: =IF(OR(AZ8="",N(O8)=0),"",AZ8+AW8/O8) -> 0.20149912 | BB8: =IF(OR(BA8="",N(AR8)=0),"",BA8-AR8) -> 0 | BC8: =IF(OR(BA8="",N(U8)=0),"",BA8-U8) -> 0.11022928
A9: A-C | B9: 21 | C9: ABR-F | D9: ABR | E9: ARBOR REALTY TRUST INC | F9: 966 | G9: PREFERRED | H9: FIXED | I9: no | J9: Q | K9: 4 | L9: 25 | M9: 0.0625 | N9: 1.5625 | O9: 22.34 | P9: OK | Q9: 0.1 | R9: 0.1 | S9: 15.625 | T9: -0.30058192 | U9: -0.23064011 | V9: 0 | W9: =IF(N(Q9)=0,"",Q9+IF(I9="yes",Q9*Inputs!$B$10*Inputs!$B$9,0)+V9) -> 0.1 | X9: =IF(OR(N(W9)<=0,N(N9)=0,N(L9)=0),"",MIN(L9,N9/W9)) -> 15.625 | Y9: =IF(OR(X9="",N(O9)=0),"",X9/O9-1) -> -0.30058192 | Z9: =IF(OR(Y9="",N(O9)=0),"",Y9+N9/O9) -> -0.23064011 | AA9: =IF(OR(Z9="",N(U9)=0),"",Z9-U9) -> 0 | AB9: =IF(N(Q9)=0,"",Q9+IF(I9="yes",Q9*Inputs!$B$10*Inputs!$B$9,0)+IFERROR(INDEX(Inputs!$B$13:$B$15,MATCH(G9,Inputs!$A$13:$A$15,0)),0)+IFERROR(INDEX(Inputs!$B$18:$B$24,MATCH(H9,Inputs!$A$18:$A$24,0)),0)) -> 0.1 | AC9: =IF(OR(N(AB9)<=0,N(N9)=0,N(L9)=0),"",MIN(L9,N9/AB9)) -> 15.625 | AD9: =IF(OR(AC9="",N(O9)=0),"",AC9/O9-1) -> -0.30058192 | AE9: =IF(OR(AD9="",N(O9)=0),"",AD9+N9/O9) -> -0.23064011 | AF9: =IF(OR(AE9="",N(Z9)=0),"",AE9-Z9) -> 0 | AG9: =IF(AND(N(M9)>0,N(L9)>0),M9*L9,N9) -> 1.5625 | AH9: =IF(OR(N(AB9)<=0,N(AG9)=0,N(L9)=0),"",MIN(L9,AG9/AB9)) -> 15.625 | AI9: =IF(OR(AH9="",N(O9)=0),"",AH9/O9-1) -> -0.30058192 | AJ9: =IF(OR(AI9="",N(O9)=0),"",AI9+AG9/O9) -> -0.23064011 | AK9: =IF(OR(AJ9="",N(AE9)=0),"",AJ9-AE9) -> 0 | AL9: =IF(N(F9)=0,"",INDEX(Inputs!$B$28:$B$32,IFERROR(MATCH(F9,Inputs!$A$28:$A$32,1),0)+1)) -> 0.09 | AN9: =IF(N(AM9)>0,AM9,AL9) -> 0.09 | AO9: =IF(N(AN9)=0,"",AN9+IF(I9="yes",AN9*Inputs!$B$10*Inputs!$B$9,0)+IFERROR(INDEX(Inputs!$B$13:$B$15,MATCH(G9,Inputs!$A$13:$A$15,0)),0)+IFERROR(INDEX(Inputs!$B$18:$B$24,MATCH(H9,Inputs!$A$18:$A$24,0)),0)) -> 0.09 | AP9: =IF(OR(N(AO9)<=0,N(AG9)=0,N(L9)=0),"",MIN(L9,AG9/AO9)) -> 17.361111 | AQ9: =IF(OR(AP9="",N(O9)=0),"",AP9/O9-1) -> -0.2228688 | AR9: =IF(OR(AQ9="",N(O9)=0),"",AQ9+AG9/O9) -> -0.15292699 | AS9: =IF(OR(AR9="",N(AJ9)=0),"",AR9-AJ9) -> 0.07771312 | AT9: 25 | AU9: 1.5625 | AV9: =IF(N(AT9)>0,AT9,L9) -> 25 | AW9: =IF(AND(N(M9)>0,N(AV9)>0),M9*AV9,IF(N(AU9)>0,AU9,N9)) -> 1.5625 | AX9: =IF(N(AN9)=0,"",AN9+IF(I9="yes",AN9*Inputs!$B$10*Inputs!$B$9,0)+IFERROR(INDEX(Inputs!$B$13:$B$15,MATCH(G9,Inputs!$A$13:$A$15,0)),0)+IFERROR(INDEX(Inputs!$B$18:$B$24,MATCH(H9,Inputs!$A$18:$A$24,0)),0)) -> 0.09 | AY9: =IF(OR(N(AX9)<=0,N(AW9)=0,N(AV9)=0),"",MIN(AV9,AW9/AX9)) -> 17.361111 | AZ9: =IF(OR(AY9="",N(O9)=0),"",AY9/O9-1) -> -0.2228688 | BA9: =IF(OR(AZ9="",N(O9)=0),"",AZ9+AW9/O9) -> -0.15292699 | BB9: =IF(OR(BA9="",N(AR9)=0),"",BA9-AR9) -> 0 | BC9: =IF(OR(BA9="",N(U9)=0),"",BA9-U9) -> 0.07771312
A10: A-C | B10: 24 | C10: ACGLN | D10: ACGL | E10: ARCH CAP GROUP LTD | F10: 33900 | G10: PREFERRED | H10: FIXED | I10: yes | J10: Q | K10: 4 | L10: 25 | M10: 0.0455 | N10: 1.1375 | O10: 16.01 | P10: OK | Q10: 0.08 | R10: 0.076 | S10: 14.967105 | T10: -0.065140208 | U10: 0.0059091357 | V10: 0 | W10: =IF(N(Q10)=0,"",Q10+IF(I10="yes",Q10*Inputs!$B$10*Inputs!$B$9,0)+V10) -> 0.076 | X10: =IF(OR(N(W10)<=0,N(N10)=0,N(L10)=0),"",MIN(L10,N10/W10)) -> 14.967105 | Y10: =IF(OR(X10="",N(O10)=0),"",X10/O10-1) -> -0.065140208 | Z10: =IF(OR(Y10="",N(O10)=0),"",Y10+N10/O10) -> 0.0059091357 | AA10: =IF(OR(Z10="",N(U10)=0),"",Z10-U10) -> 0 | AB10: =IF(N(Q10)=0,"",Q10+IF(I10="yes",Q10*Inputs!$B$10*Inputs!$B$9,0)+IFERROR(INDEX(Inputs!$B$13:$B$15,MATCH(G10,Inputs!$A$13:$A$15,0)),0)+IFERROR(INDEX(Inputs!$B$18:$B$24,MATCH(H10,Inputs!$A$18:$A$24,0)),0)) -> 0.076 | AC10: =IF(OR(N(AB10)<=0,N(N10)=0,N(L10)=0),"",MIN(L10,N10/AB10)) -> 14.967105 | AD10: =IF(OR(AC10="",N(O10)=0),"",AC10/O10-1) -> -0.065140208 | AE10: =IF(OR(AD10="",N(O10)=0),"",AD10+N10/O10) -> 0.0059091357 | AF10: =IF(OR(AE10="",N(Z10)=0),"",AE10-Z10) -> 0 | AG10: =IF(AND(N(M10)>0,N(L10)>0),M10*L10,N10) -> 1.1375 | AH10: =IF(OR(N(AB10)<=0,N(AG10)=0,N(L10)=0),"",MIN(L10,AG10/AB10)) -> 14.967105 | AI10: =IF(OR(AH10="",N(O10)=0),"",AH10/O10-1) -> -0.065140208 | AJ10: =IF(OR(AI10="",N(O10)=0),"",AI10+AG10/O10) -> 0.0059091357 | AK10: =IF(OR(AJ10="",N(AE10)=0),"",AJ10-AE10) -> 0 | AL10: =IF(N(F10)=0,"",INDEX(Inputs!$B$28:$B$32,IFERROR(MATCH(F10,Inputs!$A$28:$A$32,1),0)+1)) -> 0.075 | AN10: =IF(N(AM10)>0,AM10,AL10) -> 0.075 | AO10: =IF(N(AN10)=0,"",AN10+IF(I10="yes",AN10*Inputs!$B$10*Inputs!$B$9,0)+IFERROR(INDEX(Inputs!$B$13:$B$15,MATCH(G10,Inputs!$A$13:$A$15,0)),0)+IFERROR(INDEX(Inputs!$B$18:$B$24,MATCH(H10,Inputs!$A$18:$A$24,0)),0)) -> 0.07125 | AP10: =IF(OR(N(AO10)<=0,N(AG10)=0,N(L10)=0),"",MIN(L10,AG10/AO10)) -> 15.964912 | AQ10: =IF(OR(AP10="",N(O10)=0),"",AP10/O10-1) -> -0.0028162223 | AR10: =IF(OR(AQ10="",N(O10)=0),"",AQ10+AG10/O10) -> 0.068233122 | AS10: =IF(OR(AR10="",N(AJ10)=0),"",AR10-AJ10) -> 0.062323986 | AT10: 25 | AU10: 1.1375 | AV10: =IF(N(AT10)>0,AT10,L10) -> 25 | AW10: =IF(AND(N(M10)>0,N(AV10)>0),M10*AV10,IF(N(AU10)>0,AU10,N10)) -> 1.1375 | AX10: =IF(N(AN10)=0,"",AN10+IF(I10="yes",AN10*Inputs!$B$10*Inputs!$B$9,0)+IFERROR(INDEX(Inputs!$B$13:$B$15,MATCH(G10,Inputs!$A$13:$A$15,0)),0)+IFERROR(INDEX(Inputs!$B$18:$B$24,MATCH(H10,Inputs!$A$18:$A$24,0)),0)) -> 0.07125 | AY10: =IF(OR(N(AX10)<=0,N(AW10)=0,N(AV10)=0),"",MIN(AV10,AW10/AX10)) -> 15.964912 | AZ10: =IF(OR(AY10="",N(O10)=0),"",AY10/O10-1) -> -0.0028162223 | BA10: =IF(OR(AZ10="",N(O10)=0),"",AZ10+AW10/O10) -> 0.068233122 | BB10: =IF(OR(BA10="",N(AR10)=0),"",BA10-AR10) -> 0 | BC10: =IF(OR(BA10="",N(U10)=0),"",BA10-U10) -> 0.062323986
A11: A-C | B11: 25 | C11: ACGLO | D11: ACGL | E11: ARCH CAP GROUP LTD | F11: 33900 | G11: PREFERRED | H11: FIXED | I11: yes | J11: Q | K11: 4 | L11: 25 | M11: 0.0545 | N11: 1.3625 | O11: 18.96 | P11: OK | Q11: 0.08 | R11: 0.076 | S11: 17.927632 | T11: -0.054449811 | U11: 0.017412003 | V11: 0 | W11: =IF(N(Q11)=0,"",Q11+IF(I11="yes",Q11*Inputs!$B$10*Inputs!$B$9,0)+V11) -> 0.076 | X11: =IF(OR(N(W11)<=0,N(N11)=0,N(L11)=0),"",MIN(L11,N11/W11)) -> 17.927632 | Y11: =IF(OR(X11="",N(O11)=0),"",X11/O11-1) -> -0.054449811 | Z11: =IF(OR(Y11="",N(O11)=0),"",Y11+N11/O11) -> 0.017412003 | AA11: =IF(OR(Z11="",N(U11)=0),"",Z11-U11) -> 0 | AB11: =IF(N(Q11)=0,"",Q11+IF(I11="yes",Q11*Inputs!$B$10*Inputs!$B$9,0)+IFERROR(INDEX(Inputs!$B$13:$B$15,MATCH(G11,Inputs!$A$13:$A$15,0)),0)+IFERROR(INDEX(Inputs!$B$18:$B$24,MATCH(H11,Inputs!$A$18:$A$24,0)),0)) -> 0.076 | AC11: =IF(OR(N(AB11)<=0,N(N11)=0,N(L11)=0),"",MIN(L11,N11/AB11)) -> 17.927632 | AD11: =IF(OR(AC11="",N(O11)=0),"",AC11/O11-1) -> -0.054449811 | AE11: =IF(OR(AD11="",N(O11)=0),"",AD11+N11/O11) -> 0.017412003 | AF11: =IF(OR(AE11="",N(Z11)=0),"",AE11-Z11) -> 0 | AG11: =IF(AND(N(M11)>0,N(L11)>0),M11*L11,N11) -> 1.3625 | AH11: =IF(OR(N(AB11)<=0,N(AG11)=0,N(L11)=0),"",MIN(L11,AG11/AB11)) -> 17.927632 | AI11: =IF(OR(AH11="",N(O11)=0),"",AH11/O11-1) -> -0.054449811 | AJ11: =IF(OR(AI11="",N(O11)=0),"",AI11+AG11/O11) -> 0.017412003 | AK11: =IF(OR(AJ11="",N(AE11)=0),"",AJ11-AE11) -> 0 | AL11: =IF(N(F11)=0,"",INDEX(Inputs!$B$28:$B$32,IFERROR(MATCH(F11,Inputs!$A$28:$A$32,1),0)+1)) -> 0.075 | AN11: =IF(N(AM11)>0,AM11,AL11) -> 0.075 | AO11: =IF(N(AN11)=0,"",AN11+IF(I11="yes",AN11*Inputs!$B$10*Inputs!$B$9,0)+IFERROR(INDEX(Inputs!$B$13:$B$15,MATCH(G11,Inputs!$A$13:$A$15,0)),0)+IFERROR(INDEX(Inputs!$B$18:$B$24,MATCH(H11,Inputs!$A$18:$A$24,0)),0)) -> 0.07125 | AP11: =IF(OR(N(AO11)<=0,N(AG11)=0,N(L11)=0),"",MIN(L11,AG11/AO11)) -> 19.122807 | AQ11: =IF(OR(AP11="",N(O11)=0),"",AP11/O11-1) -> 0.008586868 | AR11: =IF(OR(AQ11="",N(O11)=0),"",AQ11+AG11/O11) -> 0.080448682 | AS11: =IF(OR(AR11="",N(AJ11)=0),"",AR11-AJ11) -> 0.063036679 | AT11: 25 | AU11: 1.36 | AV11: =IF(N(AT11)>0,AT11,L11) -> 25 | AW11: =IF(AND(N(M11)>0,N(AV11)>0),M11*AV11,IF(N(AU11)>0,AU11,N11)) -> 1.3625 | AX11: =IF(N(AN11)=0,"",AN11+IF(I11="yes",AN11*Inputs!$B$10*Inputs!$B$9,0)+IFERROR(INDEX(Inputs!$B$13:$B$15,MATCH(G11,Inputs!$A$13:$A$15,0)),0)+IFERROR(INDEX(Inputs!$B$18:$B$24,MATCH(H11,Inputs!$A$18:$A$24,0)),0)) -> 0.07125 | AY11: =IF(OR(N(AX11)<=0,N(AW11)=0,N(AV11)=0),"",MIN(AV11,AW11/AX11)) -> 19.122807 | AZ11: =IF(OR(AY11="",N(O11)=0),"",AY11/O11-1) -> 0.008586868 | BA11: =IF(OR(AZ11="",N(O11)=0),"",AZ11+AW11/O11) -> 0.080448682 | BB11: =IF(OR(BA11="",N(AR11)=0),"",BA11-AR11) -> 0 | BC11: =IF(OR(BA11="",N(U11)=0),"",BA11-U11) -> 0.063036679
A12: A-C | B12: 28 | C12: ADC-A | D12: ADC | E12: AGREE RLTY CORP | F12: 9300 | G12: PREFERRED | H12: FIXED | I12: no | J12: M | K12: 12 | L12: 25 | M12: 0.0425 | N12: 1.0625 | O12: 16.86 | P12: OK | Q12: 0.08 | R12: 0.08 | S12: 13.28125 | T12: -0.21226275 | U12: -0.14924377 | V12: 0 | W12: =IF(N(Q12)=0,"",Q12+IF(I12="yes",Q12*Inputs!$B$10*Inputs!$B$9,0)+V12) -> 0.08 | X12: =IF(OR(N(W12)<=0,N(N12)=0,N(L12)=0),"",MIN(L12,N12/W12)) -> 13.28125 | Y12: =IF(OR(X12="",N(O12)=0),"",X12/O12-1) -> -0.21226275 | Z12: =IF(OR(Y12="",N(O12)=0),"",Y12+N12/O12) -> -0.14924377 | AA12: =IF(OR(Z12="",N(U12)=0),"",Z12-U12) -> 0 | AB12: =IF(N(Q12)=0,"",Q12+IF(I12="yes",Q12*Inputs!$B$10*Inputs!$B$9,0)+IFERROR(INDEX(Inputs!$B$13:$B$15,MATCH(G12,Inputs!$A$13:$A$15,0)),0)+IFERROR(INDEX(Inputs!$B$18:$B$24,MATCH(H12,Inputs!$A$18:$A$24,0)),0)) -> 0.08 | AC12: =IF(OR(N(AB12)<=0,N(N12)=0,N(L12)=0),"",MIN(L12,N12/AB12)) -> 13.28125 | AD12: =IF(OR(AC12="",N(O12)=0),"",AC12/O12-1) -> -0.21226275 | AE12: =IF(OR(AD12="",N(O12)=0),"",AD12+N12/O12) -> -0.14924377 | AF12: =IF(OR(AE12="",N(Z12)=0),"",AE12-Z12) -> 0 | AG12: =IF(AND(N(M12)>0,N(L12)>0),M12*L12,N12) -> 1.0625 | AH12: =IF(OR(N(AB12)<=0,N(AG12)=0,N(L12)=0),"",MIN(L12,AG12/AB12)) -> 13.28125 | AI12: =IF(OR(AH12="",N(O12)=0),"",AH12/O12-1) -> -0.21226275 | AJ12: =IF(OR(AI12="",N(O12)=0),"",AI12+AG12/O12) -> -0.14924377 | AK12: =IF(OR(AJ12="",N(AE12)=0),"",AJ12-AE12) -> 0 | AL12: =IF(N(F12)=0,"",INDEX(Inputs!$B$28:$B$32,IFERROR(MATCH(F12,Inputs!$A$28:$A$32,1),0)+1)) -> 0.08 | AN12: =IF(N(AM12)>0,AM12,AL12) -> 0.08 | AO12: =IF(N(AN12)=0,"",AN12+IF(I12="yes",AN12*Inputs!$B$10*Inputs!$B$9,0)+IFERROR(INDEX(Inputs!$B$13:$B$15,MATCH(G12,Inputs!$A$13:$A$15,0)),0)+IFERROR(INDEX(Inputs!$B$18:$B$24,MATCH(H12,Inputs!$A$18:$A$24,0)),0)) -> 0.08 | AP12: =IF(OR(N(AO12)<=0,N(AG12)=0,N(L12)=0),"",MIN(L12,AG12/AO12)) -> 13.28125 | AQ12: =IF(OR(AP12="",N(O12)=0),"",AP12/O12-1) -> -0.21226275 | AR12: =IF(OR(AQ12="",N(O12)=0),"",AQ12+AG12/O12) -> -0.14924377 | AS12: =IF(OR(AR12="",N(AJ12)=0),"",AR12-AJ12) -> 0 | AT12: 25 | AU12: 1.0625 | AV12: =IF(N(AT12)>0,AT12,L12) -> 25 | AW12: =IF(AND(N(M12)>0,N(AV12)>0),M12*AV12,IF(N(AU12)>0,AU12,N12)) -> 1.0625 | AX12: =IF(N(AN12)=0,"",AN12+IF(I12="yes",AN12*Inputs!$B$10*Inputs!$B$9,0)+IFERROR(INDEX(Inputs!$B$13:$B$15,MATCH(G12,Inputs!$A$13:$A$15,0)),0)+IFERROR(INDEX(Inputs!$B$18:$B$24,MATCH(H12,Inputs!$A$18:$A$24,0)),0)) -> 0.08 | AY12: =IF(OR(N(AX12)<=0,N(AW12)=0,N(AV12)=0),"",MIN(AV12,AW12/AX12)) -> 13.28125 | AZ12: =IF(OR(AY12="",N(O12)=0),"",AY12/O12-1) -> -0.21226275 | BA12: =IF(OR(AZ12="",N(O12)=0),"",AZ12+AW12/O12) -> -0.14924377 | BB12: =IF(OR(BA12="",N(AR12)=0),"",BA12-AR12) -> 0 | BC12: =IF(OR(BA12="",N(U12)=0),"",BA12-U12) -> 0
A13: A-C | B13: 32 | C13: AILIH | D13: AEE | E13: AMEREN CORP | F13: 30100 | G13: PREFERRED | H13: FIXED | I13: yes | J13: Q | K13: 4 | L13: 50 | M13: 0.0408 | N13: 2.04 | O13: 66 | P13: OK | Q13: 0.08 | R13: 0.076 | S13: 26.842105 | T13: -0.59330144 | U13: -0.56239234 | V13: 0 | W13: =IF(N(Q13)=0,"",Q13+IF(I13="yes",Q13*Inputs!$B$10*Inputs!$B$9,0)+V13) -> 0.076 | X13: =IF(OR(N(W13)<=0,N(N13)=0,N(L13)=0),"",MIN(L13,N13/W13)) -> 26.842105 | Y13: =IF(OR(X13="",N(O13)=0),"",X13/O13-1) -> -0.59330144 | Z13: =IF(OR(Y13="",N(O13)=0),"",Y13+N13/O13) -> -0.56239234 | AA13: =IF(OR(Z13="",N(U13)=0),"",Z13-U13) -> 0 | AB13: =IF(N(Q13)=0,"",Q13+IF(I13="yes",Q13*Inputs!$B$10*Inputs!$B$9,0)+IFERROR(INDEX(Inputs!$B$13:$B$15,MATCH(G13,Inputs!$A$13:$A$15,0)),0)+IFERROR(INDEX(Inputs!$B$18:$B$24,MATCH(H13,Inputs!$A$18:$A$24,0)),0)) -> 0.076 | AC13: =IF(OR(N(AB13)<=0,N(N13)=0,N(L13)=0),"",MIN(L13,N13/AB13)) -> 26.842105 | AD13: =IF(OR(AC13="",N(O13)=0),"",AC13/O13-1) -> -0.59330144 | AE13: =IF(OR(AD13="",N(O13)=0),"",AD13+N13/O13) -> -0.56239234 | AF13: =IF(OR(AE13="",N(Z13)=0),"",AE13-Z13) -> 0 | AG13: =IF(AND(N(M13)>0,N(L13)>0),M13*L13,N13) -> 2.04 | AH13: =IF(OR(N(AB13)<=0,N(AG13)=0,N(L13)=0),"",MIN(L13,AG13/AB13)) -> 26.842105 | AI13: =IF(OR(AH13="",N(O13)=0),"",AH13/O13-1) -> -0.59330144 | AJ13: =IF(OR(AI13="",N(O13)=0),"",AI13+AG13/O13) -> -0.56239234 | AK13: =IF(OR(AJ13="",N(AE13)=0),"",AJ13-AE13) -> 0 | AL13: =IF(N(F13)=0,"",INDEX(Inputs!$B$28:$B$32,IFERROR(MATCH(F13,Inputs!$A$28:$A$32,1),0)+1)) -> 0.075 | AN13: =IF(N(AM13)>0,AM13,AL13) -> 0.075 | AO13: =IF(N(AN13)=0,"",AN13+IF(I13="yes",AN13*Inputs!$B$10*Inputs!$B$9,0)+IFERROR(INDEX(Inputs!$B$13:$B$15,MATCH(G13,Inputs!$A$13:$A$15,0)),0)+IFERROR(INDEX(Inputs!$B$18:$B$24,MATCH(H13,Inputs!$A$18:$A$24,0)),0)) -> 0.07125 | AP13: =IF(OR(N(AO13)<=0,N(AG13)=0,N(L13)=0),"",MIN(L13,AG13/AO13)) -> 28.631579 | AQ13: =IF(OR(AP13="",N(O13)=0),"",AP13/O13-1) -> -0.5661882 | AR13: =IF(OR(AQ13="",N(O13)=0),"",AQ13+AG13/O13) -> -0.53527911 | AS13: =IF(OR(AR13="",N(AJ13)=0),"",AR13-AJ13) -> 0.027113238 | AT13: 100 | AU13: 4.08 | AV13: =IF(N(AT13)>0,AT13,L13) -> 100 | AW13: =IF(AND(N(M13)>0,N(AV13)>0),M13*AV13,IF(N(AU13)>0,AU13,N13)) -> 4.08 | AX13: =IF(N(AN13)=0,"",AN13+IF(I13="yes",AN13*Inputs!$B$10*Inputs!$B$9,0)+IFERROR(INDEX(Inputs!$B$13:$B$15,MATCH(G13,Inputs!$A$13:$A$15,0)),0)+IFERROR(INDEX(Inputs!$B$18:$B$24,MATCH(H13,Inputs!$A$18:$A$24,0)),0)) -> 0.07125 | AY13: =IF(OR(N(AX13)<=0,N(AW13)=0,N(AV13)=0),"",MIN(AV13,AW13/AX13)) -> 57.263158 | AZ13: =IF(OR(AY13="",N(O13)=0),"",AY13/O13-1) -> -0.1323764 | BA13: =IF(OR(AZ13="",N(O13)=0),"",AZ13+AW13/O13) -> -0.070558214 | BB13: =IF(OR(BA13="",N(AR13)=0),"",BA13-AR13) -> 0.46472089 | BC13: =IF(OR(BA13="",N(U13)=0),"",BA13-U13) -> 0.49183413 | BD13: PAR MISMATCH
A14: A-C | B14: 33 | C14: AILIM | D14: AEE | E14: AMEREN CORP | F14: 30100 | G14: PREFERRED | H14: FIXED | I14: yes | J14: Q | K14: 4 | L14: 50 | M14: 0.047 | N14: 2.35 | O14: 77 | P14: OK | Q14: 0.08 | R14: 0.076 | S14: 30.921053 | T14: -0.59842789 | U14: -0.56790841 | V14: 0 | W14: =IF(N(Q14)=0,"",Q14+IF(I14="yes",Q14*Inputs!$B$10*Inputs!$B$9,0)+V14) -> 0.076 | X14: =IF(OR(N(W14)<=0,N(N14)=0,N(L14)=0),"",MIN(L14,N14/W14)) -> 30.921053 | Y14: =IF(OR(X14="",N(O14)=0),"",X14/O14-1) -> -0.59842789 | Z14: =IF(OR(Y14="",N(O14)=0),"",Y14+N14/O14) -> -0.56790841 | AA14: =IF(OR(Z14="",N(U14)=0),"",Z14-U14) -> 0 | AB14: =IF(N(Q14)=0,"",Q14+IF(I14="yes",Q14*Inputs!$B$10*Inputs!$B$9,0)+IFERROR(INDEX(Inputs!$B$13:$B$15,MATCH(G14,Inputs!$A$13:$A$15,0)),0)+IFERROR(INDEX(Inputs!$B$18:$B$24,MATCH(H14,Inputs!$A$18:$A$24,0)),0)) -> 0.076 | AC14: =IF(OR(N(AB14)<=0,N(N14)=0,N(L14)=0),"",MIN(L14,N14/AB14)) -> 30.921053 | AD14: =IF(OR(AC14="",N(O14)=0),"",AC14/O14-1) -> -0.59842789 | AE14: =IF(OR(AD14="",N(O14)=0),"",AD14+N14/O14) -> -0.56790841 | AF14: =IF(OR(AE14="",N(Z14)=0),"",AE14-Z14) -> 0 | AG14: =IF(AND(N(M14)>0,N(L14)>0),M14*L14,N14) -> 2.35 | AH14: =IF(OR(N(AB14)<=0,N(AG14)=0,N(L14)=0),"",MIN(L14,AG14/AB14)) -> 30.921053 | AI14: =IF(OR(AH14="",N(O14)=0),"",AH14/O14-1) -> -0.59842789 | AJ14: =IF(OR(AI14="",N(O14)=0),"",AI14+AG14/O14) -> -0.56790841 | AK14: =IF(OR(AJ14="",N(AE14)=0),"",AJ14-AE14) -> 0 | AL14: =IF(N(F14)=0,"",INDEX(Inputs!$B$28:$B$32,IFERROR(MATCH(F14,Inputs!$A$28:$A$32,1),0)+1)) -> 0.075 | AN14: =IF(N(AM14)>0,AM14,AL14) -> 0.075 | AO14: =IF(N(AN14)=0,"",AN14+IF(I14="yes",AN14*Inputs!$B$10*Inputs!$B$9,0)+IFERROR(INDEX(Inputs!$B$13:$B$15,MATCH(G14,Inputs!$A$13:$A$15,0)),0)+IFERROR(INDEX(Inputs!$B$18:$B$24,MATCH(H14,Inputs!$A$18:$A$24,0)),0)) -> 0.07125 | AP14: =IF(OR(N(AO14)<=0,N(AG14)=0,N(L14)=0),"",MIN(L14,AG14/AO14)) -> 32.982456 | AQ14: =IF(OR(AP14="",N(O14)=0),"",AP14/O14-1) -> -0.57165641 | AR14: =IF(OR(AQ14="",N(O14)=0),"",AQ14+AG14/O14) -> -0.54113693 | AS14: =IF(OR(AR14="",N(AJ14)=0),"",AR14-AJ14) -> 0.026771474 | AT14: 100 | AU14: 4.7 | AV14: =IF(N(AT14)>0,AT14,L14) -> 100 | AW14: =IF(AND(N(M14)>0,N(AV14)>0),M14*AV14,IF(N(AU14)>0,AU14,N14)) -> 4.7 | AX14: =IF(N(AN14)=0,"",AN14+IF(I14="yes",AN14*Inputs!$B$10*Inputs!$B$9,0)+IFERROR(INDEX(Inputs!$B$13:$B$15,MATCH(G14,Inputs!$A$13:$A$15,0)),0)+IFERROR(INDEX(Inputs!$B$18:$B$24,MATCH(H14,Inputs!$A$18:$A$24,0)),0)) -> 0.07125 | AY14: =IF(OR(N(AX14)<=0,N(AW14)=0,N(AV14)=0),"",MIN(AV14,AW14/AX14)) -> 65.964912 | AZ14: =IF(OR(AY14="",N(O14)=0),"",AY14/O14-1) -> -0.14331283 | BA14: =IF(OR(AZ14="",N(O14)=0),"",AZ14+AW14/O14) -> -0.082273866 | BB14: =IF(OR(BA14="",N(AR14)=0),"",BA14-AR14) -> 0.45886307 | BC14: =IF(OR(BA14="",N(U14)=0),"",BA14-U14) -> 0.48563454 | BD14: PAR MISMATCH
A15: A-C | B15: 34 | C15: AILIN | D15: AEE | E15: AMEREN CORP | F15: 30100 | G15: PREFERRED | H15: FIXED | I15: yes | J15: Q | K15: 4 | L15: 50 | M15: 0.0442 | N15: 2.21 | O15: 71 | P15: OK | Q15: 0.08 | R15: 0.076 | S15: 29.078947 | T15: -0.59043736 | U15: -0.5593106 | V15: 0 | W15: =IF(N(Q15)=0,"",Q15+IF(I15="yes",Q15*Inputs!$B$10*Inputs!$B$9,0)+V15) -> 0.076 | X15: =IF(OR(N(W15)<=0,N(N15)=0,N(L15)=0),"",MIN(L15,N15/W15)) -> 29.078947 | Y15: =IF(OR(X15="",N(O15)=0),"",X15/O15-1) -> -0.59043736 | Z15: =IF(OR(Y15="",N(O15)=0),"",Y15+N15/O15) -> -0.5593106 | AA15: =IF(OR(Z15="",N(U15)=0),"",Z15-U15) -> 0 | AB15: =IF(N(Q15)=0,"",Q15+IF(I15="yes",Q15*Inputs!$B$10*Inputs!$B$9,0)+IFERROR(INDEX(Inputs!$B$13:$B$15,MATCH(G15,Inputs!$A$13:$A$15,0)),0)+IFERROR(INDEX(Inputs!$B$18:$B$24,MATCH(H15,Inputs!$A$18:$A$24,0)),0)) -> 0.076 | AC15: =IF(OR(N(AB15)<=0,N(N15)=0,N(L15)=0),"",MIN(L15,N15/AB15)) -> 29.078947 | AD15: =IF(OR(AC15="",N(O15)=0),"",AC15/O15-1) -> -0.59043736 | AE15: =IF(OR(AD15="",N(O15)=0),"",AD15+N15/O15) -> -0.5593106 | AF15: =IF(OR(AE15="",N(Z15)=0),"",AE15-Z15) -> 0 | AG15: =IF(AND(N(M15)>0,N(L15)>0),M15*L15,N15) -> 2.21 | AH15: =IF(OR(N(AB15)<=0,N(AG15)=0,N(L15)=0),"",MIN(L15,AG15/AB15)) -> 29.078947 | AI15: =IF(OR(AH15="",N(O15)=0),"",AH15/O15-1) -> -0.59043736 | AJ15: =IF(OR(AI15="",N(O15)=0),"",AI15+AG15/O15) -> -0.5593106 | AK15: =IF(OR(AJ15="",N(AE15)=0),"",AJ15-AE15) -> 0 | AL15: =IF(N(F15)=0,"",INDEX(Inputs!$B$28:$B$32,IFERROR(MATCH(F15,Inputs!$A$28:$A$32,1),0)+1)) -> 0.075 | AN15: =IF(N(AM15)>0,AM15,AL15) -> 0.075 | AO15: =IF(N(AN15)=0,"",AN15+IF(I15="yes",AN15*Inputs!$B$10*Inputs!$B$9,0)+IFERROR(INDEX(Inputs!$B$13:$B$15,MATCH(G15,Inputs!$A$13:$A$15,0)),0)+IFERROR(INDEX(Inputs!$B$18:$B$24,MATCH(H15,Inputs!$A$18:$A$24,0)),0)) -> 0.07125 | AP15: =IF(OR(N(AO15)<=0,N(AG15)=0,N(L15)=0),"",MIN(L15,AG15/AO15)) -> 31.017544 | AQ15: =IF(OR(AP15="",N(O15)=0),"",AP15/O15-1) -> -0.56313319 | AR15: =IF(OR(AQ15="",N(O15)=0),"",AQ15+AG15/O15) -> -0.53200642 | AS15: =IF(OR(AR15="",N(AJ15)=0),"",AR15-AJ15) -> 0.027304176 | AT15: 100 | AU15: 4.42 | AV15: =IF(N(AT15)>0,AT15,L15) -> 100 | AW15: =IF(AND(N(M15)>0,N(AV15)>0),M15*AV15,IF(N(AU15)>0,AU15,N15)) -> 4.42 | AX15: =IF(N(AN15)=0,"",AN15+IF(I15="yes",AN15*Inputs!$B$10*Inputs!$B$9,0)+IFERROR(INDEX(Inputs!$B$13:$B$15,MATCH(G15,Inputs!$A$13:$A$15,0)),0)+IFERROR(INDEX(Inputs!$B$18:$B$24,MATCH(H15,Inputs!$A$18:$A$24,0)),0)) -> 0.07125 | AY15: =IF(OR(N(AX15)<=0,N(AW15)=0,N(AV15)=0),"",MIN(AV15,AW15/AX15)) -> 62.035088 | AZ15: =IF(OR(AY15="",N(O15)=0),"",AY15/O15-1) -> -0.12626637 | BA15: =IF(OR(AZ15="",N(O15)=0),"",AZ15+AW15/O15) -> -0.064012849 | BB15: =IF(OR(BA15="",N(AR15)=0),"",BA15-AR15) -> 0.46799358 | BC15: =IF(OR(BA15="",N(U15)=0),"",BA15-U15) -> 0.49529775 | BD15: PAR MISMATCH
A16: A-C | B16: 35 | C16: AILIO | D16: AEE | E16: AMEREN CORP | F16: 30100 | G16: PREFERRED | H16: FIXED | I16: yes | J16: Q | K16: 4 | L16: 50 | M16: 0.0426 | N16: 2.13 | O16: 69.825 | P16: OK | Q16: 0.08 | R16: 0.076 | S16: 28.026316 | T16: -0.59862061 | U16: -0.56811578 | V16: 0 | W16: =IF(N(Q16)=0,"",Q16+IF(I16="yes",Q16*Inputs!$B$10*Inputs!$B$9,0)+V16) -> 0.076 | X16: =IF(OR(N(W16)<=0,N(N16)=0,N(L16)=0),"",MIN(L16,N16/W16)) -> 28.026316 | Y16: =IF(OR(X16="",N(O16)=0),"",X16/O16-1) -> -0.59862061 | Z16: =IF(OR(Y16="",N(O16)=0),"",Y16+N16/O16) -> -0.56811578 | AA16: =IF(OR(Z16="",N(U16)=0),"",Z16-U16) -> 0 | AB16: =IF(N(Q16)=0,"",Q16+IF(I16="yes",Q16*Inputs!$B$10*Inputs!$B$9,0)+IFERROR(INDEX(Inputs!$B$13:$B$15,MATCH(G16,Inputs!$A$13:$A$15,0)),0)+IFERROR(INDEX(Inputs!$B$18:$B$24,MATCH(H16,Inputs!$A$18:$A$24,0)),0)) -> 0.076 | AC16: =IF(OR(N(AB16)<=0,N(N16)=0,N(L16)=0),"",MIN(L16,N16/AB16)) -> 28.026316 | AD16: =IF(OR(AC16="",N(O16)=0),"",AC16/O16-1) -> -0.59862061 | AE16: =IF(OR(AD16="",N(O16)=0),"",AD16+N16/O16) -> -0.56811578 | AF16: =IF(OR(AE16="",N(Z16)=0),"",AE16-Z16) -> 0 | AG16: =IF(AND(N(M16)>0,N(L16)>0),M16*L16,N16) -> 2.13 | AH16: =IF(OR(N(AB16)<=0,N(AG16)=0,N(L16)=0),"",MIN(L16,AG16/AB16)) -> 28.026316 | AI16: =IF(OR(AH16="",N(O16)=0),"",AH16/O16-1) -> -0.59862061 | AJ16: =IF(OR(AI16="",N(O16)=0),"",AI16+AG16/O16) -> -0.56811578 | AK16: =IF(OR(AJ16="",N(AE16)=0),"",AJ16-AE16) -> 0 | AL16: =IF(N(F16)=0,"",INDEX(Inputs!$B$28:$B$32,IFERROR(MATCH(F16,Inputs!$A$28:$A$32,1),0)+1)) -> 0.075 | AN16: =IF(N(AM16)>0,AM16,AL16) -> 0.075 | AO16: =IF(N(AN16)=0,"",AN16+IF(I16="yes",AN16*Inputs!$B$10*Inputs!$B$9,0)+IFERROR(INDEX(Inputs!$B$13:$B$15,MATCH(G16,Inputs!$A$13:$A$15,0)),0)+IFERROR(INDEX(Inputs!$B$18:$B$24,MATCH(H16,Inputs!$A$18:$A$24,0)),0)) -> 0.07125 | AP16: =IF(OR(N(AO16)<=0,N(AG16)=0,N(L16)=0),"",MIN(L16,AG16/AO16)) -> 29.894737 | AQ16: =IF(OR(AP16="",N(O16)=0),"",AP16/O16-1) -> -0.57186199 | AR16: =IF(OR(AQ16="",N(O16)=0),"",AQ16+AG16/O16) -> -0.54135715 | AS16: =IF(OR(AR16="",N(AJ16)=0),"",AR16-AJ16) -> 0.026758626 | AT16: 100 | AU16: 4.26 | AV16: =IF(N(AT16)>0,AT16,L16) -> 100 | AW16: =IF(AND(N(M16)>0,N(AV16)>0),M16*AV16,IF(N(AU16)>0,AU16,N16)) -> 4.26 | AX16: =IF(N(AN16)=0,"",AN16+IF(I16="yes",AN16*Inputs!$B$10*Inputs!$B$9,0)+IFERROR(INDEX(Inputs!$B$13:$B$15,MATCH(G16,Inputs!$A$13:$A$15,0)),0)+IFERROR(INDEX(Inputs!$B$18:$B$24,MATCH(H16,Inputs!$A$18:$A$24,0)),0)) -> 0.07125 | AY16: =IF(OR(N(AX16)<=0,N(AW16)=0,N(AV16)=0),"",MIN(AV16,AW16/AX16)) -> 59.789474 | AZ16: =IF(OR(AY16="",N(O16)=0),"",AY16/O16-1) -> -0.14372397 | BA16: =IF(OR(AZ16="",N(O16)=0),"",AZ16+AW16/O16) -> -0.082714305 | BB16: =IF(OR(BA16="",N(AR16)=0),"",BA16-AR16) -> 0.45864285 | BC16: =IF(OR(BA16="",N(U16)=0),"",BA16-U16) -> 0.48540147 | BD16: PAR MISMATCH
A17: A-C | B17: 36 | C17: AILIP | D17: AEE | E17: AMEREN CORP | F17: 30100 | G17: PREFERRED | H17: FIXED | I17: yes | J17: Q | K17: 4 | L17: 50 | M17: 0.042 | N17: 2.1 | O17: 67.3 | P17: OK | Q17: 0.08 | R17: 0.076 | S17: 27.631579 | T17: -0.58942676 | U17: -0.5582232 | V17: 0 | W17: =IF(N(Q17)=0,"",Q17+IF(I17="yes",Q17*Inputs!$B$10*Inputs!$B$9,0)+V17) -> 0.076 | X17: =IF(OR(N(W17)<=0,N(N17)=0,N(L17)=0),"",MIN(L17,N17/W17)) -> 27.631579 | Y17: =IF(OR(X17="",N(O17)=0),"",X17/O17-1) -> -0.58942676 | Z17: =IF(OR(Y17="",N(O17)=0),"",Y17+N17/O17) -> -0.5582232 | AA17: =IF(OR(Z17="",N(U17)=0),"",Z17-U17) -> 0 | AB17: =IF(N(Q17)=0,"",Q17+IF(I17="yes",Q17*Inputs!$B$10*Inputs!$B$9,0)+IFERROR(INDEX(Inputs!$B$13:$B$15,MATCH(G17,Inputs!$A$13:$A$15,0)),0)+IFERROR(INDEX(Inputs!$B$18:$B$24,MATCH(H17,Inputs!$A$18:$A$24,0)),0)) -> 0.076 | AC17: =IF(OR(N(AB17)<=0,N(N17)=0,N(L17)=0),"",MIN(L17,N17/AB17)) -> 27.631579 | AD17: =IF(OR(AC17="",N(O17)=0),"",AC17/O17-1) -> -0.58942676 | AE17: =IF(OR(AD17="",N(O17)=0),"",AD17+N17/O17) -> -0.5582232 | AF17: =IF(OR(AE17="",N(Z17)=0),"",AE17-Z17) -> 0 | AG17: =IF(AND(N(M17)>0,N(L17)>0),M17*L17,N17) -> 2.1 | AH17: =IF(OR(N(AB17)<=0,N(AG17)=0,N(L17)=0),"",MIN(L17,AG17/AB17)) -> 27.631579 | AI17: =IF(OR(AH17="",N(O17)=0),"",AH17/O17-1) -> -0.58942676 | AJ17: =IF(OR(AI17="",N(O17)=0),"",AI17+AG17/O17) -> -0.5582232 | AK17: =IF(OR(AJ17="",N(AE17)=0),"",AJ17-AE17) -> 0 | AL17: =IF(N(F17)=0,"",INDEX(Inputs!$B$28:$B$32,IFERROR(MATCH(F17,Inputs!$A$28:$A$32,1),0)+1)) -> 0.075 | AN17: =IF(N(AM17)>0,AM17,AL17) -> 0.075 | AO17: =IF(N(AN17)=0,"",AN17+IF(I17="yes",AN17*Inputs!$B$10*Inputs!$B$9,0)+IFERROR(INDEX(Inputs!$B$13:$B$15,MATCH(G17,Inputs!$A$13:$A$15,0)),0)+IFERROR(INDEX(Inputs!$B$18:$B$24,MATCH(H17,Inputs!$A$18:$A$24,0)),0)) -> 0.07125 | AP17: =IF(OR(N(AO17)<=0,N(AG17)=0,N(L17)=0),"",MIN(L17,AG17/AO17)) -> 29.473684 | AQ17: =IF(OR(AP17="",N(O17)=0),"",AP17/O17-1) -> -0.56205521 | AR17: =IF(OR(AQ17="",N(O17)=0),"",AQ17+AG17/O17) -> -0.53085165 | AS17: =IF(OR(AR17="",N(AJ17)=0),"",AR17-AJ17) -> 0.027371549 | AT17: 100 | AU17: 4.2 | AV17: =IF(N(AT17)>0,AT17,L17) -> 100 | AW17: =IF(AND(N(M17)>0,N(AV17)>0),M17*AV17,IF(N(AU17)>0,AU17,N17)) -> 4.2 | AX17: =IF(N(AN17)=0,"",AN17+IF(I17="yes",AN17*Inputs!$B$10*Inputs!$B$9,0)+IFERROR(INDEX(Inputs!$B$13:$B$15,MATCH(G17,Inputs!$A$13:$A$15,0)),0)+IFERROR(INDEX(Inputs!$B$18:$B$24,MATCH(H17,Inputs!$A$18:$A$24,0)),0)) -> 0.07125 | AY17: =IF(OR(N(AX17)<=0,N(AW17)=0,N(AV17)=0),"",MIN(AV17,AW17/AX17)) -> 58.947368 | AZ17: =IF(OR(AY17="",N(O17)=0),"",AY17/O17-1) -> -0.12411042 | BA17: =IF(OR(AZ17="",N(O17)=0),"",AZ17+AW17/O17) -> -0.061703292 | BB17: =IF(OR(BA17="",N(AR17)=0),"",BA17-AR17) -> 0.46914835 | BC17: =IF(OR(BA17="",N(U17)=0),"",BA17-U17) -> 0.4965199 | BD17: PAR MISMATCH
A18: A-C | B18: 37 | C18: AILLI | D18: AEE | E18: AMEREN CORP | F18: 30100 | G18: PREFERRED | H18: FIXED | I18: yes | J18: Q | K18: 4 | L18: 100 | M18: 0.0516 | N18: 5.16 | O18: 81 | P18: OK | Q18: 0.08 | R18: 0.076 | S18: 67.894737 | T18: -0.16179337 | U18: -0.098089669 | V18: 0 | W18: =IF(N(Q18)=0,"",Q18+IF(I18="yes",Q18*Inputs!$B$10*Inputs!$B$9,0)+V18) -> 0.076 | X18: =IF(OR(N(W18)<=0,N(N18)=0,N(L18)=0),"",MIN(L18,N18/W18)) -> 67.894737 | Y18: =IF(OR(X18="",N(O18)=0),"",X18/O18-1) -> -0.16179337 | Z18: =IF(OR(Y18="",N(O18)=0),"",Y18+N18/O18) -> -0.098089669 | AA18: =IF(OR(Z18="",N(U18)=0),"",Z18-U18) -> 0 | AB18: =IF(N(Q18)=0,"",Q18+IF(I18="yes",Q18*Inputs!$B$10*Inputs!$B$9,0)+IFERROR(INDEX(Inputs!$B$13:$B$15,MATCH(G18,Inputs!$A$13:$A$15,0)),0)+IFERROR(INDEX(Inputs!$B$18:$B$24,MATCH(H18,Inputs!$A$18:$A$24,0)),0)) -> 0.076 | AC18: =IF(OR(N(AB18)<=0,N(N18)=0,N(L18)=0),"",MIN(L18,N18/AB18)) -> 67.894737 | AD18: =IF(OR(AC18="",N(O18)=0),"",AC18/O18-1) -> -0.16179337 | AE18: =IF(OR(AD18="",N(O18)=0),"",AD18+N18/O18) -> -0.098089669 | AF18: =IF(OR(AE18="",N(Z18)=0),"",AE18-Z18) -> 0 | AG18: =IF(AND(N(M18)>0,N(L18)>0),M18*L18,N18) -> 5.16 | AH18: =IF(OR(N(AB18)<=0,N(AG18)=0,N(L18)=0),"",MIN(L18,AG18/AB18)) -> 67.894737 | AI18: =IF(OR(AH18="",N(O18)=0),"",AH18/O18-1) -> -0.16179337 | AJ18: =IF(OR(AI18="",N(O18)=0),"",AI18+AG18/O18) -> -0.098089669 | AK18: =IF(OR(AJ18="",N(AE18)=0),"",AJ18-AE18) -> 0 | AL18: =IF(N(F18)=0,"",INDEX(Inputs!$B$28:$B$32,IFERROR(MATCH(F18,Inputs!$A$28:$A$32,1),0)+1)) -> 0.075 | AN18: =IF(N(AM18)>0,AM18,AL18) -> 0.075 | AO18: =IF(N(AN18)=0,"",AN18+IF(I18="yes",AN18*Inputs!$B$10*Inputs!$B$9,0)+IFERROR(INDEX(Inputs!$B$13:$B$15,MATCH(G18,Inputs!$A$13:$A$15,0)),0)+IFERROR(INDEX(Inputs!$B$18:$B$24,MATCH(H18,Inputs!$A$18:$A$24,0)),0)) -> 0.07125 | AP18: =IF(OR(N(AO18)<=0,N(AG18)=0,N(L18)=0),"",MIN(L18,AG18/AO18)) -> 72.421053 | AQ18: =IF(OR(AP18="",N(O18)=0),"",AP18/O18-1) -> -0.10591293 | AR18: =IF(OR(AQ18="",N(O18)=0),"",AQ18+AG18/O18) -> -0.042209227 | AS18: =IF(OR(AR18="",N(AJ18)=0),"",AR18-AJ18) -> 0.055880442 | AT18: 100 | AU18: 5.16 | AV18: =IF(N(AT18)>0,AT18,L18) -> 100 | AW18: =IF(AND(N(M18)>0,N(AV18)>0),M18*AV18,IF(N(AU18)>0,AU18,N18)) -> 5.16 | AX18: =IF(N(AN18)=0,"",AN18+IF(I18="yes",AN18*Inputs!$B$10*Inputs!$B$9,0)+IFERROR(INDEX(Inputs!$B$13:$B$15,MATCH(G18,Inputs!$A$13:$A$15,0)),0)+IFERROR(INDEX(Inputs!$B$18:$B$24,MATCH(H18,Inputs!$A$18:$A$24,0)),0)) -> 0.07125 | AY18: =IF(OR(N(AX18)<=0,N(AW18)=0,N(AV18)=0),"",MIN(AV18,AW18/AX18)) -> 72.421053 | AZ18: =IF(OR(AY18="",N(O18)=0),"",AY18/O18-1) -> -0.10591293 | BA18: =IF(OR(AZ18="",N(O18)=0),"",AZ18+AW18/O18) -> -0.042209227 | BB18: =IF(OR(BA18="",N(AR18)=0),"",BA18-AR18) -> 0 | BC18: =IF(OR(BA18="",N(U18)=0),"",BA18-U18) -> 0.055880442
A19: A-C | B19: 38 | C19: AILLM | D19: AEE | E19: AMEREN CORP | F19: 30100 | G19: PREFERRED | H19: FIXED | I19: yes | J19: Q | K19: 4 | L19: 100 | M19: 0.0492 | N19: 4.92 | O19: 78.6 | P19: OK | Q19: 0.08 | R19: 0.076 | S19: 64.736842 | T19: -0.17637605 | U19: -0.11378063 | V19: 0 | W19: =IF(N(Q19)=0,"",Q19+IF(I19="yes",Q19*Inputs!$B$10*Inputs!$B$9,0)+V19) -> 0.076 | X19: =IF(OR(N(W19)<=0,N(N19)=0,N(L19)=0),"",MIN(L19,N19/W19)) -> 64.736842 | Y19: =IF(OR(X19="",N(O19)=0),"",X19/O19-1) -> -0.17637605 | Z19: =IF(OR(Y19="",N(O19)=0),"",Y19+N19/O19) -> -0.11378063 | AA19: =IF(OR(Z19="",N(U19)=0),"",Z19-U19) -> 0 | AB19: =IF(N(Q19)=0,"",Q19+IF(I19="yes",Q19*Inputs!$B$10*Inputs!$B$9,0)+IFERROR(INDEX(Inputs!$B$13:$B$15,MATCH(G19,Inputs!$A$13:$A$15,0)),0)+IFERROR(INDEX(Inputs!$B$18:$B$24,MATCH(H19,Inputs!$A$18:$A$24,0)),0)) -> 0.076 | AC19: =IF(OR(N(AB19)<=0,N(N19)=0,N(L19)=0),"",MIN(L19,N19/AB19)) -> 64.736842 | AD19: =IF(OR(AC19="",N(O19)=0),"",AC19/O19-1) -> -0.17637605 | AE19: =IF(OR(AD19="",N(O19)=0),"",AD19+N19/O19) -> -0.11378063 | AF19: =IF(OR(AE19="",N(Z19)=0),"",AE19-Z19) -> 0 | AG19: =IF(AND(N(M19)>0,N(L19)>0),M19*L19,N19) -> 4.92 | AH19: =IF(OR(N(AB19)<=0,N(AG19)=0,N(L19)=0),"",MIN(L19,AG19/AB19)) -> 64.736842 | AI19: =IF(OR(AH19="",N(O19)=0),"",AH19/O19-1) -> -0.17637605 | AJ19: =IF(OR(AI19="",N(O19)=0),"",AI19+AG19/O19) -> -0.11378063 | AK19: =IF(OR(AJ19="",N(AE19)=0),"",AJ19-AE19) -> 0 | AL19: =IF(N(F19)=0,"",INDEX(Inputs!$B$28:$B$32,IFERROR(MATCH(F19,Inputs!$A$28:$A$32,1),0)+1)) -> 0.075 | AN19: =IF(N(AM19)>0,AM19,AL19) -> 0.075 | AO19: =IF(N(AN19)=0,"",AN19+IF(I19="yes",AN19*Inputs!$B$10*Inputs!$B$9,0)+IFERROR(INDEX(Inputs!$B$13:$B$15,MATCH(G19,Inputs!$A$13:$A$15,0)),0)+IFERROR(INDEX(Inputs!$B$18:$B$24,MATCH(H19,Inputs!$A$18:$A$24,0)),0)) -> 0.07125 | AP19: =IF(OR(N(AO19)<=0,N(AG19)=0,N(L19)=0),"",MIN(L19,AG19/AO19)) -> 69.052632 | AQ19: =IF(OR(AP19="",N(O19)=0),"",AP19/O19-1) -> -0.12146779 | AR19: =IF(OR(AQ19="",N(O19)=0),"",AQ19+AG19/O19) -> -0.058872372 | AS19: =IF(OR(AR19="",N(AJ19)=0),"",AR19-AJ19) -> 0.054908263 | AT19: 100 | AU19: 4.92 | AV19: =IF(N(AT19)>0,AT19,L19) -> 100 | AW19: =IF(AND(N(M19)>0,N(AV19)>0),M19*AV19,IF(N(AU19)>0,AU19,N19)) -> 4.92 | AX19: =IF(N(AN19)=0,"",AN19+IF(I19="yes",AN19*Inputs!$B$10*Inputs!$B$9,0)+IFERROR(INDEX(Inputs!$B$13:$B$15,MATCH(G19,Inputs!$A$13:$A$15,0)),0)+IFERROR(INDEX(Inputs!$B$18:$B$24,MATCH(H19,Inputs!$A$18:$A$24,0)),0)) -> 0.07125 | AY19: =IF(OR(N(AX19)<=0,N(AW19)=0,N(AV19)=0),"",MIN(AV19,AW19/AX19)) -> 69.052632 | AZ19: =IF(OR(AY19="",N(O19)=0),"",AY19/O19-1) -> -0.12146779 | BA19: =IF(OR(AZ19="",N(O19)=0),"",AZ19+AW19/O19) -> -0.058872372 | BB19: =IF(OR(BA19="",N(AR19)=0),"",BA19-AR19) -> 0 | BC19: =IF(OR(BA19="",N(U19)=0),"",BA19-U19) -> 0.054908263
A20: A-C | B20: 39 | C20: AILLN | D20: AEE | E20: AMEREN CORP | F20: 30100 | G20: PREFERRED | H20: FIXED | I20: yes | J20: Q | K20: 4 | L20: 100 | M20: 0.049 | N20: 4.9 | O20: 77.66 | P20: OK | Q20: 0.08 | R20: 0.076 | S20: 64.473684 | T20: -0.16979546 | U20: -0.10669992 | V20: 0 | W20: =IF(N(Q20)=0,"",Q20+IF(I20="yes",Q20*Inputs!$B$10*Inputs!$B$9,0)+V20) -> 0.076 | X20: =IF(OR(N(W20)<=0,N(N20)=0,N(L20)=0),"",MIN(L20,N20/W20)) -> 64.473684 | Y20: =IF(OR(X20="",N(O20)=0),"",X20/O20-1) -> -0.16979546 | Z20: =IF(OR(Y20="",N(O20)=0),"",Y20+N20/O20) -> -0.10669992 | AA20: =IF(OR(Z20="",N(U20)=0),"",Z20-U20) -> 0 | AB20: =IF(N(Q20)=0,"",Q20+IF(I20="yes",Q20*Inputs!$B$10*Inputs!$B$9,0)+IFERROR(INDEX(Inputs!$B$13:$B$15,MATCH(G20,Inputs!$A$13:$A$15,0)),0)+IFERROR(INDEX(Inputs!$B$18:$B$24,MATCH(H20,Inputs!$A$18:$A$24,0)),0)) -> 0.076 | AC20: =IF(OR(N(AB20)<=0,N(N20)=0,N(L20)=0),"",MIN(L20,N20/AB20)) -> 64.473684 | AD20: =IF(OR(AC20="",N(O20)=0),"",AC20/O20-1) -> -0.16979546 | AE20: =IF(OR(AD20="",N(O20)=0),"",AD20+N20/O20) -> -0.10669992 | AF20: =IF(OR(AE20="",N(Z20)=0),"",AE20-Z20) -> 0 | AG20: =IF(AND(N(M20)>0,N(L20)>0),M20*L20,N20) -> 4.9 | AH20: =IF(OR(N(AB20)<=0,N(AG20)=0,N(L20)=0),"",MIN(L20,AG20/AB20)) -> 64.473684 | AI20: =IF(OR(AH20="",N(O20)=0),"",AH20/O20-1) -> -0.16979546 | AJ20: =IF(OR(AI20="",N(O20)=0),"",AI20+AG20/O20) -> -0.10669992 | AK20: =IF(OR(AJ20="",N(AE20)=0),"",AJ20-AE20) -> 0 | AL20: =IF(N(F20)=0,"",INDEX(Inputs!$B$28:$B$32,IFERROR(MATCH(F20,Inputs!$A$28:$A$32,1),0)+1)) -> 0.075 | AN20: =IF(N(AM20)>0,AM20,AL20) -> 0.075 | AO20: =IF(N(AN20)=0,"",AN20+IF(I20="yes",AN20*Inputs!$B$10*Inputs!$B$9,0)+IFERROR(INDEX(Inputs!$B$13:$B$15,MATCH(G20,Inputs!$A$13:$A$15,0)),0)+IFERROR(INDEX(Inputs!$B$18:$B$24,MATCH(H20,Inputs!$A$18:$A$24,0)),0)) -> 0.07125 | AP20: =IF(OR(N(AO20)<=0,N(AG20)=0,N(L20)=0),"",MIN(L20,AG20/AO20)) -> 68.77193 | AQ20: =IF(OR(AP20="",N(O20)=0),"",AP20/O20-1) -> -0.1144485 | AR20: =IF(OR(AQ20="",N(O20)=0),"",AQ20+AG20/O20) -> -0.051352951 | AS20: =IF(OR(AR20="",N(AJ20)=0),"",AR20-AJ20) -> 0.055346969 | AT20: 100 | AU20: 4.9 | AV20: =IF(N(AT20)>0,AT20,L20) -> 100 | AW20: =IF(AND(N(M20)>0,N(AV20)>0),M20*AV20,IF(N(AU20)>0,AU20,N20)) -> 4.9 | AX20: =IF(N(AN20)=0,"",AN20+IF(I20="yes",AN20*Inputs!$B$10*Inputs!$B$9,0)+IFERROR(INDEX(Inputs!$B$13:$B$15,MATCH(G20,Inputs!$A$13:$A$15,0)),0)+IFERROR(INDEX(Inputs!$B$18:$B$24,MATCH(H20,Inputs!$A$18:$A$24,0)),0)) -> 0.07125 | AY20: =IF(OR(N(AX20)<=0,N(AW20)=0,N(AV20)=0),"",MIN(AV20,AW20/AX20)) -> 68.77193 | AZ20: =IF(OR(AY20="",N(O20)=0),"",AY20/O20-1) -> -0.1144485 | BA20: =IF(OR(AZ20="",N(O20)=0),"",AZ20+AW20/O20) -> -0.051352951 | BB20: =IF(OR(BA20="",N(AR20)=0),"",BA20-AR20) -> 0 | BC20: =IF(OR(BA20="",N(U20)=0),"",BA20-U20) -> 0.055346969
A21: A-C | B21: 40 | C21: AILLO | D21: AEE | E21: AMEREN CORP | F21: 30100 | G21: PREFERRED | H21: FIXED | I21: yes | J21: Q | K21: 4 | L21: 100 | M21: 0.0425 | N21: 4.25 | O21: 67.5 | P21: OK | Q21: 0.08 | R21: 0.076 | S21: 55.921053 | T21: -0.17153996 | U21: -0.108577 | V21: 0 | W21: =IF(N(Q21)=0,"",Q21+IF(I21="yes",Q21*Inputs!$B$10*Inputs!$B$9,0)+V21) -> 0.076 | X21: =IF(OR(N(W21)<=0,N(N21)=0,N(L21)=0),"",MIN(L21,N21/W21)) -> 55.921053 | Y21: =IF(OR(X21="",N(O21)=0),"",X21/O21-1) -> -0.17153996 | Z21: =IF(OR(Y21="",N(O21)=0),"",Y21+N21/O21) -> -0.108577 | AA21: =IF(OR(Z21="",N(U21)=0),"",Z21-U21) -> 0 | AB21: =IF(N(Q21)=0,"",Q21+IF(I21="yes",Q21*Inputs!$B$10*Inputs!$B$9,0)+IFERROR(INDEX(Inputs!$B$13:$B$15,MATCH(G21,Inputs!$A$13:$A$15,0)),0)+IFERROR(INDEX(Inputs!$B$18:$B$24,MATCH(H21,Inputs!$A$18:$A$24,0)),0)) -> 0.076 | AC21: =IF(OR(N(AB21)<=0,N(N21)=0,N(L21)=0),"",MIN(L21,N21/AB21)) -> 55.921053 | AD21: =IF(OR(AC21="",N(O21)=0),"",AC21/O21-1) -> -0.17153996 | AE21: =IF(OR(AD21="",N(O21)=0),"",AD21+N21/O21) -> -0.108577 | AF21: =IF(OR(AE21="",N(Z21)=0),"",AE21-Z21) -> 0 | AG21: =IF(AND(N(M21)>0,N(L21)>0),M21*L21,N21) -> 4.25 | AH21: =IF(OR(N(AB21)<=0,N(AG21)=0,N(L21)=0),"",MIN(L21,AG21/AB21)) -> 55.921053 | AI21: =IF(OR(AH21="",N(O21)=0),"",AH21/O21-1) -> -0.17153996 | AJ21: =IF(OR(AI21="",N(O21)=0),"",AI21+AG21/O21) -> -0.108577 | AK21: =IF(OR(AJ21="",N(AE21)=0),"",AJ21-AE21) -> 0 | AL21: =IF(N(F21)=0,"",INDEX(Inputs!$B$28:$B$32,IFERROR(MATCH(F21,Inputs!$A$28:$A$32,1),0)+1)) -> 0.075 | AN21: =IF(N(AM21)>0,AM21,AL21) -> 0.075 | AO21: =IF(N(AN21)=0,"",AN21+IF(I21="yes",AN21*Inputs!$B$10*Inputs!$B$9,0)+IFERROR(INDEX(Inputs!$B$13:$B$15,MATCH(G21,Inputs!$A$13:$A$15,0)),0)+IFERROR(INDEX(Inputs!$B$18:$B$24,MATCH(H21,Inputs!$A$18:$A$24,0)),0)) -> 0.07125 | AP21: =IF(OR(N(AO21)<=0,N(AG21)=0,N(L21)=0),"",MIN(L21,AG21/AO21)) -> 59.649123 | AQ21: =IF(OR(AP21="",N(O21)=0),"",AP21/O21-1) -> -0.11630929 | AR21: =IF(OR(AQ21="",N(O21)=0),"",AQ21+AG21/O21) -> -0.053346329 | AS21: =IF(OR(AR21="",N(AJ21)=0),"",AR21-AJ21) -> 0.055230669 | AT21: 100 | AU21: 4.25 | AV21: =IF(N(AT21)>0,AT21,L21) -> 100 | AW21: =IF(AND(N(M21)>0,N(AV21)>0),M21*AV21,IF(N(AU21)>0,AU21,N21)) -> 4.25 | AX21: =IF(N(AN21)=0,"",AN21+IF(I21="yes",AN21*Inputs!$B$10*Inputs!$B$9,0)+IFERROR(INDEX(Inputs!$B$13:$B$15,MATCH(G21,Inputs!$A$13:$A$15,0)),0)+IFERROR(INDEX(Inputs!$B$18:$B$24,MATCH(H21,Inputs!$A$18:$A$24,0)),0)) -> 0.07125 | AY21: =IF(OR(N(AX21)<=0,N(AW21)=0,N(AV21)=0),"",MIN(AV21,AW21/AX21)) -> 59.649123 | AZ21: =IF(OR(AY21="",N(O21)=0),"",AY21/O21-1) -> -0.11630929 | BA21: =IF(OR(AZ21="",N(O21)=0),"",AZ21+AW21/O21) -> -0.053346329 | BB21: =IF(OR(BA21="",N(AR21)=0),"",BA21-AR21) -> 0 | BC21: =IF(OR(BA21="",N(U21)=0),"",BA21-U21) -> 0.055230669
A22: A-C | B22: 41 | C22: AILLP | D22: AEE | E22: AMEREN CORP | F22: 30100 | G22: PREFERRED | H22: FIXED | I22: yes | J22: Q | K22: 4 | L22: 100 | M22: 0.04 | N22: 4 | O22: 62.75 | P22: OK | Q22: 0.08 | R22: 0.076 | S22: 52.631579 | T22: -0.16124974 | U22: -0.097504718 | V22: 0 | W22: =IF(N(Q22)=0,"",Q22+IF(I22="yes",Q22*Inputs!$B$10*Inputs!$B$9,0)+V22) -> 0.076 | X22: =IF(OR(N(W22)<=0,N(N22)=0,N(L22)=0),"",MIN(L22,N22/W22)) -> 52.631579 | Y22: =IF(OR(X22="",N(O22)=0),"",X22/O22-1) -> -0.16124974 | Z22: =IF(OR(Y22="",N(O22)=0),"",Y22+N22/O22) -> -0.097504718 | AA22: =IF(OR(Z22="",N(U22)=0),"",Z22-U22) -> 0 | AB22: =IF(N(Q22)=0,"",Q22+IF(I22="yes",Q22*Inputs!$B$10*Inputs!$B$9,0)+IFERROR(INDEX(Inputs!$B$13:$B$15,MATCH(G22,Inputs!$A$13:$A$15,0)),0)+IFERROR(INDEX(Inputs!$B$18:$B$24,MATCH(H22,Inputs!$A$18:$A$24,0)),0)) -> 0.076 | AC22: =IF(OR(N(AB22)<=0,N(N22)=0,N(L22)=0),"",MIN(L22,N22/AB22)) -> 52.631579 | AD22: =IF(OR(AC22="",N(O22)=0),"",AC22/O22-1) -> -0.16124974 | AE22: =IF(OR(AD22="",N(O22)=0),"",AD22+N22/O22) -> -0.097504718 | AF22: =IF(OR(AE22="",N(Z22)=0),"",AE22-Z22) -> 0 | AG22: =IF(AND(N(M22)>0,N(L22)>0),M22*L22,N22) -> 4 | AH22: =IF(OR(N(AB22)<=0,N(AG22)=0,N(L22)=0),"",MIN(L22,AG22/AB22)) -> 52.631579 | AI22: =IF(OR(AH22="",N(O22)=0),"",AH22/O22-1) -> -0.16124974 | AJ22: =IF(OR(AI22="",N(O22)=0),"",AI22+AG22/O22) -> -0.097504718 | AK22: =IF(OR(AJ22="",N(AE22)=0),"",AJ22-AE22) -> 0 | AL22: =IF(N(F22)=0,"",INDEX(Inputs!$B$28:$B$32,IFERROR(MATCH(F22,Inputs!$A$28:$A$32,1),0)+1)) -> 0.075 | AN22: =IF(N(AM22)>0,AM22,AL22) -> 0.075 | AO22: =IF(N(AN22)=0,"",AN22+IF(I22="yes",AN22*Inputs!$B$10*Inputs!$B$9,0)+IFERROR(INDEX(Inputs!$B$13:$B$15,MATCH(G22,Inputs!$A$13:$A$15,0)),0)+IFERROR(INDEX(Inputs!$B$18:$B$24,MATCH(H22,Inputs!$A$18:$A$24,0)),0)) -> 0.07125 | AP22: =IF(OR(N(AO22)<=0,N(AG22)=0,N(L22)=0),"",MIN(L22,AG22/AO22)) -> 56.140351 | AQ22: =IF(OR(AP22="",N(O22)=0),"",AP22/O22-1) -> -0.10533305 | AR22: =IF(OR(AQ22="",N(O22)=0),"",AQ22+AG22/O22) -> -0.041588034 | AS22: =IF(OR(AR22="",N(AJ22)=0),"",AR22-AJ22) -> 0.055916684 | AT22: 100 | AU22: 4 | AV22: =IF(N(AT22)>0,AT22,L22) -> 100 | AW22: =IF(AND(N(M22)>0,N(AV22)>0),M22*AV22,IF(N(AU22)>0,AU22,N22)) -> 4 | AX22: =IF(N(AN22)=0,"",AN22+IF(I22="yes",AN22*Inputs!$B$10*Inputs!$B$9,0)+IFERROR(INDEX(Inputs!$B$13:$B$15,MATCH(G22,Inputs!$A$13:$A$15,0)),0)+IFERROR(INDEX(Inputs!$B$18:$B$24,MATCH(H22,Inputs!$A$18:$A$24,0)),0)) -> 0.07125 | AY22: =IF(OR(N(AX22)<=0,N(AW22)=0,N(AV22)=0),"",MIN(AV22,AW22/AX22)) -> 56.140351 | AZ22: =IF(OR(AY22="",N(O22)=0),"",AY22/O22-1) -> -0.10533305 | BA22: =IF(OR(AZ22="",N(O22)=0),"",AZ22+AW22/O22) -> -0.041588034 | BB22: =IF(OR(BA22="",N(AR22)=0),"",BA22-AR22) -> 0 | BC22: =IF(OR(BA22="",N(U22)=0),"",BA22-U22) -> 0.055916684
A23: A-C | B23: 42 | C23: UELMO | D23: AEE | E23: AMEREN CORP | F23: 30100 | G23: PREFERRED | H23: FIXED | I23: yes | J23: Q | K23: 4 | L23: 100 | M23: 0.037 | N23: 3.7 | O23: 60.5 | P23: OK | Q23: 0.08 | R23: 0.076 | S23: 48.684211 | T23: -0.19530231 | U23: -0.13414528 | V23: 0 | W23: =IF(N(Q23)=0,"",Q23+IF(I23="yes",Q23*Inputs!$B$10*Inputs!$B$9,0)+V23) -> 0.076 | X23: =IF(OR(N(W23)<=0,N(N23)=0,N(L23)=0),"",MIN(L23,N23/W23)) -> 48.684211 | Y23: =IF(OR(X23="",N(O23)=0),"",X23/O23-1) -> -0.19530231 | Z23: =IF(OR(Y23="",N(O23)=0),"",Y23+N23/O23) -> -0.13414528 | AA23: =IF(OR(Z23="",N(U23)=0),"",Z23-U23) -> 0 | AB23: =IF(N(Q23)=0,"",Q23+IF(I23="yes",Q23*Inputs!$B$10*Inputs!$B$9,0)+IFERROR(INDEX(Inputs!$B$13:$B$15,MATCH(G23,Inputs!$A$13:$A$15,0)),0)+IFERROR(INDEX(Inputs!$B$18:$B$24,MATCH(H23,Inputs!$A$18:$A$24,0)),0)) -> 0.076 | AC23: =IF(OR(N(AB23)<=0,N(N23)=0,N(L23)=0),"",MIN(L23,N23/AB23)) -> 48.684211 | AD23: =IF(OR(AC23="",N(O23)=0),"",AC23/O23-1) -> -0.19530231 | AE23: =IF(OR(AD23="",N(O23)=0),"",AD23+N23/O23) -> -0.13414528 | AF23: =IF(OR(AE23="",N(Z23)=0),"",AE23-Z23) -> 0 | AG23: =IF(AND(N(M23)>0,N(L23)>0),M23*L23,N23) -> 3.7 | AH23: =IF(OR(N(AB23)<=0,N(AG23)=0,N(L23)=0),"",MIN(L23,AG23/AB23)) -> 48.684211 | AI23: =IF(OR(AH23="",N(O23)=0),"",AH23/O23-1) -> -0.19530231 | AJ23: =IF(OR(AI23="",N(O23)=0),"",AI23+AG23/O23) -> -0.13414528 | AK23: =IF(OR(AJ23="",N(AE23)=0),"",AJ23-AE23) -> 0 | AL23: =IF(N(F23)=0,"",INDEX(Inputs!$B$28:$B$32,IFERROR(MATCH(F23,Inputs!$A$28:$A$32,1),0)+1)) -> 0.075 | AN23: =IF(N(AM23)>0,AM23,AL23) -> 0.075 | AO23: =IF(N(AN23)=0,"",AN23+IF(I23="yes",AN23*Inputs!$B$10*Inputs!$B$9,0)+IFERROR(INDEX(Inputs!$B$13:$B$15,MATCH(G23,Inputs!$A$13:$A$15,0)),0)+IFERROR(INDEX(Inputs!$B$18:$B$24,MATCH(H23,Inputs!$A$18:$A$24,0)),0)) -> 0.07125 | AP23: =IF(OR(N(AO23)<=0,N(AG23)=0,N(L23)=0),"",MIN(L23,AG23/AO23)) -> 51.929825 | AQ23: =IF(OR(AP23="",N(O23)=0),"",AP23/O23-1) -> -0.14165579 | AR23: =IF(OR(AQ23="",N(O23)=0),"",AQ23+AG23/O23) -> -0.080498768 | AS23: =IF(OR(AR23="",N(AJ23)=0),"",AR23-AJ23) -> 0.053646513 | AT23: 100 | AU23: 3.7 | AV23: =IF(N(AT23)>0,AT23,L23) -> 100 | AW23: =IF(AND(N(M23)>0,N(AV23)>0),M23*AV23,IF(N(AU23)>0,AU23,N23)) -> 3.7 | AX23: =IF(N(AN23)=0,"",AN23+IF(I23="yes",AN23*Inputs!$B$10*Inputs!$B$9,0)+IFERROR(INDEX(Inputs!$B$13:$B$15,MATCH(G23,Inputs!$A$13:$A$15,0)),0)+IFERROR(INDEX(Inputs!$B$18:$B$24,MATCH(H23,Inputs!$A$18:$A$24,0)),0)) -> 0.07125 | AY23: =IF(OR(N(AX23)<=0,N(AW23)=0,N(AV23)=0),"",MIN(AV23,AW23/AX23)) -> 51.929825 | AZ23: =IF(OR(AY23="",N(O23)=0),"",AY23/O23-1) -> -0.14165579 | BA23: =IF(OR(AZ23="",N(O23)=0),"",AZ23+AW23/O23) -> -0.080498768 | BB23: =IF(OR(BA23="",N(AR23)=0),"",BA23-AR23) -> 0 | BC23: =IF(OR(BA23="",N(U23)=0),"",BA23-U23) -> 0.053646513
A24: A-C | B24: 43 | C24: UEPCN | D24: AEE | E24: AMEREN CORP | F24: 30100 | G24: PREFERRED | H24: FIXED | I24: yes | J24: Q | K24: 4 | L24: 100 | M24: 0.0475 | N24: 4.75 | O24: 76.3 | P24: OK | Q24: 0.08 | R24: 0.076 | S24: 62.5 | T24: -0.18086501 | U24: -0.11861075 | V24: 0 | W24: =IF(N(Q24)=0,"",Q24+IF(I24="yes",Q24*Inputs!$B$10*Inputs!$B$9,0)+V24) -> 0.076 | X24: =IF(OR(N(W24)<=0,N(N24)=0,N(L24)=0),"",MIN(L24,N24/W24)) -> 62.5 | Y24: =IF(OR(X24="",N(O24)=0),"",X24/O24-1) -> -0.18086501 | Z24: =IF(OR(Y24="",N(O24)=0),"",Y24+N24/O24) -> -0.11861075 | AA24: =IF(OR(Z24="",N(U24)=0),"",Z24-U24) -> 0 | AB24: =IF(N(Q24)=0,"",Q24+IF(I24="yes",Q24*Inputs!$B$10*Inputs!$B$9,0)+IFERROR(INDEX(Inputs!$B$13:$B$15,MATCH(G24,Inputs!$A$13:$A$15,0)),0)+IFERROR(INDEX(Inputs!$B$18:$B$24,MATCH(H24,Inputs!$A$18:$A$24,0)),0)) -> 0.076 | AC24: =IF(OR(N(AB24)<=0,N(N24)=0,N(L24)=0),"",MIN(L24,N24/AB24)) -> 62.5 | AD24: =IF(OR(AC24="",N(O24)=0),"",AC24/O24-1) -> -0.18086501 | AE24: =IF(OR(AD24="",N(O24)=0),"",AD24+N24/O24) -> -0.11861075 | AF24: =IF(OR(AE24="",N(Z24)=0),"",AE24-Z24) -> 0 | AG24: =IF(AND(N(M24)>0,N(L24)>0),M24*L24,N24) -> 4.75 | AH24: =IF(OR(N(AB24)<=0,N(AG24)=0,N(L24)=0),"",MIN(L24,AG24/AB24)) -> 62.5 | AI24: =IF(OR(AH24="",N(O24)=0),"",AH24/O24-1) -> -0.18086501 | AJ24: =IF(OR(AI24="",N(O24)=0),"",AI24+AG24/O24) -> -0.11861075 | AK24: =IF(OR(AJ24="",N(AE24)=0),"",AJ24-AE24) -> 0 | AL24: =IF(N(F24)=0,"",INDEX(Inputs!$B$28:$B$32,IFERROR(MATCH(F24,Inputs!$A$28:$A$32,1),0)+1)) -> 0.075 | AN24: =IF(N(AM24)>0,AM24,AL24) -> 0.075 | AO24: =IF(N(AN24)=0,"",AN24+IF(I24="yes",AN24*Inputs!$B$10*Inputs!$B$9,0)+IFERROR(INDEX(Inputs!$B$13:$B$15,MATCH(G24,Inputs!$A$13:$A$15,0)),0)+IFERROR(INDEX(Inputs!$B$18:$B$24,MATCH(H24,Inputs!$A$18:$A$24,0)),0)) -> 0.07125 | AP24: =IF(OR(N(AO24)<=0,N(AG24)=0,N(L24)=0),"",MIN(L24,AG24/AO24)) -> 66.666667 | AQ24: =IF(OR(AP24="",N(O24)=0),"",AP24/O24-1) -> -0.12625601 | AR24: =IF(OR(AQ24="",N(O24)=0),"",AQ24+AG24/O24) -> -0.064001747 | AS24: =IF(OR(AR24="",N(AJ24)=0),"",AR24-AJ24) -> 0.054609 | AT24: 100 | AU24: 4.75 | AV24: =IF(N(AT24)>0,AT24,L24) -> 100 | AW24: =IF(AND(N(M24)>0,N(AV24)>0),M24*AV24,IF(N(AU24)>0,AU24,N24)) -> 4.75 | AX24: =IF(N(AN24)=0,"",AN24+IF(I24="yes",AN24*Inputs!$B$10*Inputs!$B$9,0)+IFERROR(INDEX(Inputs!$B$13:$B$15,MATCH(G24,Inputs!$A$13:$A$15,0)),0)+IFERROR(INDEX(Inputs!$B$18:$B$24,MATCH(H24,Inputs!$A$18:$A$24,0)),0)) -> 0.07125 | AY24: =IF(OR(N(AX24)<=0,N(AW24)=0,N(AV24)=0),"",MIN(AV24,AW24/AX24)) -> 66.666667 | AZ24: =IF(OR(AY24="",N(O24)=0),"",AY24/O24-1) -> -0.12625601 | BA24: =IF(OR(AZ24="",N(O24)=0),"",AZ24+AW24/O24) -> -0.064001747 | BB24: =IF(OR(BA24="",N(AR24)=0),"",BA24-AR24) -> 0 | BC24: =IF(OR(BA24="",N(U24)=0),"",BA24-U24) -> 0.054609
A25: A-C | B25: 44 | C25: UEPCO | D25: AEE | E25: AMEREN CORP | F25: 30100 | G25: PREFERRED | H25: FIXED | I25: yes | J25: Q | K25: 4 | L25: 100 | M25: 0.055 | N25: 5.5 | O25: 90.3052 | P25: OK | Q25: 0.08 | R25: 0.076 | S25: 72.368421 | T25: -0.19862399 | U25: -0.13771941 | V25: 0 | W25: =IF(N(Q25)=0,"",Q25+IF(I25="yes",Q25*Inputs!$B$10*Inputs!$B$9,0)+V25) -> 0.076 | X25: =IF(OR(N(W25)<=0,N(N25)=0,N(L25)=0),"",MIN(L25,N25/W25)) -> 72.368421 | Y25: =IF(OR(X25="",N(O25)=0),"",X25/O25-1) -> -0.19862399 | Z25: =IF(OR(Y25="",N(O25)=0),"",Y25+N25/O25) -> -0.13771941 | AA25: =IF(OR(Z25="",N(U25)=0),"",Z25-U25) -> 0 | AB25: =IF(N(Q25)=0,"",Q25+IF(I25="yes",Q25*Inputs!$B$10*Inputs!$B$9,0)+IFERROR(INDEX(Inputs!$B$13:$B$15,MATCH(G25,Inputs!$A$13:$A$15,0)),0)+IFERROR(INDEX(Inputs!$B$18:$B$24,MATCH(H25,Inputs!$A$18:$A$24,0)),0)) -> 0.076 | AC25: =IF(OR(N(AB25)<=0,N(N25)=0,N(L25)=0),"",MIN(L25,N25/AB25)) -> 72.368421 | AD25: =IF(OR(AC25="",N(O25)=0),"",AC25/O25-1) -> -0.19862399 | AE25: =IF(OR(AD25="",N(O25)=0),"",AD25+N25/O25) -> -0.13771941 | AF25: =IF(OR(AE25="",N(Z25)=0),"",AE25-Z25) -> 0 | AG25: =IF(AND(N(M25)>0,N(L25)>0),M25*L25,N25) -> 5.5 | AH25: =IF(OR(N(AB25)<=0,N(AG25)=0,N(L25)=0),"",MIN(L25,AG25/AB25)) -> 72.368421 | AI25: =IF(OR(AH25="",N(O25)=0),"",AH25/O25-1) -> -0.19862399 | AJ25: =IF(OR(AI25="",N(O25)=0),"",AI25+AG25/O25) -> -0.13771941 | AK25: =IF(OR(AJ25="",N(AE25)=0),"",AJ25-AE25) -> 0 | AL25: =IF(N(F25)=0,"",INDEX(Inputs!$B$28:$B$32,IFERROR(MATCH(F25,Inputs!$A$28:$A$32,1),0)+1)) -> 0.075 | AN25: =IF(N(AM25)>0,AM25,AL25) -> 0.075 | AO25: =IF(N(AN25)=0,"",AN25+IF(I25="yes",AN25*Inputs!$B$10*Inputs!$B$9,0)+IFERROR(INDEX(Inputs!$B$13:$B$15,MATCH(G25,Inputs!$A$13:$A$15,0)),0)+IFERROR(INDEX(Inputs!$B$18:$B$24,MATCH(H25,Inputs!$A$18:$A$24,0)),0)) -> 0.07125 | AP25: =IF(OR(N(AO25)<=0,N(AG25)=0,N(L25)=0),"",MIN(L25,AG25/AO25)) -> 77.192982 | AQ25: =IF(OR(AP25="",N(O25)=0),"",AP25/O25-1) -> -0.14519892 | AR25: =IF(OR(AQ25="",N(O25)=0),"",AQ25+AG25/O25) -> -0.084294343 | AS25: =IF(OR(AR25="",N(AJ25)=0),"",AR25-AJ25) -> 0.053425067 | AT25: 100 | AU25: 5.5 | AV25: =IF(N(AT25)>0,AT25,L25) -> 100 | AW25: =IF(AND(N(M25)>0,N(AV25)>0),M25*AV25,IF(N(AU25)>0,AU25,N25)) -> 5.5 | AX25: =IF(N(AN25)=0,"",AN25+IF(I25="yes",AN25*Inputs!$B$10*Inputs!$B$9,0)+IFERROR(INDEX(Inputs!$B$13:$B$15,MATCH(G25,Inputs!$A$13:$A$15,0)),0)+IFERROR(INDEX(Inputs!$B$18:$B$24,MATCH(H25,Inputs!$A$18:$A$24,0)),0)) -> 0.07125 | AY25: =IF(OR(N(AX25)<=0,N(AW25)=0,N(AV25)=0),"",MIN(AV25,AW25/AX25)) -> 77.192982 | AZ25: =IF(OR(AY25="",N(O25)=0),"",AY25/O25-1) -> -0.14519892 | BA25: =IF(OR(AZ25="",N(O25)=0),"",AZ25+AW25/O25) -> -0.084294343 | BB25: =IF(OR(BA25="",N(AR25)=0),"",BA25-AR25) -> 0 | BC25: =IF(OR(BA25="",N(U25)=0),"",BA25-U25) -> 0.053425067
A26: A-C | B26: 45 | C26: UEPCP | D26: AEE | E26: AMEREN CORP | F26: 30100 | G26: PREFERRED | H26: FIXED | I26: yes | J26: Q | K26: 4 | L26: 100 | M26: 0.043 | N26: 4.3 | O26: 68.775 | P26: OK | Q26: 0.08 | R26: 0.076 | S26: 56.578947 | T26: -0.17733264 | U26: -0.11480993 | V26: 0 | W26: =IF(N(Q26)=0,"",Q26+IF(I26="yes",Q26*Inputs!$B$10*Inputs!$B$9,0)+V26) -> 0.076 | X26: =IF(OR(N(W26)<=0,N(N26)=0,N(L26)=0),"",MIN(L26,N26/W26)) -> 56.578947 | Y26: =IF(OR(X26="",N(O26)=0),"",X26/O26-1) -> -0.17733264 | Z26: =IF(OR(Y26="",N(O26)=0),"",Y26+N26/O26) -> -0.11480993 | AA26: =IF(OR(Z26="",N(U26)=0),"",Z26-U26) -> 0 | AB26: =IF(N(Q26)=0,"",Q26+IF(I26="yes",Q26*Inputs!$B$10*Inputs!$B$9,0)+IFERROR(INDEX(Inputs!$B$13:$B$15,MATCH(G26,Inputs!$A$13:$A$15,0)),0)+IFERROR(INDEX(Inputs!$B$18:$B$24,MATCH(H26,Inputs!$A$18:$A$24,0)),0)) -> 0.076 | AC26: =IF(OR(N(AB26)<=0,N(N26)=0,N(L26)=0),"",MIN(L26,N26/AB26)) -> 56.578947 | AD26: =IF(OR(AC26="",N(O26)=0),"",AC26/O26-1) -> -0.17733264 | AE26: =IF(OR(AD26="",N(O26)=0),"",AD26+N26/O26) -> -0.11480993 | AF26: =IF(OR(AE26="",N(Z26)=0),"",AE26-Z26) -> 0 | AG26: =IF(AND(N(M26)>0,N(L26)>0),M26*L26,N26) -> 4.3 | AH26: =IF(OR(N(AB26)<=0,N(AG26)=0,N(L26)=0),"",MIN(L26,AG26/AB26)) -> 56.578947 | AI26: =IF(OR(AH26="",N(O26)=0),"",AH26/O26-1) -> -0.17733264 | AJ26: =IF(OR(AI26="",N(O26)=0),"",AI26+AG26/O26) -> -0.11480993 | AK26: =IF(OR(AJ26="",N(AE26)=0),"",AJ26-AE26) -> 0 | AL26: =IF(N(F26)=0,"",INDEX(Inputs!$B$28:$B$32,IFERROR(MATCH(F26,Inputs!$A$28:$A$32,1),0)+1)) -> 0.075 | AN26: =IF(N(AM26)>0,AM26,AL26) -> 0.075 | AO26: =IF(N(AN26)=0,"",AN26+IF(I26="yes",AN26*Inputs!$B$10*Inputs!$B$9,0)+IFERROR(INDEX(Inputs!$B$13:$B$15,MATCH(G26,Inputs!$A$13:$A$15,0)),0)+IFERROR(INDEX(Inputs!$B$18:$B$24,MATCH(H26,Inputs!$A$18:$A$24,0)),0)) -> 0.07125 | AP26: =IF(OR(N(AO26)<=0,N(AG26)=0,N(L26)=0),"",MIN(L26,AG26/AO26)) -> 60.350877 | AQ26: =IF(OR(AP26="",N(O26)=0),"",AP26/O26-1) -> -0.12248815 | AR26: =IF(OR(AQ26="",N(O26)=0),"",AQ26+AG26/O26) -> -0.059965435 | AS26: =IF(OR(AR26="",N(AJ26)=0),"",AR26-AJ26) -> 0.05484449 | AT26: 100 | AU26: 4.3 | AV26: =IF(N(AT26)>0,AT26,L26) -> 100 | AW26: =IF(AND(N(M26)>0,N(AV26)>0),M26*AV26,IF(N(AU26)>0,AU26,N26)) -> 4.3 | AX26: =IF(N(AN26)=0,"",AN26+IF(I26="yes",AN26*Inputs!$B$10*Inputs!$B$9,0)+IFERROR(INDEX(Inputs!$B$13:$B$15,MATCH(G26,Inputs!$A$13:$A$15,0)),0)+IFERROR(INDEX(Inputs!$B$18:$B$24,MATCH(H26,Inputs!$A$18:$A$24,0)),0)) -> 0.07125 | AY26: =IF(OR(N(AX26)<=0,N(AW26)=0,N(AV26)=0),"",MIN(AV26,AW26/AX26)) -> 60.350877 | AZ26: =IF(OR(AY26="",N(O26)=0),"",AY26/O26-1) -> -0.12248815 | BA26: =IF(OR(AZ26="",N(O26)=0),"",AZ26+AW26/O26) -> -0.059965435 | BB26: =IF(OR(BA26="",N(AR26)=0),"",BA26-AR26) -> 0 | BC26: =IF(OR(BA26="",N(U26)=0),"",BA26-U26) -> 0.05484449
A27: A-C | B27: 46 | C27: UEPEM | D27: AEE | E27: AMEREN CORP | F27: 30100 | G27: PREFERRED | H27: FIXED | I27: yes | J27: Q | K27: 4 | L27: 100 | M27: 0.04 | N27: 4 | O27: 63.45 | P27: OK | Q27: 0.08 | R27: 0.076 | S27: 52.631579 | T27: -0.17050309 | U27: -0.10746132 | V27: 0 | W27: =IF(N(Q27)=0,"",Q27+IF(I27="yes",Q27*Inputs!$B$10*Inputs!$B$9,0)+V27) -> 0.076 | X27: =IF(OR(N(W27)<=0,N(N27)=0,N(L27)=0),"",MIN(L27,N27/W27)) -> 52.631579 | Y27: =IF(OR(X27="",N(O27)=0),"",X27/O27-1) -> -0.17050309 | Z27: =IF(OR(Y27="",N(O27)=0),"",Y27+N27/O27) -> -0.10746132 | AA27: =IF(OR(Z27="",N(U27)=0),"",Z27-U27) -> 0 | AB27: =IF(N(Q27)=0,"",Q27+IF(I27="yes",Q27*Inputs!$B$10*Inputs!$B$9,0)+IFERROR(INDEX(Inputs!$B$13:$B$15,MATCH(G27,Inputs!$A$13:$A$15,0)),0)+IFERROR(INDEX(Inputs!$B$18:$B$24,MATCH(H27,Inputs!$A$18:$A$24,0)),0)) -> 0.076 | AC27: =IF(OR(N(AB27)<=0,N(N27)=0,N(L27)=0),"",MIN(L27,N27/AB27)) -> 52.631579 | AD27: =IF(OR(AC27="",N(O27)=0),"",AC27/O27-1) -> -0.17050309 | AE27: =IF(OR(AD27="",N(O27)=0),"",AD27+N27/O27) -> -0.10746132 | AF27: =IF(OR(AE27="",N(Z27)=0),"",AE27-Z27) -> 0 | AG27: =IF(AND(N(M27)>0,N(L27)>0),M27*L27,N27) -> 4 | AH27: =IF(OR(N(AB27)<=0,N(AG27)=0,N(L27)=0),"",MIN(L27,AG27/AB27)) -> 52.631579 | AI27: =IF(OR(AH27="",N(O27)=0),"",AH27/O27-1) -> -0.17050309 | AJ27: =IF(OR(AI27="",N(O27)=0),"",AI27+AG27/O27) -> -0.10746132 | AK27: =IF(OR(AJ27="",N(AE27)=0),"",AJ27-AE27) -> 0 | AL27: =IF(N(F27)=0,"",INDEX(Inputs!$B$28:$B$32,IFERROR(MATCH(F27,Inputs!$A$28:$A$32,1),0)+1)) -> 0.075 | AN27: =IF(N(AM27)>0,AM27,AL27) -> 0.075 | AO27: =IF(N(AN27)=0,"",AN27+IF(I27="yes",AN27*Inputs!$B$10*Inputs!$B$9,0)+IFERROR(INDEX(Inputs!$B$13:$B$15,MATCH(G27,Inputs!$A$13:$A$15,0)),0)+IFERROR(INDEX(Inputs!$B$18:$B$24,MATCH(H27,Inputs!$A$18:$A$24,0)),0)) -> 0.07125 | AP27: =IF(OR(N(AO27)<=0,N(AG27)=0,N(L27)=0),"",MIN(L27,AG27/AO27)) -> 56.140351 | AQ27: =IF(OR(AP27="",N(O27)=0),"",AP27/O27-1) -> -0.1152033 | AR27: =IF(OR(AQ27="",N(O27)=0),"",AQ27+AG27/O27) -> -0.052161531 | AS27: =IF(OR(AR27="",N(AJ27)=0),"",AR27-AJ27) -> 0.055299794 | AT27: 100 | AU27: 4 | AV27: =IF(N(AT27)>0,AT27,L27) -> 100 | AW27: =IF(AND(N(M27)>0,N(AV27)>0),M27*AV27,IF(N(AU27)>0,AU27,N27)) -> 4 | AX27: =IF(N(AN27)=0,"",AN27+IF(I27="yes",AN27*Inputs!$B$10*Inputs!$B$9,0)+IFERROR(INDEX(Inputs!$B$13:$B$15,MATCH(G27,Inputs!$A$13:$A$15,0)),0)+IFERROR(INDEX(Inputs!$B$18:$B$24,MATCH(H27,Inputs!$A$18:$A$24,0)),0)) -> 0.07125 | AY27: =IF(OR(N(AX27)<=0,N(AW27)=0,N(AV27)=0),"",MIN(AV27,AW27/AX27)) -> 56.140351 | AZ27: =IF(OR(AY27="",N(O27)=0),"",AY27/O27-1) -> -0.1152033 | BA27: =IF(OR(AZ27="",N(O27)=0),"",AZ27+AW27/O27) -> -0.052161531 | BB27: =IF(OR(BA27="",N(AR27)=0),"",BA27-AR27) -> 0 | BC27: =IF(OR(BA27="",N(U27)=0),"",BA27-U27) -> 0.055299794
A28: A-C | B28: 47 | C28: UEPEN | D28: AEE | E28: AMEREN CORP | F28: 30100 | G28: PREFERRED | H28: FIXED | I28: yes | J28: Q | K28: 4 | L28: 100 | M28: 0.035 | N28: 3.5 | O28: 61.97 | P28: OK | Q28: 0.08 | R28: 0.076 | S28: 46.052632 | T28: -0.25685603 | U28: -0.20037709 | V28: 0 | W28: =IF(N(Q28)=0,"",Q28+IF(I28="yes",Q28*Inputs!$B$10*Inputs!$B$9,0)+V28) -> 0.076 | X28: =IF(OR(N(W28)<=0,N(N28)=0,N(L28)=0),"",MIN(L28,N28/W28)) -> 46.052632 | Y28: =IF(OR(X28="",N(O28)=0),"",X28/O28-1) -> -0.25685603 | Z28: =IF(OR(Y28="",N(O28)=0),"",Y28+N28/O28) -> -0.20037709 | AA28: =IF(OR(Z28="",N(U28)=0),"",Z28-U28) -> 0 | AB28: =IF(N(Q28)=0,"",Q28+IF(I28="yes",Q28*Inputs!$B$10*Inputs!$B$9,0)+IFERROR(INDEX(Inputs!$B$13:$B$15,MATCH(G28,Inputs!$A$13:$A$15,0)),0)+IFERROR(INDEX(Inputs!$B$18:$B$24,MATCH(H28,Inputs!$A$18:$A$24,0)),0)) -> 0.076 | AC28: =IF(OR(N(AB28)<=0,N(N28)=0,N(L28)=0),"",MIN(L28,N28/AB28)) -> 46.052632 | AD28: =IF(OR(AC28="",N(O28)=0),"",AC28/O28-1) -> -0.25685603 | AE28: =IF(OR(AD28="",N(O28)=0),"",AD28+N28/O28) -> -0.20037709 | AF28: =IF(OR(AE28="",N(Z28)=0),"",AE28-Z28) -> 0 | AG28: =IF(AND(N(M28)>0,N(L28)>0),M28*L28,N28) -> 3.5 | AH28: =IF(OR(N(AB28)<=0,N(AG28)=0,N(L28)=0),"",MIN(L28,AG28/AB28)) -> 46.052632 | AI28: =IF(OR(AH28="",N(O28)=0),"",AH28/O28-1) -> -0.25685603 | AJ28: =IF(OR(AI28="",N(O28)=0),"",AI28+AG28/O28) -> -0.20037709 | AK28: =IF(OR(AJ28="",N(AE28)=0),"",AJ28-AE28) -> 0 | AL28: =IF(N(F28)=0,"",INDEX(Inputs!$B$28:$B$32,IFERROR(MATCH(F28,Inputs!$A$28:$A$32,1),0)+1)) -> 0.075 | AN28: =IF(N(AM28)>0,AM28,AL28) -> 0.075 | AO28: =IF(N(AN28)=0,"",AN28+IF(I28="yes",AN28*Inputs!$B$10*Inputs!$B$9,0)+IFERROR(INDEX(Inputs!$B$13:$B$15,MATCH(G28,Inputs!$A$13:$A$15,0)),0)+IFERROR(INDEX(Inputs!$B$18:$B$24,MATCH(H28,Inputs!$A$18:$A$24,0)),0)) -> 0.07125 | AP28: =IF(OR(N(AO28)<=0,N(AG28)=0,N(L28)=0),"",MIN(L28,AG28/AO28)) -> 49.122807 | AQ28: =IF(OR(AP28="",N(O28)=0),"",AP28/O28-1) -> -0.2073131 | AR28: =IF(OR(AQ28="",N(O28)=0),"",AQ28+AG28/O28) -> -0.15083416 | AS28: =IF(OR(AR28="",N(AJ28)=0),"",AR28-AJ28) -> 0.049542931 | AT28: 100 | AU28: 3.5 | AV28: =IF(N(AT28)>0,AT28,L28) -> 100 | AW28: =IF(AND(N(M28)>0,N(AV28)>0),M28*AV28,IF(N(AU28)>0,AU28,N28)) -> 3.5 | AX28: =IF(N(AN28)=0,"",AN28+IF(I28="yes",AN28*Inputs!$B$10*Inputs!$B$9,0)+IFERROR(INDEX(Inputs!$B$13:$B$15,MATCH(G28,Inputs!$A$13:$A$15,0)),0)+IFERROR(INDEX(Inputs!$B$18:$B$24,MATCH(H28,Inputs!$A$18:$A$24,0)),0)) -> 0.07125 | AY28: =IF(OR(N(AX28)<=0,N(AW28)=0,N(AV28)=0),"",MIN(AV28,AW28/AX28)) -> 49.122807 | AZ28: =IF(OR(AY28="",N(O28)=0),"",AY28/O28-1) -> -0.2073131 | BA28: =IF(OR(AZ28="",N(O28)=0),"",AZ28+AW28/O28) -> -0.15083416 | BB28: =IF(OR(BA28="",N(AR28)=0),"",BA28-AR28) -> 0 | BC28: =IF(OR(BA28="",N(U28)=0),"",BA28-U28) -> 0.049542931
A29: A-C | B29: 48 | C29: UEPEO | D29: AEE | E29: AMEREN CORP | F29: 30100 | G29: PREFERRED | H29: FIXED | I29: yes | J29: Q | K29: 4 | L29: 100 | M29: 0.045 | N29: 4.5 | O29: 71.99 | P29: OK | Q29: 0.08 | R29: 0.076 | S29: 59.210526 | T29: -0.17751735 | U29: -0.11500866 | V29: 0 | W29: =IF(N(Q29)=0,"",Q29+IF(I29="yes",Q29*Inputs!$B$10*Inputs!$B$9,0)+V29) -> 0.076 | X29: =IF(OR(N(W29)<=0,N(N29)=0,N(L29)=0),"",MIN(L29,N29/W29)) -> 59.210526 | Y29: =IF(OR(X29="",N(O29)=0),"",X29/O29-1) -> -0.17751735 | Z29: =IF(OR(Y29="",N(O29)=0),"",Y29+N29/O29) -> -0.11500866 | AA29: =IF(OR(Z29="",N(U29)=0),"",Z29-U29) -> 0 | AB29: =IF(N(Q29)=0,"",Q29+IF(I29="yes",Q29*Inputs!$B$10*Inputs!$B$9,0)+IFERROR(INDEX(Inputs!$B$13:$B$15,MATCH(G29,Inputs!$A$13:$A$15,0)),0)+IFERROR(INDEX(Inputs!$B$18:$B$24,MATCH(H29,Inputs!$A$18:$A$24,0)),0)) -> 0.076 | AC29: =IF(OR(N(AB29)<=0,N(N29)=0,N(L29)=0),"",MIN(L29,N29/AB29)) -> 59.210526 | AD29: =IF(OR(AC29="",N(O29)=0),"",AC29/O29-1) -> -0.17751735 | AE29: =IF(OR(AD29="",N(O29)=0),"",AD29+N29/O29) -> -0.11500866 | AF29: =IF(OR(AE29="",N(Z29)=0),"",AE29-Z29) -> 0 | AG29: =IF(AND(N(M29)>0,N(L29)>0),M29*L29,N29) -> 4.5 | AH29: =IF(OR(N(AB29)<=0,N(AG29)=0,N(L29)=0),"",MIN(L29,AG29/AB29)) -> 59.210526 | AI29: =IF(OR(AH29="",N(O29)=0),"",AH29/O29-1) -> -0.17751735 | AJ29: =IF(OR(AI29="",N(O29)=0),"",AI29+AG29/O29) -> -0.11500866 | AK29: =IF(OR(AJ29="",N(AE29)=0),"",AJ29-AE29) -> 0 | AL29: =IF(N(F29)=0,"",INDEX(Inputs!$B$28:$B$32,IFERROR(MATCH(F29,Inputs!$A$28:$A$32,1),0)+1)) -> 0.075 | AN29: =IF(N(AM29)>0,AM29,AL29) -> 0.075 | AO29: =IF(N(AN29)=0,"",AN29+IF(I29="yes",AN29*Inputs!$B$10*Inputs!$B$9,0)+IFERROR(INDEX(Inputs!$B$13:$B$15,MATCH(G29,Inputs!$A$13:$A$15,0)),0)+IFERROR(INDEX(Inputs!$B$18:$B$24,MATCH(H29,Inputs!$A$18:$A$24,0)),0)) -> 0.07125 | AP29: =IF(OR(N(AO29)<=0,N(AG29)=0,N(L29)=0),"",MIN(L29,AG29/AO29)) -> 63.157895 | AQ29: =IF(OR(AP29="",N(O29)=0),"",AP29/O29-1) -> -0.12268517 | AR29: =IF(OR(AQ29="",N(O29)=0),"",AQ29+AG29/O29) -> -0.060176487 | AS29: =IF(OR(AR29="",N(AJ29)=0),"",AR29-AJ29) -> 0.054832177 | AT29: 100 | AU29: 4.5 | AV29: =IF(N(AT29)>0,AT29,L29) -> 100 | AW29: =IF(AND(N(M29)>0,N(AV29)>0),M29*AV29,IF(N(AU29)>0,AU29,N29)) -> 4.5 | AX29: =IF(N(AN29)=0,"",AN29+IF(I29="yes",AN29*Inputs!$B$10*Inputs!$B$9,0)+IFERROR(INDEX(Inputs!$B$13:$B$15,MATCH(G29,Inputs!$A$13:$A$15,0)),0)+IFERROR(INDEX(Inputs!$B$18:$B$24,MATCH(H29,Inputs!$A$18:$A$24,0)),0)) -> 0.07125 | AY29: =IF(OR(N(AX29)<=0,N(AW29)=0,N(AV29)=0),"",MIN(AV29,AW29/AX29)) -> 63.157895 | AZ29: =IF(OR(AY29="",N(O29)=0),"",AY29/O29-1) -> -0.12268517 | BA29: =IF(OR(AZ29="",N(O29)=0),"",AZ29+AW29/O29) -> -0.060176487 | BB29: =IF(OR(BA29="",N(AR29)=0),"",BA29-AR29) -> 0 | BC29: =IF(OR(BA29="",N(U29)=0),"",BA29-U29) -> 0.054832177
... A31: A-C | B31: 52 | C31: AEFC | D31: AEG | E31: AEGON LTD AMER REG 1 CERT | F31: 14200 | G31: BABY_BOND | H31: FIXED | I31: no | J31: Q | K31: 4 | L31: 25 | M31: 0.051 | N31: 1.275 | O31: 18.12 | P31: OK | Q31: 0.08 | R31: 0.075 | S31: 17 | T31: -0.061810155 | U31: 0.0085540839 | V31: -0.005 | W31: =IF(N(Q31)=0,"",Q31+IF(I31="yes",Q31*Inputs!$B$10*Inputs!$B$9,0)+V31) -> 0.075 | X31: =IF(OR(N(W31)<=0,N(N31)=0,N(L31)=0),"",MIN(L31,N31/W31)) -> 17 | Y31: =IF(OR(X31="",N(O31)=0),"",X31/O31-1) -> -0.061810155 | Z31: =IF(OR(Y31="",N(O31)=0),"",Y31+N31/O31) -> 0.0085540839 | AA31: =IF(OR(Z31="",N(U31)=0),"",Z31-U31) -> 0 | AB31: =IF(N(Q31)=0,"",Q31+IF(I31="yes",Q31*Inputs!$B$10*Inputs!$B$9,0)+IFERROR(INDEX(Inputs!$B$13:$B$15,MATCH(G31,Inputs!$A$13:$A$15,0)),0)+IFERROR(INDEX(Inputs!$B$18:$B$24,MATCH(H31,Inputs!$A$18:$A$24,0)),0)) -> 0.075 | AC31: =IF(OR(N(AB31)<=0,N(N31)=0,N(L31)=0),"",MIN(L31,N31/AB31)) -> 17 | AD31: =IF(OR(AC31="",N(O31)=0),"",AC31/O31-1) -> -0.061810155 | AE31: =IF(OR(AD31="",N(O31)=0),"",AD31+N31/O31) -> 0.0085540839 | AF31: =IF(OR(AE31="",N(Z31)=0),"",AE31-Z31) -> 0 | AG31: =IF(AND(N(M31)>0,N(L31)>0),M31*L31,N31) -> 1.275 | AH31: =IF(OR(N(AB31)<=0,N(AG31)=0,N(L31)=0),"",MIN(L31,AG31/AB31)) -> 17 | AI31: =IF(OR(AH31="",N(O31)=0),"",AH31/O31-1) -> -0.061810155 | AJ31: =IF(OR(AI31="",N(O31)=0),"",AI31+AG31/O31) -> 0.0085540839 | AK31: =IF(OR(AJ31="",N(AE31)=0),"",AJ31-AE31) -> 0 | AL31: =IF(N(F31)=0,"",INDEX(Inputs!$B$28:$B$32,IFERROR(MATCH(F31,Inputs!$A$28:$A$32,1),0)+1)) -> 0.08 | AN31: =IF(N(AM31)>0,AM31,AL31) -> 0.08 | AO31: =IF(N(AN31)=0,"",AN31+IF(I31="yes",AN31*Inputs!$B$10*Inputs!$B$9,0)+IFERROR(INDEX(Inputs!$B$13:$B$15,MATCH(G31,Inputs!$A$13:$A$15,0)),0)+IFERROR(INDEX(Inputs!$B$18:$B$24,MATCH(H31,Inputs!$A$18:$A$24,0)),0)) -> 0.075 | AP31: =IF(OR(N(AO31)<=0,N(AG31)=0,N(L31)=0),"",MIN(L31,AG31/AO31)) -> 17 | AQ31: =IF(OR(AP31="",N(O31)=0),"",AP31/O31-1) -> -0.061810155 | AR31: =IF(OR(AQ31="",N(O31)=0),"",AQ31+AG31/O31) -> 0.0085540839 | AS31: =IF(OR(AR31="",N(AJ31)=0),"",AR31-AJ31) -> 0 | AT31: 25 | AU31: 1.28 | AV31: =IF(N(AT31)>0,AT31,L31) -> 25 | AW31: =IF(AND(N(M31)>0,N(AV31)>0),M31*AV31,IF(N(AU31)>0,AU31,N31)) -> 1.275 | AX31: =IF(N(AN31)=0,"",AN31+IF(I31="yes",AN31*Inputs!$B$10*Inputs!$B$9,0)+IFERROR(INDEX(Inputs!$B$13:$B$15,MATCH(G31,Inputs!$A$13:$A$15,0)),0)+IFERROR(INDEX(Inputs!$B$18:$B$24,MATCH(H31,Inputs!$A$18:$A$24,0)),0)) -> 0.075 | AY31: =IF(OR(N(AX31)<=0,N(AW31)=0,N(AV31)=0),"",MIN(AV31,AW31/AX31)) -> 17 | AZ31: =IF(OR(AY31="",N(O31)=0),"",AY31/O31-1) -> -0.061810155 | BA31: =IF(OR(AZ31="",N(O31)=0),"",AZ31+AW31/O31) -> 0.0085540839 | BB31: =IF(OR(BA31="",N(AR31)=0),"",BA31-AR31) -> 0 | BC31: =IF(OR(BA31="",N(U31)=0),"",BA31-U31) -> 0
A32: A-C | B32: 56 | C32: AEL-A | D32: AEL | E32: na | G32: PREFERRED | H32: FIX_TO_FLOAT | I32: yes | J32: Q | K32: 4 | L32: 25 | M32: 0.0595 | N32: 1.4875 | O32: 0 | P32: OK | Q32: 0 | R32: 0 | V32: 0 | W32: =IF(N(Q32)=0,"",Q32+IF(I32="yes",Q32*Inputs!$B$10*Inputs!$B$9,0)+V32) | X32: =IF(OR(N(W32)<=0,N(N32)=0,N(L32)=0),"",MIN(L32,N32/W32)) | Y32: =IF(OR(X32="",N(O32)=0),"",X32/O32-1) | Z32: =IF(OR(Y32="",N(O32)=0),"",Y32+N32/O32) | AA32: =IF(OR(Z32="",N(U32)=0),"",Z32-U32) | AB32: =IF(N(Q32)=0,"",Q32+IF(I32="yes",Q32*Inputs!$B$10*Inputs!$B$9,0)+IFERROR(INDEX(Inputs!$B$13:$B$15,MATCH(G32,Inputs!$A$13:$A$15,0)),0)+IFERROR(INDEX(Inputs!$B$18:$B$24,MATCH(H32,Inputs!$A$18:$A$24,0)),0)) | AC32: =IF(OR(N(AB32)<=0,N(N32)=0,N(L32)=0),"",MIN(L32,N32/AB32)) | AD32: =IF(OR(AC32="",N(O32)=0),"",AC32/O32-1) | AE32: =IF(OR(AD32="",N(O32)=0),"",AD32+N32/O32) | AF32: =IF(OR(AE32="",N(Z32)=0),"",AE32-Z32) | AG32: =IF(AND(N(M32)>0,N(L32)>0),M32*L32,N32) -> 1.4875 | AH32: =IF(OR(N(AB32)<=0,N(AG32)=0,N(L32)=0),"",MIN(L32,AG32/AB32)) | AI32: =IF(OR(AH32="",N(O32)=0),"",AH32/O32-1) | AJ32: =IF(OR(AI32="",N(O32)=0),"",AI32+AG32/O32) | AK32: =IF(OR(AJ32="",N(AE32)=0),"",AJ32-AE32) | AL32: =IF(N(F32)=0,"",INDEX(Inputs!$B$28:$B$32,IFERROR(MATCH(F32,Inputs!$A$28:$A$32,1),0)+1)) | AN32: =IF(N(AM32)>0,AM32,AL32) | AO32: =IF(N(AN32)=0,"",AN32+IF(I32="yes",AN32*Inputs!$B$10*Inputs!$B$9,0)+IFERROR(INDEX(Inputs!$B$13:$B$15,MATCH(G32,Inputs!$A$13:$A$15,0)),0)+IFERROR(INDEX(Inputs!$B$18:$B$24,MATCH(H32,Inputs!$A$18:$A$24,0)),0)) | AP32: =IF(OR(N(AO32)<=0,N(AG32)=0,N(L32)=0),"",MIN(L32,AG32/AO32)) | AQ32: =IF(OR(AP32="",N(O32)=0),"",AP32/O32-1) | AR32: =IF(OR(AQ32="",N(O32)=0),"",AQ32+AG32/O32) | AS32: =IF(OR(AR32="",N(AJ32)=0),"",AR32-AJ32) | AV32: =IF(N(AT32)>0,AT32,L32) -> 25 | AW32: =IF(AND(N(M32)>0,N(AV32)>0),M32*AV32,IF(N(AU32)>0,AU32,N32)) -> 1.4875 | AX32: =IF(N(AN32)=0,"",AN32+IF(I32="yes",AN32*Inputs!$B$10*Inputs!$B$9,0)+IFERROR(INDEX(Inputs!$B$13:$B$15,MATCH(G32,Inputs!$A$13:$A$15,0)),0)+IFERROR(INDEX(Inputs!$B$18:$B$24,MATCH(H32,Inputs!$A$18:$A$24,0)),0)) | AY32: =IF(OR(N(AX32)<=0,N(AW32)=0,N(AV32)=0),"",MIN(AV32,AW32/AX32)) | AZ32: =IF(OR(AY32="",N(O32)=0),"",AY32/O32-1) | BA32: =IF(OR(AZ32="",N(O32)=0),"",AZ32+AW32/O32) | BB32: =IF(OR(BA32="",N(AR32)=0),"",BA32-AR32) | BC32: =IF(OR(BA32="",N(U32)=0),"",BA32-U32) | BD32: NO PRICE; not in QOL paste - retire/rename?; group base = 0 (parent did not quote)
A33: A-C | B33: 60 | C33: AESC | D33: AES | E33: AES CORP | F33: 10500 | G33: PREFERRED | H33: MAND_CONVERT | I33: no | J33: Q | K33: 4 | L33: 100 | M33: 0.06875 | N33: 6.875 | O33: 0 | P33: OK | Q33: 0.09 | R33: 0.09 | S33: 76.388889 | V33: 0 | W33: =IF(N(Q33)=0,"",Q33+IF(I33="yes",Q33*Inputs!$B$10*Inputs!$B$9,0)+V33) -> 0.09 | X33: =IF(OR(N(W33)<=0,N(N33)=0,N(L33)=0),"",MIN(L33,N33/W33)) -> 76.388889 | Y33: =IF(OR(X33="",N(O33)=0),"",X33/O33-1) | Z33: =IF(OR(Y33="",N(O33)=0),"",Y33+N33/O33) | AA33: =IF(OR(Z33="",N(U33)=0),"",Z33-U33) | AB33: =IF(N(Q33)=0,"",Q33+IF(I33="yes",Q33*Inputs!$B$10*Inputs!$B$9,0)+IFERROR(INDEX(Inputs!$B$13:$B$15,MATCH(G33,Inputs!$A$13:$A$15,0)),0)+IFERROR(INDEX(Inputs!$B$18:$B$24,MATCH(H33,Inputs!$A$18:$A$24,0)),0)) -> 0.09 | AC33: =IF(OR(N(AB33)<=0,N(N33)=0,N(L33)=0),"",MIN(L33,N33/AB33)) -> 76.388889 | AD33: =IF(OR(AC33="",N(O33)=0),"",AC33/O33-1) | AE33: =IF(OR(AD33="",N(O33)=0),"",AD33+N33/O33) | AF33: =IF(OR(AE33="",N(Z33)=0),"",AE33-Z33) | AG33: =IF(AND(N(M33)>0,N(L33)>0),M33*L33,N33) -> 6.875 | AH33: =IF(OR(N(AB33)<=0,N(AG33)=0,N(L33)=0),"",MIN(L33,AG33/AB33)) -> 76.388889 | AI33: =IF(OR(AH33="",N(O33)=0),"",AH33/O33-1) | AJ33: =IF(OR(AI33="",N(O33)=0),"",AI33+AG33/O33) | AK33: =IF(OR(AJ33="",N(AE33)=0),"",AJ33-AE33) | AL33: =IF(N(F33)=0,"",INDEX(Inputs!$B$28:$B$32,IFERROR(MATCH(F33,Inputs!$A$28:$A$32,1),0)+1)) -> 0.08 | AN33: =IF(N(AM33)>0,AM33,AL33) -> 0.08 | AO33: =IF(N(AN33)=0,"",AN33+IF(I33="yes",AN33*Inputs!$B$10*Inputs!$B$9,0)+IFERROR(INDEX(Inputs!$B$13:$B$15,MATCH(G33,Inputs!$A$13:$A$15,0)),0)+IFERROR(INDEX(Inputs!$B$18:$B$24,MATCH(H33,Inputs!$A$18:$A$24,0)),0)) -> 0.08 | AP33: =IF(OR(N(AO33)<=0,N(AG33)=0,N(L33)=0),"",MIN(L33,AG33/AO33)) -> 85.9375 | AQ33: =IF(OR(AP33="",N(O33)=0),"",AP33/O33-1) | AR33: =IF(OR(AQ33="",N(O33)=0),"",AQ33+AG33/O33) | AS33: =IF(OR(AR33="",N(AJ33)=0),"",AR33-AJ33) | AV33: =IF(N(AT33)>0,AT33,L33) -> 100 | AW33: =IF(AND(N(M33)>0,N(AV33)>0),M33*AV33,IF(N(AU33)>0,AU33,N33)) -> 6.875 | AX33: =IF(N(AN33)=0,"",AN33+IF(I33="yes",AN33*Inputs!$B$10*Inputs!$B$9,0)+IFERROR(INDEX(Inputs!$B$13:$B$15,MATCH(G33,Inputs!$A$13:$A$15,0)),0)+IFERROR(INDEX(Inputs!$B$18:$B$24,MATCH(H33,Inputs!$A$18:$A$24,0)),0)) -> 0.08 | AY33: =IF(OR(N(AX33)<=0,N(AW33)=0,N(AV33)=0),"",MIN(AV33,AW33/AX33)) -> 85.9375 | AZ33: =IF(OR(AY33="",N(O33)=0),"",AY33/O33-1) | BA33: =IF(OR(AZ33="",N(O33)=0),"",AZ33+AW33/O33) | BB33: =IF(OR(BA33="",N(AR33)=0),"",BA33-AR33) | BC33: =IF(OR(BA33="",N(U33)=0),"",BA33-U33) | BD33: NO PRICE; not in QOL paste - retire/rename?
A34: A-C | B34: 64 | C34: AFGB | D34: AFG | E34: AMERICAN FINANCIAL GROUP INC | F34: 11900 | G34: BABY_BOND | H34: FIXED | I34: no | J34: Q | K34: 4 | L34: 25 | M34: 0.05875 | N34: 1.46875 | O34: 20.19 | P34: OK | Q34: 0.08 | R34: 0.075 | S34: 19.583333 | T34: -0.030047878 | U34: 0.042698531 | V34: -0.005 | W34: =IF(N(Q34)=0,"",Q34+IF(I34="yes",Q34*Inputs!$B$10*Inputs!$B$9,0)+V34) -> 0.075 | X34: =IF(OR(N(W34)<=0,N(N34)=0,N(L34)=0),"",MIN(L34,N34/W34)) -> 19.583333 | Y34: =IF(OR(X34="",N(O34)=0),"",X34/O34-1) -> -0.030047878 | Z34: =IF(OR(Y34="",N(O34)=0),"",Y34+N34/O34) -> 0.042698531 | AA34: =IF(OR(Z34="",N(U34)=0),"",Z34-U34) -> 0 | AB34: =IF(N(Q34)=0,"",Q34+IF(I34="yes",Q34*Inputs!$B$10*Inputs!$B$9,0)+IFERROR(INDEX(Inputs!$B$13:$B$15,MATCH(G34,Inputs!$A$13:$A$15,0)),0)+IFERROR(INDEX(Inputs!$B$18:$B$24,MATCH(H34,Inputs!$A$18:$A$24,0)),0)) -> 0.075 | AC34: =IF(OR(N(AB34)<=0,N(N34)=0,N(L34)=0),"",MIN(L34,N34/AB34)) -> 19.583333 | AD34: =IF(OR(AC34="",N(O34)=0),"",AC34/O34-1) -> -0.030047878 | AE34: =IF(OR(AD34="",N(O34)=0),"",AD34+N34/O34) -> 0.042698531 | AF34: =IF(OR(AE34="",N(Z34)=0),"",AE34-Z34) -> 0 | AG34: =IF(AND(N(M34)>0,N(L34)>0),M34*L34,N34) -> 1.46875 | AH34: =IF(OR(N(AB34)<=0,N(AG34)=0,N(L34)=0),"",MIN(L34,AG34/AB34)) -> 19.583333 | AI34: =IF(OR(AH34="",N(O34)=0),"",AH34/O34-1) -> -0.030047878 | AJ34: =IF(OR(AI34="",N(O34)=0),"",AI34+AG34/O34) -> 0.042698531 | AK34: =IF(OR(AJ34="",N(AE34)=0),"",AJ34-AE34) -> 0 | AL34: =IF(N(F34)=0,"",INDEX(Inputs!$B$28:$B$32,IFERROR(MATCH(F34,Inputs!$A$28:$A$32,1),0)+1)) -> 0.08 | AN34: =IF(N(AM34)>0,AM34,AL34) -> 0.08 | AO34: =IF(N(AN34)=0,"",AN34+IF(I34="yes",AN34*Inputs!$B$10*Inputs!$B$9,0)+IFERROR(INDEX(Inputs!$B$13:$B$15,MATCH(G34,Inputs!$A$13:$A$15,0)),0)+IFERROR(INDEX(Inputs!$B$18:$B$24,MATCH(H34,Inputs!$A$18:$A$24,0)),0)) -> 0.075 | AP34: =IF(OR(N(AO34)<=0,N(AG34)=0,N(L34)=0),"",MIN(L34,AG34/AO34)) -> 19.583333 | AQ34: =IF(OR(AP34="",N(O34)=0),"",AP34/O34-1) -> -0.030047878 | AR34: =IF(OR(AQ34="",N(O34)=0),"",AQ34+AG34/O34) -> 0.042698531 | AS34: =IF(OR(AR34="",N(AJ34)=0),"",AR34-AJ34) -> 0 | AT34: 25 | AU34: 1.47 | AV34: =IF(N(AT34)>0,AT34,L34) -> 25 | AW34: =IF(AND(N(M34)>0,N(AV34)>0),M34*AV34,IF(N(AU34)>0,AU34,N34)) -> 1.46875 | AX34: =IF(N(AN34)=0,"",AN34+IF(I34="yes",AN34*Inputs!$B$10*Inputs!$B$9,0)+IFERROR(INDEX(Inputs!$B$13:$B$15,MATCH(G34,Inputs!$A$13:$A$15,0)),0)+IFERROR(INDEX(Inputs!$B$18:$B$24,MATCH(H34,Inputs!$A$18:$A$24,0)),0)) -> 0.075 | AY34: =IF(OR(N(AX34)<=0,N(AW34)=0,N(AV34)=0),"",MIN(AV34,AW34/AX34)) -> 19.583333 | AZ34: =IF(OR(AY34="",N(O34)=0),"",AY34/O34-1) -> -0.030047878 | BA34: =IF(OR(AZ34="",N(O34)=0),"",AZ34+AW34/O34) -> 0.042698531 | BB34: =IF(OR(BA34="",N(AR34)=0),"",BA34-AR34) -> 0 | BC34: =IF(OR(BA34="",N(U34)=0),"",BA34-U34) -> 0
A35: A-C | B35: 65 | C35: AFGC | D35: AFG | E35: AMERICAN FINANCIAL GROUP INC | F35: 11900 | G35: BABY_BOND | H35: FIXED | I35: no | J35: Q | K35: 4 | L35: 25 | M35: 0.05125 | N35: 1.28125 | O35: 17.75 | P35: OK | Q35: 0.08 | R35: 0.075 | S35: 17.083333 | T35: -0.037558685 | U35: 0.034624413 | V35: -0.005 | W35: =IF(N(Q35)=0,"",Q35+IF(I35="yes",Q35*Inputs!$B$10*Inputs!$B$9,0)+V35) -> 0.075 | X35: =IF(OR(N(W35)<=0,N(N35)=0,N(L35)=0),"",MIN(L35,N35/W35)) -> 17.083333 | Y35: =IF(OR(X35="",N(O35)=0),"",X35/O35-1) -> -0.037558685 | Z35: =IF(OR(Y35="",N(O35)=0),"",Y35+N35/O35) -> 0.034624413 | AA35: =IF(OR(Z35="",N(U35)=0),"",Z35-U35) -> 0 | AB35: =IF(N(Q35)=0,"",Q35+IF(I35="yes",Q35*Inputs!$B$10*Inputs!$B$9,0)+IFERROR(INDEX(Inputs!$B$13:$B$15,MATCH(G35,Inputs!$A$13:$A$15,0)),0)+IFERROR(INDEX(Inputs!$B$18:$B$24,MATCH(H35,Inputs!$A$18:$A$24,0)),0)) -> 0.075 | AC35: =IF(OR(N(AB35)<=0,N(N35)=0,N(L35)=0),"",MIN(L35,N35/AB35)) -> 17.083333 | AD35: =IF(OR(AC35="",N(O35)=0),"",AC35/O35-1) -> -0.037558685 | AE35: =IF(OR(AD35="",N(O35)=0),"",AD35+N35/O35) -> 0.034624413 | AF35: =IF(OR(AE35="",N(Z35)=0),"",AE35-Z35) -> 0 | AG35: =IF(AND(N(M35)>0,N(L35)>0),M35*L35,N35) -> 1.28125 | AH35: =IF(OR(N(AB35)<=0,N(AG35)=0,N(L35)=0),"",MIN(L35,AG35/AB35)) -> 17.083333 | AI35: =IF(OR(AH35="",N(O35)=0),"",AH35/O35-1) -> -0.037558685 | AJ35: =IF(OR(AI35="",N(O35)=0),"",AI35+AG35/O35) -> 0.034624413 | AK35: =IF(OR(AJ35="",N(AE35)=0),"",AJ35-AE35) -> 0 | AL35: =IF(N(F35)=0,"",INDEX(Inputs!$B$28:$B$32,IFERROR(MATCH(F35,Inputs!$A$28:$A$32,1),0)+1)) -> 0.08 | AN35: =IF(N(AM35)>0,AM35,AL35) -> 0.08 | AO35: =IF(N(AN35)=0,"",AN35+IF(I35="yes",AN35*Inputs!$B$10*Inputs!$B$9,0)+IFERROR(INDEX(Inputs!$B$13:$B$15,MATCH(G35,Inputs!$A$13:$A$15,0)),0)+IFERROR(INDEX(Inputs!$B$18:$B$24,MATCH(H35,Inputs!$A$18:$A$24,0)),0)) -> 0.075 | AP35: =IF(OR(N(AO35)<=0,N(AG35)=0,N(L35)=0),"",MIN(L35,AG35/AO35)) -> 17.083333 | AQ35: =IF(OR(AP35="",N(O35)=0),"",AP35/O35-1) -> -0.037558685 | AR35: =IF(OR(AQ35="",N(O35)=0),"",AQ35+AG35/O35) -> 0.034624413 | AS35: =IF(OR(AR35="",N(AJ35)=0),"",AR35-AJ35) -> 0 | AT35: 25 | AU35: 1.28 | AV35: =IF(N(AT35)>0,AT35,L35) -> 25 | AW35: =IF(AND(N(M35)>0,N(AV35)>0),M35*AV35,IF(N(AU35)>0,AU35,N35)) -> 1.28125 | AX35: =IF(N(AN35)=0,"",AN35+IF(I35="yes",AN35*Inputs!$B$10*Inputs!$B$9,0)+IFERROR(INDEX(Inputs!$B$13:$B$15,MATCH(G35,Inputs!$A$13:$A$15,0)),0)+IFERROR(INDEX(Inputs!$B$18:$B$24,MATCH(H35,Inputs!$A$18:$A$24,0)),0)) -> 0.075 | AY35: =IF(OR(N(AX35)<=0,N(AW35)=0,N(AV35)=0),"",MIN(AV35,AW35/AX35)) -> 17.083333 | AZ35: =IF(OR(AY35="",N(O35)=0),"",AY35/O35-1) -> -0.037558685 | BA35: =IF(OR(AZ35="",N(O35)=0),"",AZ35+AW35/O35) -> 0.034624413 | BB35: =IF(OR(BA35="",N(AR35)=0),"",BA35-AR35) -> 0 | BC35: =IF(OR(BA35="",N(U35)=0),"",BA35-U35) -> 0
A36: A-C | B36: 66 | C36: AFGD | D36: AFG | E36: AMERICAN FINANCIAL GROUP INC | F36: 11900 | G36: BABY_BOND | H36: FIXED | I36: no | J36: Q | K36: 4 | L36: 25 | M36: 0.05625 | N36: 1.40625 | O36: 19.92 | P36: OK | Q36: 0.08 | R36: 0.075 | S36: 18.75 | T36: -0.05873494 | U36: 0.01185994 | V36: -0.005 | W36: =IF(N(Q36)=0,"",Q36+IF(I36="yes",Q36*Inputs!$B$10*Inputs!$B$9,0)+V36) -> 0.075 | X36: =IF(OR(N(W36)<=0,N(N36)=0,N(L36)=0),"",MIN(L36,N36/W36)) -> 18.75 | Y36: =IF(OR(X36="",N(O36)=0),"",X36/O36-1) -> -0.05873494 | Z36: =IF(OR(Y36="",N(O36)=0),"",Y36+N36/O36) -> 0.01185994 | AA36: =IF(OR(Z36="",N(U36)=0),"",Z36-U36) -> 0 | AB36: =IF(N(Q36)=0,"",Q36+IF(I36="yes",Q36*Inputs!$B$10*Inputs!$B$9,0)+IFERROR(INDEX(Inputs!$B$13:$B$15,MATCH(G36,Inputs!$A$13:$A$15,0)),0)+IFERROR(INDEX(Inputs!$B$18:$B$24,MATCH(H36,Inputs!$A$18:$A$24,0)),0)) -> 0.075 | AC36: =IF(OR(N(AB36)<=0,N(N36)=0,N(L36)=0),"",MIN(L36,N36/AB36)) -> 18.75 | AD36: =IF(OR(AC36="",N(O36)=0),"",AC36/O36-1) -> -0.05873494 | AE36: =IF(OR(AD36="",N(O36)=0),"",AD36+N36/O36) -> 0.01185994 | AF36: =IF(OR(AE36="",N(Z36)=0),"",AE36-Z36) -> 0 | AG36: =IF(AND(N(M36)>0,N(L36)>0),M36*L36,N36) -> 1.40625 | AH36: =IF(OR(N(AB36)<=0,N(AG36)=0,N(L36)=0),"",MIN(L36,AG36/AB36)) -> 18.75 | AI36: =IF(OR(AH36="",N(O36)=0),"",AH36/O36-1) -> -0.05873494 | AJ36: =IF(OR(AI36="",N(O36)=0),"",AI36+AG36/O36) -> 0.01185994 | AK36: =IF(OR(AJ36="",N(AE36)=0),"",AJ36-AE36) -> 0 | AL36: =IF(N(F36)=0,"",INDEX(Inputs!$B$28:$B$32,IFERROR(MATCH(F36,Inputs!$A$28:$A$32,1),0)+1)) -> 0.08 | AN36: =IF(N(AM36)>0,AM36,AL36) -> 0.08 | AO36: =IF(N(AN36)=0,"",AN36+IF(I36="yes",AN36*Inputs!$B$10*Inputs!$B$9,0)+IFERROR(INDEX(Inputs!$B$13:$B$15,MATCH(G36,Inputs!$A$13:$A$15,0)),0)+IFERROR(INDEX(Inputs!$B$18:$B$24,MATCH(H36,Inputs!$A$18:$A$24,0)),0)) -> 0.075 | AP36: =IF(OR(N(AO36)<=0,N(AG36)=0,N(L36)=0),"",MIN(L36,AG36/AO36)) -> 18.75 | AQ36: =IF(OR(AP36="",N(O36)=0),"",AP36/O36-1) -> -0.05873494 | AR36: =IF(OR(AQ36="",N(O36)=0),"",AQ36+AG36/O36) -> 0.01185994 | AS36: =IF(OR(AR36="",N(AJ36)=0),"",AR36-AJ36) -> 0 | AT36: 25 | AU36: 1.40625 | AV36: =IF(N(AT36)>0,AT36,L36) -> 25 | AW36: =IF(AND(N(M36)>0,N(AV36)>0),M36*AV36,IF(N(AU36)>0,AU36,N36)) -> 1.40625 | AX36: =IF(N(AN36)=0,"",AN36+IF(I36="yes",AN36*Inputs!$B$10*Inputs!$B$9,0)+IFERROR(INDEX(Inputs!$B$13:$B$15,MATCH(G36,Inputs!$A$13:$A$15,0)),0)+IFERROR(INDEX(Inputs!$B$18:$B$24,MATCH(H36,Inputs!$A$18:$A$24,0)),0)) -> 0.075 | AY36: =IF(OR(N(AX36)<=0,N(AW36)=0,N(AV36)=0),"",MIN(AV36,AW36/AX36)) -> 18.75 | AZ36: =IF(OR(AY36="",N(O36)=0),"",AY36/O36-1) -> -0.05873494 | BA36: =IF(OR(AZ36="",N(O36)=0),"",AZ36+AW36/O36) -> 0.01185994 | BB36: =IF(OR(BA36="",N(AR36)=0),"",BA36-AR36) -> 0 | BC36: =IF(OR(BA36="",N(U36)=0),"",BA36-U36) -> 0
A37: A-C | B37: 67 | C37: AFGE | D37: AFG | E37: AMERICAN FINANCIAL GROUP INC | F37: 11900 | G37: BABY_BOND | H37: FIXED | I37: no | J37: Q | K37: 4 | L37: 25 | M37: 0.045 | N37: 1.125 | O37: 16.11 | P37: OK | Q37: 0.08 | R37: 0.075 | S37: 15 | T37: -0.068901304 | U37: 0.0009310987 | V37: -0.005 | W37: =IF(N(Q37)=0,"",Q37+IF(I37="yes",Q37*Inputs!$B$10*Inputs!$B$9,0)+V37) -> 0.075 | X37: =IF(OR(N(W37)<=0,N(N37)=0,N(L37)=0),"",MIN(L37,N37/W37)) -> 15 | Y37: =IF(OR(X37="",N(O37)=0),"",X37/O37-1) -> -0.068901304 | Z37: =IF(OR(Y37="",N(O37)=0),"",Y37+N37/O37) -> 0.0009310987 | AA37: =IF(OR(Z37="",N(U37)=0),"",Z37-U37) -> 0 | AB37: =IF(N(Q37)=0,"",Q37+IF(I37="yes",Q37*Inputs!$B$10*Inputs!$B$9,0)+IFERROR(INDEX(Inputs!$B$13:$B$15,MATCH(G37,Inputs!$A$13:$A$15,0)),0)+IFERROR(INDEX(Inputs!$B$18:$B$24,MATCH(H37,Inputs!$A$18:$A$24,0)),0)) -> 0.075 | AC37: =IF(OR(N(AB37)<=0,N(N37)=0,N(L37)=0),"",MIN(L37,N37/AB37)) -> 15 | AD37: =IF(OR(AC37="",N(O37)=0),"",AC37/O37-1) -> -0.068901304 | AE37: =IF(OR(AD37="",N(O37)=0),"",AD37+N37/O37) -> 0.0009310987 | AF37: =IF(OR(AE37="",N(Z37)=0),"",AE37-Z37) -> 0 | AG37: =IF(AND(N(M37)>0,N(L37)>0),M37*L37,N37) -> 1.125 | AH37: =IF(OR(N(AB37)<=0,N(AG37)=0,N(L37)=0),"",MIN(L37,AG37/AB37)) -> 15 | AI37: =IF(OR(AH37="",N(O37)=0),"",AH37/O37-1) -> -0.068901304 | AJ37: =IF(OR(AI37="",N(O37)=0),"",AI37+AG37/O37) -> 0.0009310987 | AK37: =IF(OR(AJ37="",N(AE37)=0),"",AJ37-AE37) -> 0 | AL37: =IF(N(F37)=0,"",INDEX(Inputs!$B$28:$B$32,IFERROR(MATCH(F37,Inputs!$A$28:$A$32,1),0)+1)) -> 0.08 | AN37: =IF(N(AM37)>0,AM37,AL37) -> 0.08 | AO37: =IF(N(AN37)=0,"",AN37+IF(I37="yes",AN37*Inputs!$B$10*Inputs!$B$9,0)+IFERROR(INDEX(Inputs!$B$13:$B$15,MATCH(G37,Inputs!$A$13:$A$15,0)),0)+IFERROR(INDEX(Inputs!$B$18:$B$24,MATCH(H37,Inputs!$A$18:$A$24,0)),0)) -> 0.075 | AP37: =IF(OR(N(AO37)<=0,N(AG37)=0,N(L37)=0),"",MIN(L37,AG37/AO37)) -> 15 | AQ37: =IF(OR(AP37="",N(O37)=0),"",AP37/O37-1) -> -0.068901304 | AR37: =IF(OR(AQ37="",N(O37)=0),"",AQ37+AG37/O37) -> 0.0009310987 | AS37: =IF(OR(AR37="",N(AJ37)=0),"",AR37-AJ37) -> 0 | AT37: 25 | AU37: 1.125 | AV37: =IF(N(AT37)>0,AT37,L37) -> 25 | AW37: =IF(AND(N(M37)>0,N(AV37)>0),M37*AV37,IF(N(AU37)>0,AU37,N37)) -> 1.125 | AX37: =IF(N(AN37)=0,"",AN37+IF(I37="yes",AN37*Inputs!$B$10*Inputs!$B$9,0)+IFERROR(INDEX(Inputs!$B$13:$B$15,MATCH(G37,Inputs!$A$13:$A$15,0)),0)+IFERROR(INDEX(Inputs!$B$18:$B$24,MATCH(H37,Inputs!$A$18:$A$24,0)),0)) -> 0.075 | AY37: =IF(OR(N(AX37)<=0,N(AW37)=0,N(AV37)=0),"",MIN(AV37,AW37/AX37)) -> 15 | AZ37: =IF(OR(AY37="",N(O37)=0),"",AY37/O37-1) -> -0.068901304 | BA37: =IF(OR(AZ37="",N(O37)=0),"",AZ37+AW37/O37) -> 0.0009310987 | BB37: =IF(OR(BA37="",N(AR37)=0),"",BA37-AR37) -> 0 | BC37: =IF(OR(BA37="",N(U37)=0),"",BA37-U37) -> 0
A38: A-C | B38: 70 | C38: AFSIA | D38: AFG | E38: AMERICAN FINANCIAL GROUP INC | F38: 11900 | G38: PREFERRED | H38: FIXED | I38: yes | J38: Q | K38: 4 | L38: 25 | M38: 0.0675 | N38: 1.6875 | O38: 13.25 | P38: OK | Q38: 0.09 | R38: 0.0855 | S38: 19.736842 | T38: 0.48957299 | U38: 0.61693148 | V38: 0 | W38: =IF(N(Q38)=0,"",Q38+IF(I38="yes",Q38*Inputs!$B$10*Inputs!$B$9,0)+V38) -> 0.0855 | X38: =IF(OR(N(W38)<=0,N(N38)=0,N(L38)=0),"",MIN(L38,N38/W38)) -> 19.736842 | Y38: =IF(OR(X38="",N(O38)=0),"",X38/O38-1) -> 0.48957299 | Z38: =IF(OR(Y38="",N(O38)=0),"",Y38+N38/O38) -> 0.61693148 | AA38: =IF(OR(Z38="",N(U38)=0),"",Z38-U38) -> 0 | AB38: =IF(N(Q38)=0,"",Q38+IF(I38="yes",Q38*Inputs!$B$10*Inputs!$B$9,0)+IFERROR(INDEX(Inputs!$B$13:$B$15,MATCH(G38,Inputs!$A$13:$A$15,0)),0)+IFERROR(INDEX(Inputs!$B$18:$B$24,MATCH(H38,Inputs!$A$18:$A$24,0)),0)) -> 0.0855 | AC38: =IF(OR(N(AB38)<=0,N(N38)=0,N(L38)=0),"",MIN(L38,N38/AB38)) -> 19.736842 | AD38: =IF(OR(AC38="",N(O38)=0),"",AC38/O38-1) -> 0.48957299 | AE38: =IF(OR(AD38="",N(O38)=0),"",AD38+N38/O38) -> 0.61693148 | AF38: =IF(OR(AE38="",N(Z38)=0),"",AE38-Z38) -> 0 | AG38: =IF(AND(N(M38)>0,N(L38)>0),M38*L38,N38) -> 1.6875 | AH38: =IF(OR(N(AB38)<=0,N(AG38)=0,N(L38)=0),"",MIN(L38,AG38/AB38)) -> 19.736842 | AI38: =IF(OR(AH38="",N(O38)=0),"",AH38/O38-1) -> 0.48957299 | AJ38: =IF(OR(AI38="",N(O38)=0),"",AI38+AG38/O38) -> 0.61693148 | AK38: =IF(OR(AJ38="",N(AE38)=0),"",AJ38-AE38) -> 0 | AL38: =IF(N(F38)=0,"",INDEX(Inputs!$B$28:$B$32,IFERROR(MATCH(F38,Inputs!$A$28:$A$32,1),0)+1)) -> 0.08 | AN38: =IF(N(AM38)>0,AM38,AL38) -> 0.08 | AO38: =IF(N(AN38)=0,"",AN38+IF(I38="yes",AN38*Inputs!$B$10*Inputs!$B$9,0)+IFERROR(INDEX(Inputs!$B$13:$B$15,MATCH(G38,Inputs!$A$13:$A$15,0)),0)+IFERROR(INDEX(Inputs!$B$18:$B$24,MATCH(H38,Inputs!$A$18:$A$24,0)),0)) -> 0.076 | AP38: =IF(OR(N(AO38)<=0,N(AG38)=0,N(L38)=0),"",MIN(L38,AG38/AO38)) -> 22.203947 | AQ38: =IF(OR(AP38="",N(O38)=0),"",AP38/O38-1) -> 0.67576961 | AR38: =IF(OR(AQ38="",N(O38)=0),"",AQ38+AG38/O38) -> 0.8031281 | AS38: =IF(OR(AR38="",N(AJ38)=0),"",AR38-AJ38) -> 0.18619662 | AT38: 25 | AU38: 1.69 | AV38: =IF(N(AT38)>0,AT38,L38) -> 25 | AW38: =IF(AND(N(M38)>0,N(AV38)>0),M38*AV38,IF(N(AU38)>0,AU38,N38)) -> 1.6875 | AX38: =IF(N(AN38)=0,"",AN38+IF(I38="yes",AN38*Inputs!$B$10*Inputs!$B$9,0)+IFERROR(INDEX(Inputs!$B$13:$B$15,MATCH(G38,Inputs!$A$13:$A$15,0)),0)+IFERROR(INDEX(Inputs!$B$18:$B$24,MATCH(H38,Inputs!$A$18:$A$24,0)),0)) -> 0.076 | AY38: =IF(OR(N(AX38)<=0,N(AW38)=0,N(AV38)=0),"",MIN(AV38,AW38/AX38)) -> 22.203947 | AZ38: =IF(OR(AY38="",N(O38)=0),"",AY38/O38-1) -> 0.67576961 | BA38: =IF(OR(AZ38="",N(O38)=0),"",AZ38+AW38/O38) -> 0.8031281 | BB38: =IF(OR(BA38="",N(AR38)=0),"",BA38-AR38) -> 0 | BC38: =IF(OR(BA38="",N(U38)=0),"",BA38-U38) -> 0.18619662
A39: A-C | B39: 71 | C39: AFSIB | D39: AFG | E39: AMERICAN FINANCIAL GROUP INC | F39: 11900 | G39: PREFERRED | H39: FIXED | I39: yes | J39: Q | K39: 4 | L39: 25 | M39: 0.0725 | N39: 1.8125 | O39: 14.6 | P39: OK | Q39: 0.09 | R39: 0.0855 | S39: 21.19883 | T39: 0.45197469 | U39: 0.57611852 | V39: 0 | W39: =IF(N(Q39)=0,"",Q39+IF(I39="yes",Q39*Inputs!$B$10*Inputs!$B$9,0)+V39) -> 0.0855 | X39: =IF(OR(N(W39)<=0,N(N39)=0,N(L39)=0),"",MIN(L39,N39/W39)) -> 21.19883 | Y39: =IF(OR(X39="",N(O39)=0),"",X39/O39-1) -> 0.45197469 | Z39: =IF(OR(Y39="",N(O39)=0),"",Y39+N39/O39) -> 0.57611852 | AA39: =IF(OR(Z39="",N(U39)=0),"",Z39-U39) -> 0 | AB39: =IF(N(Q39)=0,"",Q39+IF(I39="yes",Q39*Inputs!$B$10*Inputs!$B$9,0)+IFERROR(INDEX(Inputs!$B$13:$B$15,MATCH(G39,Inputs!$A$13:$A$15,0)),0)+IFERROR(INDEX(Inputs!$B$18:$B$24,MATCH(H39,Inputs!$A$18:$A$24,0)),0)) -> 0.0855 | AC39: =IF(OR(N(AB39)<=0,N(N39)=0,N(L39)=0),"",MIN(L39,N39/AB39)) -> 21.19883 | AD39: =IF(OR(AC39="",N(O39)=0),"",AC39/O39-1) -> 0.45197469 | AE39: =IF(OR(AD39="",N(O39)=0),"",AD39+N39/O39) -> 0.57611852 | AF39: =IF(OR(AE39="",N(Z39)=0),"",AE39-Z39) -> 0 | AG39: =IF(AND(N(M39)>0,N(L39)>0),M39*L39,N39) -> 1.8125 | AH39: =IF(OR(N(AB39)<=0,N(AG39)=0,N(L39)=0),"",MIN(L39,AG39/AB39)) -> 21.19883 | AI39: =IF(OR(AH39="",N(O39)=0),"",AH39/O39-1) -> 0.45197469 | AJ39: =IF(OR(AI39="",N(O39)=0),"",AI39+AG39/O39) -> 0.57611852 | AK39: =IF(OR(AJ39="",N(AE39)=0),"",AJ39-AE39) -> 0 | AL39: =IF(N(F39)=0,"",INDEX(Inputs!$B$28:$B$32,IFERROR(MATCH(F39,Inputs!$A$28:$A$32,1),0)+1)) -> 0.08 | AN39: =IF(N(AM39)>0,AM39,AL39) -> 0.08 | AO39: =IF(N(AN39)=0,"",AN39+IF(I39="yes",AN39*Inputs!$B$10*Inputs!$B$9,0)+IFERROR(INDEX(Inputs!$B$13:$B$15,MATCH(G39,Inputs!$A$13:$A$15,0)),0)+IFERROR(INDEX(Inputs!$B$18:$B$24,MATCH(H39,Inputs!$A$18:$A$24,0)),0)) -> 0.076 | AP39: =IF(OR(N(AO39)<=0,N(AG39)=0,N(L39)=0),"",MIN(L39,AG39/AO39)) -> 23.848684 | AQ39: =IF(OR(AP39="",N(O39)=0),"",AP39/O39-1) -> 0.63347152 | AR39: =IF(OR(AQ39="",N(O39)=0),"",AQ39+AG39/O39) -> 0.75761536 | AS39: =IF(OR(AR39="",N(AJ39)=0),"",AR39-AJ39) -> 0.18149684 | AT39: 25 | AU39: 1.81 | AV39: =IF(N(AT39)>0,AT39,L39) -> 25 | AW39: =IF(AND(N(M39)>0,N(AV39)>0),M39*AV39,IF(N(AU39)>0,AU39,N39)) -> 1.8125 | AX39: =IF(N(AN39)=0,"",AN39+IF(I39="yes",AN39*Inputs!$B$10*Inputs!$B$9,0)+IFERROR(INDEX(Inputs!$B$13:$B$15,MATCH(G39,Inputs!$A$13:$A$15,0)),0)+IFERROR(INDEX(Inputs!$B$18:$B$24,MATCH(H39,Inputs!$A$18:$A$24,0)),0)) -> 0.076 | AY39: =IF(OR(N(AX39)<=0,N(AW39)=0,N(AV39)=0),"",MIN(AV39,AW39/AX39)) -> 23.848684 | AZ39: =IF(OR(AY39="",N(O39)=0),"",AY39/O39-1) -> 0.63347152 | BA39: =IF(OR(AZ39="",N(O39)=0),"",AZ39+AW39/O39) -> 0.75761536 | BB39: =IF(OR(BA39="",N(AR39)=0),"",BA39-AR39) -> 0 | BC39: =IF(OR(BA39="",N(U39)=0),"",BA39-U39) -> 0.18149684
A40: A-C | B40: 72 | C40: AFSIC | D40: AFG | E40: AMERICAN FINANCIAL GROUP INC | F40: 11900 | G40: PREFERRED | H40: FIXED | I40: yes | J40: Q | K40: 4 | L40: 25 | M40: 0.07625 | N40: 1.90625 | O40: 14.9 | P40: OK | Q40: 0.09 | R40: 0.0855 | S40: 22.295322 | T40: 0.49633031 | U40: 0.62426655 | V40: 0 | W40: =IF(N(Q40)=0,"",Q40+IF(I40="yes",Q40*Inputs!$B$10*Inputs!$B$9,0)+V40) -> 0.0855 | X40: =IF(OR(N(W40)<=0,N(N40)=0,N(L40)=0),"",MIN(L40,N40/W40)) -> 22.295322 | Y40: =IF(OR(X40="",N(O40)=0),"",X40/O40-1) -> 0.49633031 | Z40: =IF(OR(Y40="",N(O40)=0),"",Y40+N40/O40) -> 0.62426655 | AA40: =IF(OR(Z40="",N(U40)=0),"",Z40-U40) -> 0 | AB40: =IF(N(Q40)=0,"",Q40+IF(I40="yes",Q40*Inputs!$B$10*Inputs!$B$9,0)+IFERROR(INDEX(Inputs!$B$13:$B$15,MATCH(G40,Inputs!$A$13:$A$15,0)),0)+IFERROR(INDEX(Inputs!$B$18:$B$24,MATCH(H40,Inputs!$A$18:$A$24,0)),0)) -> 0.0855 | AC40: =IF(OR(N(AB40)<=0,N(N40)=0,N(L40)=0),"",MIN(L40,N40/AB40)) -> 22.295322 | AD40: =IF(OR(AC40="",N(O40)=0),"",AC40/O40-1) -> 0.49633031 | AE40: =IF(OR(AD40="",N(O40)=0),"",AD40+N40/O40) -> 0.62426655 | AF40: =IF(OR(AE40="",N(Z40)=0),"",AE40-Z40) -> 0 | AG40: =IF(AND(N(M40)>0,N(L40)>0),M40*L40,N40) -> 1.90625 | AH40: =IF(OR(N(AB40)<=0,N(AG40)=0,N(L40)=0),"",MIN(L40,AG40/AB40)) -> 22.295322 | AI40: =IF(OR(AH40="",N(O40)=0),"",AH40/O40-1) -> 0.49633031 | AJ40: =IF(OR(AI40="",N(O40)=0),"",AI40+AG40/O40) -> 0.62426655 | AK40: =IF(OR(AJ40="",N(AE40)=0),"",AJ40-AE40) -> 0 | AL40: =IF(N(F40)=0,"",INDEX(Inputs!$B$28:$B$32,IFERROR(MATCH(F40,Inputs!$A$28:$A$32,1),0)+1)) -> 0.08 | AN40: =IF(N(AM40)>0,AM40,AL40) -> 0.08 | AO40: =IF(N(AN40)=0,"",AN40+IF(I40="yes",AN40*Inputs!$B$10*Inputs!$B$9,0)+IFERROR(INDEX(Inputs!$B$13:$B$15,MATCH(G40,Inputs!$A$13:$A$15,0)),0)+IFERROR(INDEX(Inputs!$B$18:$B$24,MATCH(H40,Inputs!$A$18:$A$24,0)),0)) -> 0.076 | AP40: =IF(OR(N(AO40)<=0,N(AG40)=0,N(L40)=0),"",MIN(L40,AG40/AO40)) -> 25 | AQ40: =IF(OR(AP40="",N(O40)=0),"",AP40/O40-1) -> 0.67785235 | AR40: =IF(OR(AQ40="",N(O40)=0),"",AQ40+AG40/O40) -> 0.80578859 | AS40: =IF(OR(AR40="",N(AJ40)=0),"",AR40-AJ40) -> 0.18152204 | AT40: 25 | AU40: 1.91 | AV40: =IF(N(AT40)>0,AT40,L40) -> 25 | AW40: =IF(AND(N(M40)>0,N(AV40)>0),M40*AV40,IF(N(AU40)>0,AU40,N40)) -> 1.90625 | AX40: =IF(N(AN40)=0,"",AN40+IF(I40="yes",AN40*Inputs!$B$10*Inputs!$B$9,0)+IFERROR(INDEX(Inputs!$B$13:$B$15,MATCH(G40,Inputs!$A$13:$A$15,0)),0)+IFERROR(INDEX(Inputs!$B$18:$B$24,MATCH(H40,Inputs!$A$18:$A$24,0)),0)) -> 0.076 | AY40: =IF(OR(N(AX40)<=0,N(AW40)=0,N(AV40)=0),"",MIN(AV40,AW40/AX40)) -> 25 | AZ40: =IF(OR(AY40="",N(O40)=0),"",AY40/O40-1) -> 0.67785235 | BA40: =IF(OR(AZ40="",N(O40)=0),"",AZ40+AW40/O40) -> 0.80578859 | BB40: =IF(OR(BA40="",N(AR40)=0),"",BA40-AR40) -> 0 | BC40: =IF(OR(BA40="",N(U40)=0),"",BA40-U40) -> 0.18152204
A41: A-C | B41: 73 | C41: AFSIP | D41: AFG | E41: AMERICAN FINANCIAL GROUP INC | F41: 11900 | G41: PREFERRED | H41: FIXED | I41: yes | J41: Q | K41: 4 | L41: 25 | M41: 0.075 | N41: 1.875 | O41: 14.78 | P41: OK | Q41: 0.09 | R41: 0.0855 | S41: 21.929825 | T41: 0.48374997 | U41: 0.61061059 | V41: 0 | W41: =IF(N(Q41)=0,"",Q41+IF(I41="yes",Q41*Inputs!$B$10*Inputs!$B$9,0)+V41) -> 0.0855 | X41: =IF(OR(N(W41)<=0,N(N41)=0,N(L41)=0),"",MIN(L41,N41/W41)) -> 21.929825 | Y41: =IF(OR(X41="",N(O41)=0),"",X41/O41-1) -> 0.48374997 | Z41: =IF(OR(Y41="",N(O41)=0),"",Y41+N41/O41) -> 0.61061059 | AA41: =IF(OR(Z41="",N(U41)=0),"",Z41-U41) -> 0 | AB41: =IF(N(Q41)=0,"",Q41+IF(I41="yes",Q41*Inputs!$B$10*Inputs!$B$9,0)+IFERROR(INDEX(Inputs!$B$13:$B$15,MATCH(G41,Inputs!$A$13:$A$15,0)),0)+IFERROR(INDEX(Inputs!$B$18:$B$24,MATCH(H41,Inputs!$A$18:$A$24,0)),0)) -> 0.0855 | AC41: =IF(OR(N(AB41)<=0,N(N41)=0,N(L41)=0),"",MIN(L41,N41/AB41)) -> 21.929825 | AD41: =IF(OR(AC41="",N(O41)=0),"",AC41/O41-1) -> 0.48374997 | AE41: =IF(OR(AD41="",N(O41)=0),"",AD41+N41/O41) -> 0.61061059 | AF41: =IF(OR(AE41="",N(Z41)=0),"",AE41-Z41) -> 0 | AG41: =IF(AND(N(M41)>0,N(L41)>0),M41*L41,N41) -> 1.875 | AH41: =IF(OR(N(AB41)<=0,N(AG41)=0,N(L41)=0),"",MIN(L41,AG41/AB41)) -> 21.929825 | AI41: =IF(OR(AH41="",N(O41)=0),"",AH41/O41-1) -> 0.48374997 | AJ41: =IF(OR(AI41="",N(O41)=0),"",AI41+AG41/O41) -> 0.61061059 | AK41: =IF(OR(AJ41="",N(AE41)=0),"",AJ41-AE41) -> 0 | AL41: =IF(N(F41)=0,"",INDEX(Inputs!$B$28:$B$32,IFERROR(MATCH(F41,Inputs!$A$28:$A$32,1),0)+1)) -> 0.08 | AN41: =IF(N(AM41)>0,AM41,AL41) -> 0.08 | AO41: =IF(N(AN41)=0,"",AN41+IF(I41="yes",AN41*Inputs!$B$10*Inputs!$B$9,0)+IFERROR(INDEX(Inputs!$B$13:$B$15,MATCH(G41,Inputs!$A$13:$A$15,0)),0)+IFERROR(INDEX(Inputs!$B$18:$B$24,MATCH(H41,Inputs!$A$18:$A$24,0)),0)) -> 0.076 | AP41: =IF(OR(N(AO41)<=0,N(AG41)=0,N(L41)=0),"",MIN(L41,AG41/AO41)) -> 24.671053 | AQ41: =IF(OR(AP41="",N(O41)=0),"",AP41/O41-1) -> 0.66921872 | AR41: =IF(OR(AQ41="",N(O41)=0),"",AQ41+AG41/O41) -> 0.79607934 | AS41: =IF(OR(AR41="",N(AJ41)=0),"",AR41-AJ41) -> 0.18546875 | AT41: 25 | AU41: 1.88 | AV41: =IF(N(AT41)>0,AT41,L41) -> 25 | AW41: =IF(AND(N(M41)>0,N(AV41)>0),M41*AV41,IF(N(AU41)>0,AU41,N41)) -> 1.875 | AX41: =IF(N(AN41)=0,"",AN41+IF(I41="yes",AN41*Inputs!$B$10*Inputs!$B$9,0)+IFERROR(INDEX(Inputs!$B$13:$B$15,MATCH(G41,Inputs!$A$13:$A$15,0)),0)+IFERROR(INDEX(Inputs!$B$18:$B$24,MATCH(H41,Inputs!$A$18:$A$24,0)),0)) -> 0.076 | AY41: =IF(OR(N(AX41)<=0,N(AW41)=0,N(AV41)=0),"",MIN(AV41,AW41/AX41)) -> 24.671053 | AZ41: =IF(OR(AY41="",N(O41)=0),"",AY41/O41-1) -> 0.66921872 | BA41: =IF(OR(AZ41="",N(O41)=0),"",AZ41+AW41/O41) -> 0.79607934 | BB41: =IF(OR(BA41="",N(AR41)=0),"",BA41-AR41) -> 0 | BC41: =IF(OR(BA41="",N(U41)=0),"",BA41-U41) -> 0.18546875
A42: A-C | B42: 74 | C42: AFSIM | D42: AFG | E42: AMERICAN FINANCIAL GROUP INC | F42: 11900 | G42: PREFERRED | H42: FIXED | I42: yes | J42: Q | K42: 4 | L42: 25 | M42: 0.0775 | N42: 1.9375 | O42: 15.01 | P42: OK | Q42: 0.09 | R42: 0.0855 | S42: 22.660819 | T42: 0.50971477 | U42: 0.63879538 | V42: 0 | W42: =IF(N(Q42)=0,"",Q42+IF(I42="yes",Q42*Inputs!$B$10*Inputs!$B$9,0)+V42) -> 0.0855 | X42: =IF(OR(N(W42)<=0,N(N42)=0,N(L42)=0),"",MIN(L42,N42/W42)) -> 22.660819 | Y42: =IF(OR(X42="",N(O42)=0),"",X42/O42-1) -> 0.50971477 | Z42: =IF(OR(Y42="",N(O42)=0),"",Y42+N42/O42) -> 0.63879538 | AA42: =IF(OR(Z42="",N(U42)=0),"",Z42-U42) -> 0 | AB42: =IF(N(Q42)=0,"",Q42+IF(I42="yes",Q42*Inputs!$B$10*Inputs!$B$9,0)+IFERROR(INDEX(Inputs!$B$13:$B$15,MATCH(G42,Inputs!$A$13:$A$15,0)),0)+IFERROR(INDEX(Inputs!$B$18:$B$24,MATCH(H42,Inputs!$A$18:$A$24,0)),0)) -> 0.0855 | AC42: =IF(OR(N(AB42)<=0,N(N42)=0,N(L42)=0),"",MIN(L42,N42/AB42)) -> 22.660819 | AD42: =IF(OR(AC42="",N(O42)=0),"",AC42/O42-1) -> 0.50971477 | AE42: =IF(OR(AD42="",N(O42)=0),"",AD42+N42/O42) -> 0.63879538 | AF42: =IF(OR(AE42="",N(Z42)=0),"",AE42-Z42) -> 0 | AG42: =IF(AND(N(M42)>0,N(L42)>0),M42*L42,N42) -> 1.9375 | AH42: =IF(OR(N(AB42)<=0,N(AG42)=0,N(L42)=0),"",MIN(L42,AG42/AB42)) -> 22.660819 | AI42: =IF(OR(AH42="",N(O42)=0),"",AH42/O42-1) -> 0.50971477 | AJ42: =IF(OR(AI42="",N(O42)=0),"",AI42+AG42/O42) -> 0.63879538 | AK42: =IF(OR(AJ42="",N(AE42)=0),"",AJ42-AE42) -> 0 | AL42: =IF(N(F42)=0,"",INDEX(Inputs!$B$28:$B$32,IFERROR(MATCH(F42,Inputs!$A$28:$A$32,1),0)+1)) -> 0.08 | AN42: =IF(N(AM42)>0,AM42,AL42) -> 0.08 | AO42: =IF(N(AN42)=0,"",AN42+IF(I42="yes",AN42*Inputs!$B$10*Inputs!$B$9,0)+IFERROR(INDEX(Inputs!$B$13:$B$15,MATCH(G42,Inputs!$A$13:$A$15,0)),0)+IFERROR(INDEX(Inputs!$B$18:$B$24,MATCH(H42,Inputs!$A$18:$A$24,0)),0)) -> 0.076 | AP42: =IF(OR(N(AO42)<=0,N(AG42)=0,N(L42)=0),"",MIN(L42,AG42/AO42)) -> 25 | AQ42: =IF(OR(AP42="",N(O42)=0),"",AP42/O42-1) -> 0.6655563 | AR42: =IF(OR(AQ42="",N(O42)=0),"",AQ42+AG42/O42) -> 0.79463691 | AS42: =IF(OR(AR42="",N(AJ42)=0),"",AR42-AJ42) -> 0.15584152 | AT42: 25 | AU42: 1.94 | AV42: =IF(N(AT42)>0,AT42,L42) -> 25 | AW42: =IF(AND(N(M42)>0,N(AV42)>0),M42*AV42,IF(N(AU42)>0,AU42,N42)) -> 1.9375 | AX42: =IF(N(AN42)=0,"",AN42+IF(I42="yes",AN42*Inputs!$B$10*Inputs!$B$9,0)+IFERROR(INDEX(Inputs!$B$13:$B$15,MATCH(G42,Inputs!$A$13:$A$15,0)),0)+IFERROR(INDEX(Inputs!$B$18:$B$24,MATCH(H42,Inputs!$A$18:$A$24,0)),0)) -> 0.076 | AY42: =IF(OR(N(AX42)<=0,N(AW42)=0,N(AV42)=0),"",MIN(AV42,AW42/AX42)) -> 25 | AZ42: =IF(OR(AY42="",N(O42)=0),"",AY42/O42-1) -> 0.6655563 | BA42: =IF(OR(AZ42="",N(O42)=0),"",AZ42+AW42/O42) -> 0.79463691 | BB42: =IF(OR(BA42="",N(AR42)=0),"",BA42-AR42) -> 0 | BC42: =IF(OR(BA42="",N(U42)=0),"",BA42-U42) -> 0.15584152
A43: A-C | B43: 75 | C43: AFSIN | D43: AFG | E43: AMERICAN FINANCIAL GROUP INC | F43: 11900 | G43: PREFERRED | H43: FIXED | I43: yes | J43: Q | K43: 4 | L43: 25 | M43: 0.0695 | N43: 1.7375 | O43: 13.57 | P43: OK | Q43: 0.09 | R43: 0.0855 | S43: 20.321637 | T43: 0.49754145 | U43: 0.62558124 | V43: 0 | W43: =IF(N(Q43)=0,"",Q43+IF(I43="yes",Q43*Inputs!$B$10*Inputs!$B$9,0)+V43) -> 0.0855 | X43: =IF(OR(N(W43)<=0,N(N43)=0,N(L43)=0),"",MIN(L43,N43/W43)) -> 20.321637 | Y43: =IF(OR(X43="",N(O43)=0),"",X43/O43-1) -> 0.49754145 | Z43: =IF(OR(Y43="",N(O43)=0),"",Y43+N43/O43) -> 0.62558124 | AA43: =IF(OR(Z43="",N(U43)=0),"",Z43-U43) -> 0 | AB43: =IF(N(Q43)=0,"",Q43+IF(I43="yes",Q43*Inputs!$B$10*Inputs!$B$9,0)+IFERROR(INDEX(Inputs!$B$13:$B$15,MATCH(G43,Inputs!$A$13:$A$15,0)),0)+IFERROR(INDEX(Inputs!$B$18:$B$24,MATCH(H43,Inputs!$A$18:$A$24,0)),0)) -> 0.0855 | AC43: =IF(OR(N(AB43)<=0,N(N43)=0,N(L43)=0),"",MIN(L43,N43/AB43)) -> 20.321637 | AD43: =IF(OR(AC43="",N(O43)=0),"",AC43/O43-1) -> 0.49754145 | AE43: =IF(OR(AD43="",N(O43)=0),"",AD43+N43/O43) -> 0.62558124 | AF43: =IF(OR(AE43="",N(Z43)=0),"",AE43-Z43) -> 0 | AG43: =IF(AND(N(M43)>0,N(L43)>0),M43*L43,N43) -> 1.7375 | AH43: =IF(OR(N(AB43)<=0,N(AG43)=0,N(L43)=0),"",MIN(L43,AG43/AB43)) -> 20.321637 | AI43: =IF(OR(AH43="",N(O43)=0),"",AH43/O43-1) -> 0.49754145 | AJ43: =IF(OR(AI43="",N(O43)=0),"",AI43+AG43/O43) -> 0.62558124 | AK43: =IF(OR(AJ43="",N(AE43)=0),"",AJ43-AE43) -> 0 | AL43: =IF(N(F43)=0,"",INDEX(Inputs!$B$28:$B$32,IFERROR(MATCH(F43,Inputs!$A$28:$A$32,1),0)+1)) -> 0.08 | AN43: =IF(N(AM43)>0,AM43,AL43) -> 0.08 | AO43: =IF(N(AN43)=0,"",AN43+IF(I43="yes",AN43*Inputs!$B$10*Inputs!$B$9,0)+IFERROR(INDEX(Inputs!$B$13:$B$15,MATCH(G43,Inputs!$A$13:$A$15,0)),0)+IFERROR(INDEX(Inputs!$B$18:$B$24,MATCH(H43,Inputs!$A$18:$A$24,0)),0)) -> 0.076 | AP43: =IF(OR(N(AO43)<=0,N(AG43)=0,N(L43)=0),"",MIN(L43,AG43/AO43)) -> 22.861842 | AQ43: =IF(OR(AP43="",N(O43)=0),"",AP43/O43-1) -> 0.68473413 | AR43: =IF(OR(AQ43="",N(O43)=0),"",AQ43+AG43/O43) -> 0.81277392 | AS43: =IF(OR(AR43="",N(AJ43)=0),"",AR43-AJ43) -> 0.18719268 | AT43: 25 | AU43: 1.74 | AV43: =IF(N(AT43)>0,AT43,L43) -> 25 | AW43: =IF(AND(N(M43)>0,N(AV43)>0),M43*AV43,IF(N(AU43)>0,AU43,N43)) -> 1.7375 | AX43: =IF(N(AN43)=0,"",AN43+IF(I43="yes",AN43*Inputs!$B$10*Inputs!$B$9,0)+IFERROR(INDEX(Inputs!$B$13:$B$15,MATCH(G43,Inputs!$A$13:$A$15,0)),0)+IFERROR(INDEX(Inputs!$B$18:$B$24,MATCH(H43,Inputs!$A$18:$A$24,0)),0)) -> 0.076 | AY43: =IF(OR(N(AX43)<=0,N(AW43)=0,N(AV43)=0),"",MIN(AV43,AW43/AX43)) -> 22.861842 | AZ43: =IF(OR(AY43="",N(O43)=0),"",AY43/O43-1) -> 0.68473413 | BA43: =IF(OR(AZ43="",N(O43)=0),"",AZ43+AW43/O43) -> 0.81277392 | BB43: =IF(OR(BA43="",N(AR43)=0),"",BA43-AR43) -> 0 | BC43: =IF(OR(BA43="",N(U43)=0),"",BA43-U43) -> 0.18719268
A44: A-C | B44: 76 | C44: AFFS | D44: AFG | E44: AMERICAN FINANCIAL GROUP INC | F44: 11900 | G44: BABY_BOND | H44: FIXED | I44: no | J44: Q | K44: 4 | L44: 25 | M44: 0.0725 | N44: 1.8125 | O44: 15.3 | P44: OK | Q44: 0.09 | R44: 0.0825 | S44: 21.969697 | T44: 0.43592791 | U44: 0.55439196 | V44: -0.0075 | W44: =IF(N(Q44)=0,"",Q44+IF(I44="yes",Q44*Inputs!$B$10*Inputs!$B$9,0)+V44) -> 0.0825 | X44: =IF(OR(N(W44)<=0,N(N44)=0,N(L44)=0),"",MIN(L44,N44/W44)) -> 21.969697 | Y44: =IF(OR(X44="",N(O44)=0),"",X44/O44-1) -> 0.43592791 | Z44: =IF(OR(Y44="",N(O44)=0),"",Y44+N44/O44) -> 0.55439196 | AA44: =IF(OR(Z44="",N(U44)=0),"",Z44-U44) -> 0 | AB44: =IF(N(Q44)=0,"",Q44+IF(I44="yes",Q44*Inputs!$B$10*Inputs!$B$9,0)+IFERROR(INDEX(Inputs!$B$13:$B$15,MATCH(G44,Inputs!$A$13:$A$15,0)),0)+IFERROR(INDEX(Inputs!$B$18:$B$24,MATCH(H44,Inputs!$A$18:$A$24,0)),0)) -> 0.085 | AC44: =IF(OR(N(AB44)<=0,N(N44)=0,N(L44)=0),"",MIN(L44,N44/AB44)) -> 21.323529 | AD44: =IF(OR(AC44="",N(O44)=0),"",AC44/O44-1) -> 0.39369473 | AE44: =IF(OR(AD44="",N(O44)=0),"",AD44+N44/O44) -> 0.51215879 | AF44: =IF(OR(AE44="",N(Z44)=0),"",AE44-Z44) -> -0.042233174 | AG44: =IF(AND(N(M44)>0,N(L44)>0),M44*L44,N44) -> 1.8125 | AH44: =IF(OR(N(AB44)<=0,N(AG44)=0,N(L44)=0),"",MIN(L44,AG44/AB44)) -> 21.323529 | AI44: =IF(OR(AH44="",N(O44)=0),"",AH44/O44-1) -> 0.39369473 | AJ44: =IF(OR(AI44="",N(O44)=0),"",AI44+AG44/O44) -> 0.51215879 | AK44: =IF(OR(AJ44="",N(AE44)=0),"",AJ44-AE44) -> 0 | AL44: =IF(N(F44)=0,"",INDEX(Inputs!$B$28:$B$32,IFERROR(MATCH(F44,Inputs!$A$28:$A$32,1),0)+1)) -> 0.08 | AN44: =IF(N(AM44)>0,AM44,AL44) -> 0.08 | AO44: =IF(N(AN44)=0,"",AN44+IF(I44="yes",AN44*Inputs!$B$10*Inputs!$B$9,0)+IFERROR(INDEX(Inputs!$B$13:$B$15,MATCH(G44,Inputs!$A$13:$A$15,0)),0)+IFERROR(INDEX(Inputs!$B$18:$B$24,MATCH(H44,Inputs!$A$18:$A$24,0)),0)) -> 0.075 | AP44: =IF(OR(N(AO44)<=0,N(AG44)=0,N(L44)=0),"",MIN(L44,AG44/AO44)) -> 24.166667 | AQ44: =IF(OR(AP44="",N(O44)=0),"",AP44/O44-1) -> 0.5795207 | AR44: =IF(OR(AQ44="",N(O44)=0),"",AQ44+AG44/O44) -> 0.69798475 | AS44: =IF(OR(AR44="",N(AJ44)=0),"",AR44-AJ44) -> 0.18582596 | AT44: 25 | AU44: 1.81 | AV44: =IF(N(AT44)>0,AT44,L44) -> 25 | AW44: =IF(AND(N(M44)>0,N(AV44)>0),M44*AV44,IF(N(AU44)>0,AU44,N44)) -> 1.8125 | AX44: =IF(N(AN44)=0,"",AN44+IF(I44="yes",AN44*Inputs!$B$10*Inputs!$B$9,0)+IFERROR(INDEX(Inputs!$B$13:$B$15,MATCH(G44,Inputs!$A$13:$A$15,0)),0)+IFERROR(INDEX(Inputs!$B$18:$B$24,MATCH(H44,Inputs!$A$18:$A$24,0)),0)) -> 0.075 | AY44: =IF(OR(N(AX44)<=0,N(AW44)=0,N(AV44)=0),"",MIN(AV44,AW44/AX44)) -> 24.166667 | AZ44: =IF(OR(AY44="",N(O44)=0),"",AY44/O44-1) -> 0.5795207 | BA44: =IF(OR(AZ44="",N(O44)=0),"",AZ44+AW44/O44) -> 0.69798475 | BB44: =IF(OR(BA44="",N(AR44)=0),"",BA44-AR44) -> 0 | BC44: =IF(OR(BA44="",N(U44)=0),"",BA44-U44) -> 0.14359279
A45: A-C | B45: 77 | C45: AFFT | D45: AFG | E45: AMERICAN FINANCIAL GROUP INC | F45: 11900 | G45: BABY_BOND | H45: FIXED | I45: no | J45: Q | K45: 4 | L45: 25 | M45: 0.075 | N45: 1.875 | O45: 15.68 | P45: OK | Q45: 0.09 | R45: 0.0825 | S45: 22.727273 | T45: 0.44944341 | U45: 0.5690225 | V45: -0.0075 | W45: =IF(N(Q45)=0,"",Q45+IF(I45="yes",Q45*Inputs!$B$10*Inputs!$B$9,0)+V45) -> 0.0825 | X45: =IF(OR(N(W45)<=0,N(N45)=0,N(L45)=0),"",MIN(L45,N45/W45)) -> 22.727273 | Y45: =IF(OR(X45="",N(O45)=0),"",X45/O45-1) -> 0.44944341 | Z45: =IF(OR(Y45="",N(O45)=0),"",Y45+N45/O45) -> 0.5690225 | AA45: =IF(OR(Z45="",N(U45)=0),"",Z45-U45) -> 0 | AB45: =IF(N(Q45)=0,"",Q45+IF(I45="yes",Q45*Inputs!$B$10*Inputs!$B$9,0)+IFERROR(INDEX(Inputs!$B$13:$B$15,MATCH(G45,Inputs!$A$13:$A$15,0)),0)+IFERROR(INDEX(Inputs!$B$18:$B$24,MATCH(H45,Inputs!$A$18:$A$24,0)),0)) -> 0.085 | AC45: =IF(OR(N(AB45)<=0,N(N45)=0,N(L45)=0),"",MIN(L45,N45/AB45)) -> 22.058824 | AD45: =IF(OR(AC45="",N(O45)=0),"",AC45/O45-1) -> 0.40681273 | AE45: =IF(OR(AD45="",N(O45)=0),"",AD45+N45/O45) -> 0.52639181 | AF45: =IF(OR(AE45="",N(Z45)=0),"",AE45-Z45) -> -0.042630689 | AG45: =IF(AND(N(M45)>0,N(L45)>0),M45*L45,N45) -> 1.875 | AH45: =IF(OR(N(AB45)<=0,N(AG45)=0,N(L45)=0),"",MIN(L45,AG45/AB45)) -> 22.058824 | AI45: =IF(OR(AH45="",N(O45)=0),"",AH45/O45-1) -> 0.40681273 | AJ45: =IF(OR(AI45="",N(O45)=0),"",AI45+AG45/O45) -> 0.52639181 | AK45: =IF(OR(AJ45="",N(AE45)=0),"",AJ45-AE45) -> 0 | AL45: =IF(N(F45)=0,"",INDEX(Inputs!$B$28:$B$32,IFERROR(MATCH(F45,Inputs!$A$28:$A$32,1),0)+1)) -> 0.08 | AN45: =IF(N(AM45)>0,AM45,AL45) -> 0.08 | AO45: =IF(N(AN45)=0,"",AN45+IF(I45="yes",AN45*Inputs!$B$10*Inputs!$B$9,0)+IFERROR(INDEX(Inputs!$B$13:$B$15,MATCH(G45,Inputs!$A$13:$A$15,0)),0)+IFERROR(INDEX(Inputs!$B$18:$B$24,MATCH(H45,Inputs!$A$18:$A$24,0)),0)) -> 0.075 | AP45: =IF(OR(N(AO45)<=0,N(AG45)=0,N(L45)=0),"",MIN(L45,AG45/AO45)) -> 25 | AQ45: =IF(OR(AP45="",N(O45)=0),"",AP45/O45-1) -> 0.59438776 | AR45: =IF(OR(AQ45="",N(O45)=0),"",AQ45+AG45/O45) -> 0.71396684 | AS45: =IF(OR(AR45="",N(AJ45)=0),"",AR45-AJ45) -> 0.18757503 | AT45: 25 | AU45: 1.88 | AV45: =IF(N(AT45)>0,AT45,L45) -> 25 | AW45: =IF(AND(N(M45)>0,N(AV45)>0),M45*AV45,IF(N(AU45)>0,AU45,N45)) -> 1.875 | AX45: =IF(N(AN45)=0,"",AN45+IF(I45="yes",AN45*Inputs!$B$10*Inputs!$B$9,0)+IFERROR(INDEX(Inputs!$B$13:$B$15,MATCH(G45,Inputs!$A$13:$A$15,0)),0)+IFERROR(INDEX(Inputs!$B$18:$B$24,MATCH(H45,Inputs!$A$18:$A$24,0)),0)) -> 0.075 | AY45: =IF(OR(N(AX45)<=0,N(AW45)=0,N(AV45)=0),"",MIN(AV45,AW45/AX45)) -> 25 | AZ45: =IF(OR(AY45="",N(O45)=0),"",AY45/O45-1) -> 0.59438776 | BA45: =IF(OR(AZ45="",N(O45)=0),"",AZ45+AW45/O45) -> 0.71396684 | BB45: =IF(OR(BA45="",N(AR45)=0),"",BA45-AR45) -> 0 | BC45: =IF(OR(BA45="",N(U45)=0),"",BA45-U45) -> 0.14494434
A46: A-C | B46: 80 | C46: AGM-C | D46: AGM | E46: FEDERAL AGRIC MTG CORP CL C | F46: 2100 | G46: PREFERRED | H46: FIXED | I46: yes | J46: Q | K46: 4 | L46: 25 | M46: 0.06 | N46: 1.5 | O46: 0 | P46: OK | Q46: 0.08 | R46: 0.076 | S46: 19.736842 | V46: 0 | W46: =IF(N(Q46)=0,"",Q46+IF(I46="yes",Q46*Inputs!$B$10*Inputs!$B$9,0)+V46) -> 0.076 | X46: =IF(OR(N(W46)<=0,N(N46)=0,N(L46)=0),"",MIN(L46,N46/W46)) -> 19.736842 | Y46: =IF(OR(X46="",N(O46)=0),"",X46/O46-1) | Z46: =IF(OR(Y46="",N(O46)=0),"",Y46+N46/O46) | AA46: =IF(OR(Z46="",N(U46)=0),"",Z46-U46) | AB46: =IF(N(Q46)=0,"",Q46+IF(I46="yes",Q46*Inputs!$B$10*Inputs!$B$9,0)+IFERROR(INDEX(Inputs!$B$13:$B$15,MATCH(G46,Inputs!$A$13:$A$15,0)),0)+IFERROR(INDEX(Inputs!$B$18:$B$24,MATCH(H46,Inputs!$A$18:$A$24,0)),0)) -> 0.076 | AC46: =IF(OR(N(AB46)<=0,N(N46)=0,N(L46)=0),"",MIN(L46,N46/AB46)) -> 19.736842 | AD46: =IF(OR(AC46="",N(O46)=0),"",AC46/O46-1) | AE46: =IF(OR(AD46="",N(O46)=0),"",AD46+N46/O46) | AF46: =IF(OR(AE46="",N(Z46)=0),"",AE46-Z46) | AG46: =IF(AND(N(M46)>0,N(L46)>0),M46*L46,N46) -> 1.5 | AH46: =IF(OR(N(AB46)<=0,N(AG46)=0,N(L46)=0),"",MIN(L46,AG46/AB46)) -> 19.736842 | AI46: =IF(OR(AH46="",N(O46)=0),"",AH46/O46-1) | AJ46: =IF(OR(AI46="",N(O46)=0),"",AI46+AG46/O46) | AK46: =IF(OR(AJ46="",N(AE46)=0),"",AJ46-AE46) | AL46: =IF(N(F46)=0,"",INDEX(Inputs!$B$28:$B$32,IFERROR(MATCH(F46,Inputs!$A$28:$A$32,1),0)+1)) -> 0.085 | AN46: =IF(N(AM46)>0,AM46,AL46) -> 0.085 | AO46: =IF(N(AN46)=0,"",AN46+IF(I46="yes",AN46*Inputs!$B$10*Inputs!$B$9,0)+IFERROR(INDEX(Inputs!$B$13:$B$15,MATCH(G46,Inputs!$A$13:$A$15,0)),0)+IFERROR(INDEX(Inputs!$B$18:$B$24,MATCH(H46,Inputs!$A$18:$A$24,0)),0)) -> 0.08075 | AP46: =IF(OR(N(AO46)<=0,N(AG46)=0,N(L46)=0),"",MIN(L46,AG46/AO46)) -> 18.575851 | AQ46: =IF(OR(AP46="",N(O46)=0),"",AP46/O46-1) | AR46: =IF(OR(AQ46="",N(O46)=0),"",AQ46+AG46/O46) | AS46: =IF(OR(AR46="",N(AJ46)=0),"",AR46-AJ46) | AV46: =IF(N(AT46)>0,AT46,L46) -> 25 | AW46: =IF(AND(N(M46)>0,N(AV46)>0),M46*AV46,IF(N(AU46)>0,AU46,N46)) -> 1.5 | AX46: =IF(N(AN46)=0,"",AN46+IF(I46="yes",AN46*Inputs!$B$10*Inputs!$B$9,0)+IFERROR(INDEX(Inputs!$B$13:$B$15,MATCH(G46,Inputs!$A$13:$A$15,0)),0)+IFERROR(INDEX(Inputs!$B$18:$B$24,MATCH(H46,Inputs!$A$18:$A$24,0)),0)) -> 0.08075 | AY46: =IF(OR(N(AX46)<=0,N(AW46)=0,N(AV46)=0),"",MIN(AV46,AW46/AX46)) -> 18.575851 | AZ46: =IF(OR(AY46="",N(O46)=0),"",AY46/O46-1) | BA46: =IF(OR(AZ46="",N(O46)=0),"",AZ46+AW46/O46) | BB46: =IF(OR(BA46="",N(AR46)=0),"",BA46-AR46) | BC46: =IF(OR(BA46="",N(U46)=0),"",BA46-U46) | BD46: NO PRICE; not in QOL paste - retire/rename?
A47: A-C | B47: 81 | C47: AGM-D | D47: AGM | E47: FEDERAL AGRIC MTG CORP CL C | F47: 2100 | G47: PREFERRED | H47: FIXED | I47: yes | J47: Q | K47: 4 | L47: 25 | M47: 0.057 | N47: 1.425 | O47: 21.29 | P47: OK | Q47: 0.08 | R47: 0.076 | S47: 18.75 | T47: -0.11930484 | U47: -0.052372006 | V47: 0 | W47: =IF(N(Q47)=0,"",Q47+IF(I47="yes",Q47*Inputs!$B$10*Inputs!$B$9,0)+V47) -> 0.076 | X47: =IF(OR(N(W47)<=0,N(N47)=0,N(L47)=0),"",MIN(L47,N47/W47)) -> 18.75 | Y47: =IF(OR(X47="",N(O47)=0),"",X47/O47-1) -> -0.11930484 | Z47: =IF(OR(Y47="",N(O47)=0),"",Y47+N47/O47) -> -0.052372006 | AA47: =IF(OR(Z47="",N(U47)=0),"",Z47-U47) -> 0 | AB47: =IF(N(Q47)=0,"",Q47+IF(I47="yes",Q47*Inputs!$B$10*Inputs!$B$9,0)+IFERROR(INDEX(Inputs!$B$13:$B$15,MATCH(G47,Inputs!$A$13:$A$15,0)),0)+IFERROR(INDEX(Inputs!$B$18:$B$24,MATCH(H47,Inputs!$A$18:$A$24,0)),0)) -> 0.076 | AC47: =IF(OR(N(AB47)<=0,N(N47)=0,N(L47)=0),"",MIN(L47,N47/AB47)) -> 18.75 | AD47: =IF(OR(AC47="",N(O47)=0),"",AC47/O47-1) -> -0.11930484 | AE47: =IF(OR(AD47="",N(O47)=0),"",AD47+N47/O47) -> -0.052372006 | AF47: =IF(OR(AE47="",N(Z47)=0),"",AE47-Z47) -> 0 | AG47: =IF(AND(N(M47)>0,N(L47)>0),M47*L47,N47) -> 1.425 | AH47: =IF(OR(N(AB47)<=0,N(AG47)=0,N(L47)=0),"",MIN(L47,AG47/AB47)) -> 18.75 | AI47: =IF(OR(AH47="",N(O47)=0),"",AH47/O47-1) -> -0.11930484 | AJ47: =IF(OR(AI47="",N(O47)=0),"",AI47+AG47/O47) -> -0.052372006 | AK47: =IF(OR(AJ47="",N(AE47)=0),"",AJ47-AE47) -> 0 | AL47: =IF(N(F47)=0,"",INDEX(Inputs!$B$28:$B$32,IFERROR(MATCH(F47,Inputs!$A$28:$A$32,1),0)+1)) -> 0.085 | AN47: =IF(N(AM47)>0,AM47,AL47) -> 0.085 | AO47: =IF(N(AN47)=0,"",AN47+IF(I47="yes",AN47*Inputs!$B$10*Inputs!$B$9,0)+IFERROR(INDEX(Inputs!$B$13:$B$15,MATCH(G47,Inputs!$A$13:$A$15,0)),0)+IFERROR(INDEX(Inputs!$B$18:$B$24,MATCH(H47,Inputs!$A$18:$A$24,0)),0)) -> 0.08075 | AP47: =IF(OR(N(AO47)<=0,N(AG47)=0,N(L47)=0),"",MIN(L47,AG47/AO47)) -> 17.647059 | AQ47: =IF(OR(AP47="",N(O47)=0),"",AP47/O47-1) -> -0.17111044 | AR47: =IF(OR(AQ47="",N(O47)=0),"",AQ47+AG47/O47) -> -0.1041776 | AS47: =IF(OR(AR47="",N(AJ47)=0),"",AR47-AJ47) -> -0.051805598 | AT47: 25 | AU47: 1.43 | AV47: =IF(N(AT47)>0,AT47,L47) -> 25 | AW47: =IF(AND(N(M47)>0,N(AV47)>0),M47*AV47,IF(N(AU47)>0,AU47,N47)) -> 1.425 | AX47: =IF(N(AN47)=0,"",AN47+IF(I47="yes",AN47*Inputs!$B$10*Inputs!$B$9,0)+IFERROR(INDEX(Inputs!$B$13:$B$15,MATCH(G47,Inputs!$A$13:$A$15,0)),0)+IFERROR(INDEX(Inputs!$B$18:$B$24,MATCH(H47,Inputs!$A$18:$A$24,0)),0)) -> 0.08075 | AY47: =IF(OR(N(AX47)<=0,N(AW47)=0,N(AV47)=0),"",MIN(AV47,AW47/AX47)) -> 17.647059 | AZ47: =IF(OR(AY47="",N(O47)=0),"",AY47/O47-1) -> -0.17111044 | BA47: =IF(OR(AZ47="",N(O47)=0),"",AZ47+AW47/O47) -> -0.1041776 | BB47: =IF(OR(BA47="",N(AR47)=0),"",BA47-AR47) -> 0 | BC47: =IF(OR(BA47="",N(U47)=0),"",BA47-U47) -> -0.051805598
A48: A-C | B48: 82 | C48: AGM-E | D48: AGM | E48: FEDERAL AGRIC MTG CORP CL C | F48: 2100 | G48: PREFERRED | H48: FIXED | I48: yes | J48: Q | K48: 4 | L48: 25 | M48: 0.0575 | N48: 1.4375 | O48: 20.82 | P48: OK | Q48: 0.08 | R48: 0.076 | S48: 18.914474 | T48: -0.091523838 | U48: -0.02247965 | V48: 0 | W48: =IF(N(Q48)=0,"",Q48+IF(I48="yes",Q48*Inputs!$B$10*Inputs!$B$9,0)+V48) -> 0.076 | X48: =IF(OR(N(W48)<=0,N(N48)=0,N(L48)=0),"",MIN(L48,N48/W48)) -> 18.914474 | Y48: =IF(OR(X48="",N(O48)=0),"",X48/O48-1) -> -0.091523838 | Z48: =IF(OR(Y48="",N(O48)=0),"",Y48+N48/O48) -> -0.02247965 | AA48: =IF(OR(Z48="",N(U48)=0),"",Z48-U48) -> 0 | AB48: =IF(N(Q48)=0,"",Q48+IF(I48="yes",Q48*Inputs!$B$10*Inputs!$B$9,0)+IFERROR(INDEX(Inputs!$B$13:$B$15,MATCH(G48,Inputs!$A$13:$A$15,0)),0)+IFERROR(INDEX(Inputs!$B$18:$B$24,MATCH(H48,Inputs!$A$18:$A$24,0)),0)) -> 0.076 | AC48: =IF(OR(N(AB48)<=0,N(N48)=0,N(L48)=0),"",MIN(L48,N48/AB48)) -> 18.914474 | AD48: =IF(OR(AC48="",N(O48)=0),"",AC48/O48-1) -> -0.091523838 | AE48: =IF(OR(AD48="",N(O48)=0),"",AD48+N48/O48) -> -0.02247965 | AF48: =IF(OR(AE48="",N(Z48)=0),"",AE48-Z48) -> 0 | AG48: =IF(AND(N(M48)>0,N(L48)>0),M48*L48,N48) -> 1.4375 | AH48: =IF(OR(N(AB48)<=0,N(AG48)=0,N(L48)=0),"",MIN(L48,AG48/AB48)) -> 18.914474 | AI48: =IF(OR(AH48="",N(O48)=0),"",AH48/O48-1) -> -0.091523838 | AJ48: =IF(OR(AI48="",N(O48)=0),"",AI48+AG48/O48) -> -0.02247965 | AK48: =IF(OR(AJ48="",N(AE48)=0),"",AJ48-AE48) -> 0 | AL48: =IF(N(F48)=0,"",INDEX(Inputs!$B$28:$B$32,IFERROR(MATCH(F48,Inputs!$A$28:$A$32,1),0)+1)) -> 0.085 | AN48: =IF(N(AM48)>0,AM48,AL48) -> 0.085 | AO48: =IF(N(AN48)=0,"",AN48+IF(I48="yes",AN48*Inputs!$B$10*Inputs!$B$9,0)+IFERROR(INDEX(Inputs!$B$13:$B$15,MATCH(G48,Inputs!$A$13:$A$15,0)),0)+IFERROR(INDEX(Inputs!$B$18:$B$24,MATCH(H48,Inputs!$A$18:$A$24,0)),0)) -> 0.08075 | AP48: =IF(OR(N(AO48)<=0,N(AG48)=0,N(L48)=0),"",MIN(L48,AG48/AO48)) -> 17.801858 | AQ48: =IF(OR(AP48="",N(O48)=0),"",AP48/O48-1) -> -0.14496361 | AR48: =IF(OR(AQ48="",N(O48)=0),"",AQ48+AG48/O48) -> -0.075919424 | AS48: =IF(OR(AR48="",N(AJ48)=0),"",AR48-AJ48) -> -0.053439774 | AT48: 25 | AU48: 1.4375 | AV48: =IF(N(AT48)>0,AT48,L48) -> 25 | AW48: =IF(AND(N(M48)>0,N(AV48)>0),M48*AV48,IF(N(AU48)>0,AU48,N48)) -> 1.4375 | AX48: =IF(N(AN48)=0,"",AN48+IF(I48="yes",AN48*Inputs!$B$10*Inputs!$B$9,0)+IFERROR(INDEX(Inputs!$B$13:$B$15,MATCH(G48,Inputs!$A$13:$A$15,0)),0)+IFERROR(INDEX(Inputs!$B$18:$B$24,MATCH(H48,Inputs!$A$18:$A$24,0)),0)) -> 0.08075 | AY48: =IF(OR(N(AX48)<=0,N(AW48)=0,N(AV48)=0),"",MIN(AV48,AW48/AX48)) -> 17.801858 | AZ48: =IF(OR(AY48="",N(O48)=0),"",AY48/O48-1) -> -0.14496361 | BA48: =IF(OR(AZ48="",N(O48)=0),"",AZ48+AW48/O48) -> -0.075919424 | BB48: =IF(OR(BA48="",N(AR48)=0),"",BA48-AR48) -> 0 | BC48: =IF(OR(BA48="",N(U48)=0),"",BA48-U48) -> -0.053439774
A49: A-C | B49: 83 | C49: AGM-F | D49: AGM | E49: FEDERAL AGRIC MTG CORP CL C | F49: 2100 | G49: PREFERRED | H49: FIXED | I49: yes | J49: Q | K49: 4 | L49: 25 | M49: 0.0525 | N49: 1.3125 | O49: 18.8 | P49: OK | Q49: 0.08 | R49: 0.076 | S49: 17.269737 | T49: -0.081396976 | U49: -0.011583147 | V49: 0 | W49: =IF(N(Q49)=0,"",Q49+IF(I49="yes",Q49*Inputs!$B$10*Inputs!$B$9,0)+V49) -> 0.076 | X49: =IF(OR(N(W49)<=0,N(N49)=0,N(L49)=0),"",MIN(L49,N49/W49)) -> 17.269737 | Y49: =IF(OR(X49="",N(O49)=0),"",X49/O49-1) -> -0.081396976 | Z49: =IF(OR(Y49="",N(O49)=0),"",Y49+N49/O49) -> -0.011583147 | AA49: =IF(OR(Z49="",N(U49)=0),"",Z49-U49) -> 0 | AB49: =IF(N(Q49)=0,"",Q49+IF(I49="yes",Q49*Inputs!$B$10*Inputs!$B$9,0)+IFERROR(INDEX(Inputs!$B$13:$B$15,MATCH(G49,Inputs!$A$13:$A$15,0)),0)+IFERROR(INDEX(Inputs!$B$18:$B$24,MATCH(H49,Inputs!$A$18:$A$24,0)),0)) -> 0.076 | AC49: =IF(OR(N(AB49)<=0,N(N49)=0,N(L49)=0),"",MIN(L49,N49/AB49)) -> 17.269737 | AD49: =IF(OR(AC49="",N(O49)=0),"",AC49/O49-1) -> -0.081396976 | AE49: =IF(OR(AD49="",N(O49)=0),"",AD49+N49/O49) -> -0.011583147 | AF49: =IF(OR(AE49="",N(Z49)=0),"",AE49-Z49) -> 0 | AG49: =IF(AND(N(M49)>0,N(L49)>0),M49*L49,N49) -> 1.3125 | AH49: =IF(OR(N(AB49)<=0,N(AG49)=0,N(L49)=0),"",MIN(L49,AG49/AB49)) -> 17.269737 | AI49: =IF(OR(AH49="",N(O49)=0),"",AH49/O49-1) -> -0.081396976 | AJ49: =IF(OR(AI49="",N(O49)=0),"",AI49+AG49/O49) -> -0.011583147 | AK49: =IF(OR(AJ49="",N(AE49)=0),"",AJ49-AE49) -> 0 | AL49: =IF(N(F49)=0,"",INDEX(Inputs!$B$28:$B$32,IFERROR(MATCH(F49,Inputs!$A$28:$A$32,1),0)+1)) -> 0.085 | AN49: =IF(N(AM49)>0,AM49,AL49) -> 0.085 | AO49: =IF(N(AN49)=0,"",AN49+IF(I49="yes",AN49*Inputs!$B$10*Inputs!$B$9,0)+IFERROR(INDEX(Inputs!$B$13:$B$15,MATCH(G49,Inputs!$A$13:$A$15,0)),0)+IFERROR(INDEX(Inputs!$B$18:$B$24,MATCH(H49,Inputs!$A$18:$A$24,0)),0)) -> 0.08075 | AP49: =IF(OR(N(AO49)<=0,N(AG49)=0,N(L49)=0),"",MIN(L49,AG49/AO49)) -> 16.25387 | AQ49: =IF(OR(AP49="",N(O49)=0),"",AP49/O49-1) -> -0.13543245 | AR49: =IF(OR(AQ49="",N(O49)=0),"",AQ49+AG49/O49) -> -0.065618619 | AS49: =IF(OR(AR49="",N(AJ49)=0),"",AR49-AJ49) -> -0.054035472 | AT49: 25 | AU49: 1.3125 | AV49: =IF(N(AT49)>0,AT49,L49) -> 25 | AW49: =IF(AND(N(M49)>0,N(AV49)>0),M49*AV49,IF(N(AU49)>0,AU49,N49)) -> 1.3125 | AX49: =IF(N(AN49)=0,"",AN49+IF(I49="yes",AN49*Inputs!$B$10*Inputs!$B$9,0)+IFERROR(INDEX(Inputs!$B$13:$B$15,MATCH(G49,Inputs!$A$13:$A$15,0)),0)+IFERROR(INDEX(Inputs!$B$18:$B$24,MATCH(H49,Inputs!$A$18:$A$24,0)),0)) -> 0.08075 | AY49: =IF(OR(N(AX49)<=0,N(AW49)=0,N(AV49)=0),"",MIN(AV49,AW49/AX49)) -> 16.25387 | AZ49: =IF(OR(AY49="",N(O49)=0),"",AY49/O49-1) -> -0.13543245 | BA49: =IF(OR(AZ49="",N(O49)=0),"",AZ49+AW49/O49) -> -0.065618619 | BB49: =IF(OR(BA49="",N(AR49)=0),"",BA49-AR49) -> 0 | BC49: =IF(OR(BA49="",N(U49)=0),"",BA49-U49) -> -0.054035472
A50: A-C | B50: 84 | C50: AGM-G | D50: AGM | E50: FEDERAL AGRIC MTG CORP CL C | F50: 2100 | G50: PREFERRED | H50: FIXED | I50: yes | J50: Q | K50: 4 | L50: 25 | M50: 0.04875 | N50: 1.21875 | O50: 17.35 | P50: OK | Q50: 0.08 | R50: 0.076 | S50: 16.036184 | T50: -0.075724253 | U50: -0.0054792962 | V50: 0 | W50: =IF(N(Q50)=0,"",Q50+IF(I50="yes",Q50*Inputs!$B$10*Inputs!$B$9,0)+V50) -> 0.076 | X50: =IF(OR(N(W50)<=0,N(N50)=0,N(L50)=0),"",MIN(L50,N50/W50)) -> 16.036184 | Y50: =IF(OR(X50="",N(O50)=0),"",X50/O50-1) -> -0.075724253 | Z50: =IF(OR(Y50="",N(O50)=0),"",Y50+N50/O50) -> -0.0054792962 | AA50: =IF(OR(Z50="",N(U50)=0),"",Z50-U50) -> 0 | AB50: =IF(N(Q50)=0,"",Q50+IF(I50="yes",Q50*Inputs!$B$10*Inputs!$B$9,0)+IFERROR(INDEX(Inputs!$B$13:$B$15,MATCH(G50,Inputs!$A$13:$A$15,0)),0)+IFERROR(INDEX(Inputs!$B$18:$B$24,MATCH(H50,Inputs!$A$18:$A$24,0)),0)) -> 0.076 | AC50: =IF(OR(N(AB50)<=0,N(N50)=0,N(L50)=0),"",MIN(L50,N50/AB50)) -> 16.036184 | AD50: =IF(OR(AC50="",N(O50)=0),"",AC50/O50-1) -> -0.075724253 | AE50: =IF(OR(AD50="",N(O50)=0),"",AD50+N50/O50) -> -0.0054792962 | AF50: =IF(OR(AE50="",N(Z50)=0),"",AE50-Z50) -> 0 | AG50: =IF(AND(N(M50)>0,N(L50)>0),M50*L50,N50) -> 1.21875 | AH50: =IF(OR(N(AB50)<=0,N(AG50)=0,N(L50)=0),"",MIN(L50,AG50/AB50)) -> 16.036184 | AI50: =IF(OR(AH50="",N(O50)=0),"",AH50/O50-1) -> -0.075724253 | AJ50: =IF(OR(AI50="",N(O50)=0),"",AI50+AG50/O50) -> -0.0054792962 | AK50: =IF(OR(AJ50="",N(AE50)=0),"",AJ50-AE50) -> 0 | AL50: =IF(N(F50)=0,"",INDEX(Inputs!$B$28:$B$32,IFERROR(MATCH(F50,Inputs!$A$28:$A$32,1),0)+1)) -> 0.085 | AN50: =IF(N(AM50)>0,AM50,AL50) -> 0.085 | AO50: =IF(N(AN50)=0,"",AN50+IF(I50="yes",AN50*Inputs!$B$10*Inputs!$B$9,0)+IFERROR(INDEX(Inputs!$B$13:$B$15,MATCH(G50,Inputs!$A$13:$A$15,0)),0)+IFERROR(INDEX(Inputs!$B$18:$B$24,MATCH(H50,Inputs!$A$18:$A$24,0)),0)) -> 0.08075 | AP50: =IF(OR(N(AO50)<=0,N(AG50)=0,N(L50)=0),"",MIN(L50,AG50/AO50)) -> 15.092879 | AQ50: =IF(OR(AP50="",N(O50)=0),"",AP50/O50-1) -> -0.13009341 | AR50: =IF(OR(AQ50="",N(O50)=0),"",AQ50+AG50/O50) -> -0.059848458 | AS50: =IF(OR(AR50="",N(AJ50)=0),"",AR50-AJ50) -> -0.054369162 | AT50: 25 | AU50: 1.21875 | AV50: =IF(N(AT50)>0,AT50,L50) -> 25 | AW50: =IF(AND(N(M50)>0,N(AV50)>0),M50*AV50,IF(N(AU50)>0,AU50,N50)) -> 1.21875 | AX50: =IF(N(AN50)=0,"",AN50+IF(I50="yes",AN50*Inputs!$B$10*Inputs!$B$9,0)+IFERROR(INDEX(Inputs!$B$13:$B$15,MATCH(G50,Inputs!$A$13:$A$15,0)),0)+IFERROR(INDEX(Inputs!$B$18:$B$24,MATCH(H50,Inputs!$A$18:$A$24,0)),0)) -> 0.08075 | AY50: =IF(OR(N(AX50)<=0,N(AW50)=0,N(AV50)=0),"",MIN(AV50,AW50/AX50)) -> 15.092879 | AZ50: =IF(OR(AY50="",N(O50)=0),"",AY50/O50-1) -> -0.13009341 | BA50: =IF(OR(AZ50="",N(O50)=0),"",AZ50+AW50/O50) -> -0.059848458 | BB50: =IF(OR(BA50="",N(AR50)=0),"",BA50-AR50) -> 0 | BC50: =IF(OR(BA50="",N(U50)=0),"",BA50-U50) -> -0.054369162
A51: A-C | B51: 87 | C51: AGNCL | D51: AGNC | E51: AGNC INVT CORP | F51: 12900 | G51: PREFERRED | H51: FIX_TO_FLOAT | I51: no | J51: Q | K51: 4 | L51: 25 | M51: 0.0775 | N51: 1.9375 | O51: 25.11 | P51: MISWIRED_CD | Q51: 0.09 | R51: 0.09 | S51: 21.527778 | T51: -0.14266118 | U51: -0.065500686 | V51: 0 | W51: =IF(N(Q51)=0,"",Q51+IF(I51="yes",Q51*Inputs!$B$10*Inputs!$B$9,0)+V51) -> 0.09 | X51: =IF(OR(N(W51)<=0,N(N51)=0,N(L51)=0),"",MIN(L51,N51/W51)) -> 21.527778 | Y51: =IF(OR(X51="",N(O51)=0),"",X51/O51-1) -> -0.14266118 | Z51: =IF(OR(Y51="",N(O51)=0),"",Y51+N51/O51) -> -0.065500686 | AA51: =IF(OR(Z51="",N(U51)=0),"",Z51-U51) -> 0 | AB51: =IF(N(Q51)=0,"",Q51+IF(I51="yes",Q51*Inputs!$B$10*Inputs!$B$9,0)+IFERROR(INDEX(Inputs!$B$13:$B$15,MATCH(G51,Inputs!$A$13:$A$15,0)),0)+IFERROR(INDEX(Inputs!$B$18:$B$24,MATCH(H51,Inputs!$A$18:$A$24,0)),0)) -> 0.09 | AC51: =IF(OR(N(AB51)<=0,N(N51)=0,N(L51)=0),"",MIN(L51,N51/AB51)) -> 21.527778 | AD51: =IF(OR(AC51="",N(O51)=0),"",AC51/O51-1) -> -0.14266118 | AE51: =IF(OR(AD51="",N(O51)=0),"",AD51+N51/O51) -> -0.065500686 | AF51: =IF(OR(AE51="",N(Z51)=0),"",AE51-Z51) -> 0 | AG51: =IF(AND(N(M51)>0,N(L51)>0),M51*L51,N51) -> 1.9375 | AH51: =IF(OR(N(AB51)<=0,N(AG51)=0,N(L51)=0),"",MIN(L51,AG51/AB51)) -> 21.527778 | AI51: =IF(OR(AH51="",N(O51)=0),"",AH51/O51-1) -> -0.14266118 | AJ51: =IF(OR(AI51="",N(O51)=0),"",AI51+AG51/O51) -> -0.065500686 | AK51: =IF(OR(AJ51="",N(AE51)=0),"",AJ51-AE51) -> 0 | AL51: =IF(N(F51)=0,"",INDEX(Inputs!$B$28:$B$32,IFERROR(MATCH(F51,Inputs!$A$28:$A$32,1),0)+1)) -> 0.08 | AN51: =IF(N(AM51)>0,AM51,AL51) -> 0.08 | AO51: =IF(N(AN51)=0,"",AN51+IF(I51="yes",AN51*Inputs!$B$10*Inputs!$B$9,0)+IFERROR(INDEX(Inputs!$B$13:$B$15,MATCH(G51,Inputs!$A$13:$A$15,0)),0)+IFERROR(INDEX(Inputs!$B$18:$B$24,MATCH(H51,Inputs!$A$18:$A$24,0)),0)) -> 0.08 | AP51: =IF(OR(N(AO51)<=0,N(AG51)=0,N(L51)=0),"",MIN(L51,AG51/AO51)) -> 24.21875 | AQ51: =IF(OR(AP51="",N(O51)=0),"",AP51/O51-1) -> -0.035493827 | AR51: =IF(OR(AQ51="",N(O51)=0),"",AQ51+AG51/O51) -> 0.041666667 | AS51: =IF(OR(AR51="",N(AJ51)=0),"",AR51-AJ51) -> 0.10716735 | AT51: 25 | AU51: 1.9375 | AV51: =IF(N(AT51)>0,AT51,L51) -> 25 | AW51: =IF(AND(N(M51)>0,N(AV51)>0),M51*AV51,IF(N(AU51)>0,AU51,N51)) -> 1.9375 | AX51: =IF(N(AN51)=0,"",AN51+IF(I51="yes",AN51*Inputs!$B$10*Inputs!$B$9,0)+IFERROR(INDEX(Inputs!$B$13:$B$15,MATCH(G51,Inputs!$A$13:$A$15,0)),0)+IFERROR(INDEX(Inputs!$B$18:$B$24,MATCH(H51,Inputs!$A$18:$A$24,0)),0)) -> 0.08 | AY51: =IF(OR(N(AX51)<=0,N(AW51)=0,N(AV51)=0),"",MIN(AV51,AW51/AX51)) -> 24.21875 | AZ51: =IF(OR(AY51="",N(O51)=0),"",AY51/O51-1) -> -0.035493827 | BA51: =IF(OR(AZ51="",N(O51)=0),"",AZ51+AW51/O51) -> 0.041666667 | BB51: =IF(OR(BA51="",N(AR51)=0),"",BA51-AR51) -> 0 | BC51: =IF(OR(BA51="",N(U51)=0),"",BA51-U51) -> 0.10716735 | BD51: wiring: reads C/D not D/E - no adjustments fired
A52: A-C | B52: 88 | C52: AGNCM | D52: AGNC | E52: AGNC INVT CORP | F52: 12900 | G52: PREFERRED | H52: FIX_TO_FLOAT | I52: no | J52: Q | K52: 4 | L52: 25 | M52: 0.06875 | N52: 1.71875 | O52: 25.16 | P52: OK | Q52: 0.09 | R52: 0.09 | S52: 19.097222 | T52: -0.24096891 | U52: -0.17265611 | V52: 0 | W52: =IF(N(Q52)=0,"",Q52+IF(I52="yes",Q52*Inputs!$B$10*Inputs!$B$9,0)+V52) -> 0.09 | X52: =IF(OR(N(W52)<=0,N(N52)=0,N(L52)=0),"",MIN(L52,N52/W52)) -> 19.097222 | Y52: =IF(OR(X52="",N(O52)=0),"",X52/O52-1) -> -0.24096891 | Z52: =IF(OR(Y52="",N(O52)=0),"",Y52+N52/O52) -> -0.17265611 | AA52: =IF(OR(Z52="",N(U52)=0),"",Z52-U52) -> 0 | AB52: =IF(N(Q52)=0,"",Q52+IF(I52="yes",Q52*Inputs!$B$10*Inputs!$B$9,0)+IFERROR(INDEX(Inputs!$B$13:$B$15,MATCH(G52,Inputs!$A$13:$A$15,0)),0)+IFERROR(INDEX(Inputs!$B$18:$B$24,MATCH(H52,Inputs!$A$18:$A$24,0)),0)) -> 0.09 | AC52: =IF(OR(N(AB52)<=0,N(N52)=0,N(L52)=0),"",MIN(L52,N52/AB52)) -> 19.097222 | AD52: =IF(OR(AC52="",N(O52)=0),"",AC52/O52-1) -> -0.24096891 | AE52: =IF(OR(AD52="",N(O52)=0),"",AD52+N52/O52) -> -0.17265611 | AF52: =IF(OR(AE52="",N(Z52)=0),"",AE52-Z52) -> 0 | AG52: =IF(AND(N(M52)>0,N(L52)>0),M52*L52,N52) -> 1.71875 | AH52: =IF(OR(N(AB52)<=0,N(AG52)=0,N(L52)=0),"",MIN(L52,AG52/AB52)) -> 19.097222 | AI52: =IF(OR(AH52="",N(O52)=0),"",AH52/O52-1) -> -0.24096891 | AJ52: =IF(OR(AI52="",N(O52)=0),"",AI52+AG52/O52) -> -0.17265611 | AK52: =IF(OR(AJ52="",N(AE52)=0),"",AJ52-AE52) -> 0 | AL52: =IF(N(F52)=0,"",INDEX(Inputs!$B$28:$B$32,IFERROR(MATCH(F52,Inputs!$A$28:$A$32,1),0)+1)) -> 0.08 | AN52: =IF(N(AM52)>0,AM52,AL52) -> 0.08 | AO52: =IF(N(AN52)=0,"",AN52+IF(I52="yes",AN52*Inputs!$B$10*Inputs!$B$9,0)+IFERROR(INDEX(Inputs!$B$13:$B$15,MATCH(G52,Inputs!$A$13:$A$15,0)),0)+IFERROR(INDEX(Inputs!$B$18:$B$24,MATCH(H52,Inputs!$A$18:$A$24,0)),0)) -> 0.08 | AP52: =IF(OR(N(AO52)<=0,N(AG52)=0,N(L52)=0),"",MIN(L52,AG52/AO52)) -> 21.484375 | AQ52: =IF(OR(AP52="",N(O52)=0),"",AP52/O52-1) -> -0.14609002 | AR52: =IF(OR(AQ52="",N(O52)=0),"",AQ52+AG52/O52) -> -0.077777226 | AS52: =IF(OR(AR52="",N(AJ52)=0),"",AR52-AJ52) -> 0.094878886 | AT52: 25 | AV52: =IF(N(AT52)>0,AT52,L52) -> 25 | AW52: =IF(AND(N(M52)>0,N(AV52)>0),M52*AV52,IF(N(AU52)>0,AU52,N52)) -> 1.71875 | AX52: =IF(N(AN52)=0,"",AN52+IF(I52="yes",AN52*Inputs!$B$10*Inputs!$B$9,0)+IFERROR(INDEX(Inputs!$B$13:$B$15,MATCH(G52,Inputs!$A$13:$A$15,0)),0)+IFERROR(INDEX(Inputs!$B$18:$B$24,MATCH(H52,Inputs!$A$18:$A$24,0)),0)) -> 0.08 | AY52: =IF(OR(N(AX52)<=0,N(AW52)=0,N(AV52)=0),"",MIN(AV52,AW52/AX52)) -> 21.484375 | AZ52: =IF(OR(AY52="",N(O52)=0),"",AY52/O52-1) -> -0.14609002 | BA52: =IF(OR(AZ52="",N(O52)=0),"",AZ52+AW52/O52) -> -0.077777226 | BB52: =IF(OR(BA52="",N(AR52)=0),"",BA52-AR52) -> 0 | BC52: =IF(OR(BA52="",N(U52)=0),"",BA52-U52) -> 0.094878886
A53: A-C | B53: 89 | C53: AGNCN | D53: AGNC | E53: AGNC INVT CORP | F53: 12900 | G53: PREFERRED | H53: FIXED | I53: no | J53: Q | K53: 4 | L53: 25 | M53: 0.07 | N53: 1.75 | O53: 25.86 | P53: OK | Q53: 0.09 | R53: 0.09 | S53: 19.444444 | T53: -0.248088 | U53: -0.18041591 | V53: 0 | W53: =IF(N(Q53)=0,"",Q53+IF(I53="yes",Q53*Inputs!$B$10*Inputs!$B$9,0)+V53) -> 0.09 | X53: =IF(OR(N(W53)<=0,N(N53)=0,N(L53)=0),"",MIN(L53,N53/W53)) -> 19.444444 | Y53: =IF(OR(X53="",N(O53)=0),"",X53/O53-1) -> -0.248088 | Z53: =IF(OR(Y53="",N(O53)=0),"",Y53+N53/O53) -> -0.18041591 | AA53: =IF(OR(Z53="",N(U53)=0),"",Z53-U53) -> 0 | AB53: =IF(N(Q53)=0,"",Q53+IF(I53="yes",Q53*Inputs!$B$10*Inputs!$B$9,0)+IFERROR(INDEX(Inputs!$B$13:$B$15,MATCH(G53,Inputs!$A$13:$A$15,0)),0)+IFERROR(INDEX(Inputs!$B$18:$B$24,MATCH(H53,Inputs!$A$18:$A$24,0)),0)) -> 0.09 | AC53: =IF(OR(N(AB53)<=0,N(N53)=0,N(L53)=0),"",MIN(L53,N53/AB53)) -> 19.444444 | AD53: =IF(OR(AC53="",N(O53)=0),"",AC53/O53-1) -> -0.248088 | AE53: =IF(OR(AD53="",N(O53)=0),"",AD53+N53/O53) -> -0.18041591 | AF53: =IF(OR(AE53="",N(Z53)=0),"",AE53-Z53) -> 0 | AG53: =IF(AND(N(M53)>0,N(L53)>0),M53*L53,N53) -> 1.75 | AH53: =IF(OR(N(AB53)<=0,N(AG53)=0,N(L53)=0),"",MIN(L53,AG53/AB53)) -> 19.444444 | AI53: =IF(OR(AH53="",N(O53)=0),"",AH53/O53-1) -> -0.248088 | AJ53: =IF(OR(AI53="",N(O53)=0),"",AI53+AG53/O53) -> -0.18041591 | AK53: =IF(OR(AJ53="",N(AE53)=0),"",AJ53-AE53) -> 0 | AL53: =IF(N(F53)=0,"",INDEX(Inputs!$B$28:$B$32,IFERROR(MATCH(F53,Inputs!$A$28:$A$32,1),0)+1)) -> 0.08 | AN53: =IF(N(AM53)>0,AM53,AL53) -> 0.08 | AO53: =IF(N(AN53)=0,"",AN53+IF(I53="yes",AN53*Inputs!$B$10*Inputs!$B$9,0)+IFERROR(INDEX(Inputs!$B$13:$B$15,MATCH(G53,Inputs!$A$13:$A$15,0)),0)+IFERROR(INDEX(Inputs!$B$18:$B$24,MATCH(H53,Inputs!$A$18:$A$24,0)),0)) -> 0.08 | AP53: =IF(OR(N(AO53)<=0,N(AG53)=0,N(L53)=0),"",MIN(L53,AG53/AO53)) -> 21.875 | AQ53: =IF(OR(AP53="",N(O53)=0),"",AP53/O53-1) -> -0.15409899 | AR53: =IF(OR(AQ53="",N(O53)=0),"",AQ53+AG53/O53) -> -0.086426914 | AS53: =IF(OR(AR53="",N(AJ53)=0),"",AR53-AJ53) -> 0.093989001 | AT53: 25 | AU53: 1.75 | AV53: =IF(N(AT53)>0,AT53,L53) -> 25 | AW53: =IF(AND(N(M53)>0,N(AV53)>0),M53*AV53,IF(N(AU53)>0,AU53,N53)) -> 1.75 | AX53: =IF(N(AN53)=0,"",AN53+IF(I53="yes",AN53*Inputs!$B$10*Inputs!$B$9,0)+IFERROR(INDEX(Inputs!$B$13:$B$15,MATCH(G53,Inputs!$A$13:$A$15,0)),0)+IFERROR(INDEX(Inputs!$B$18:$B$24,MATCH(H53,Inputs!$A$18:$A$24,0)),0)) -> 0.08 | AY53: =IF(OR(N(AX53)<=0,N(AW53)=0,N(AV53)=0),"",MIN(AV53,AW53/AX53)) -> 21.875 | AZ53: =IF(OR(AY53="",N(O53)=0),"",AY53/O53-1) -> -0.15409899 | BA53: =IF(OR(AZ53="",N(O53)=0),"",AZ53+AW53/O53) -> -0.086426914 | BB53: =IF(OR(BA53="",N(AR53)=0),"",BA53-AR53) -> 0 | BC53: =IF(OR(BA53="",N(U53)=0),"",BA53-U53) -> 0.093989001
A54: A-C | B54: 90 | C54: AGNCO | D54: AGNC | E54: AGNC INVT CORP | F54: 12900 | G54: PREFERRED | H54: FIX_TO_FLOAT | I54: no | J54: Q | K54: 4 | L54: 25 | M54: 0.0652 | N54: 1.63 | O54: 25.65 | P54: OK | Q54: 0.09 | R54: 0.09 | S54: 18.111111 | T54: -0.2939138 | U54: -0.23036604 | V54: 0 | W54: =IF(N(Q54)=0,"",Q54+IF(I54="yes",Q54*Inputs!$B$10*Inputs!$B$9,0)+V54) -> 0.09 | X54: =IF(OR(N(W54)<=0,N(N54)=0,N(L54)=0),"",MIN(L54,N54/W54)) -> 18.111111 | Y54: =IF(OR(X54="",N(O54)=0),"",X54/O54-1) -> -0.2939138 | Z54: =IF(OR(Y54="",N(O54)=0),"",Y54+N54/O54) -> -0.23036604 | AA54: =IF(OR(Z54="",N(U54)=0),"",Z54-U54) -> 0 | AB54: =IF(N(Q54)=0,"",Q54+IF(I54="yes",Q54*Inputs!$B$10*Inputs!$B$9,0)+IFERROR(INDEX(Inputs!$B$13:$B$15,MATCH(G54,Inputs!$A$13:$A$15,0)),0)+IFERROR(INDEX(Inputs!$B$18:$B$24,MATCH(H54,Inputs!$A$18:$A$24,0)),0)) -> 0.09 | AC54: =IF(OR(N(AB54)<=0,N(N54)=0,N(L54)=0),"",MIN(L54,N54/AB54)) -> 18.111111 | AD54: =IF(OR(AC54="",N(O54)=0),"",AC54/O54-1) -> -0.2939138 | AE54: =IF(OR(AD54="",N(O54)=0),"",AD54+N54/O54) -> -0.23036604 | AF54: =IF(OR(AE54="",N(Z54)=0),"",AE54-Z54) -> 0 | AG54: =IF(AND(N(M54)>0,N(L54)>0),M54*L54,N54) -> 1.63 | AH54: =IF(OR(N(AB54)<=0,N(AG54)=0,N(L54)=0),"",MIN(L54,AG54/AB54)) -> 18.111111 | AI54: =IF(OR(AH54="",N(O54)=0),"",AH54/O54-1) -> -0.2939138 | AJ54: =IF(OR(AI54="",N(O54)=0),"",AI54+AG54/O54) -> -0.23036604 | AK54: =IF(OR(AJ54="",N(AE54)=0),"",AJ54-AE54) -> 0 | AL54: =IF(N(F54)=0,"",INDEX(Inputs!$B$28:$B$32,IFERROR(MATCH(F54,Inputs!$A$28:$A$32,1),0)+1)) -> 0.08 | AN54: =IF(N(AM54)>0,AM54,AL54) -> 0.08 | AO54: =IF(N(AN54)=0,"",AN54+IF(I54="yes",AN54*Inputs!$B$10*Inputs!$B$9,0)+IFERROR(INDEX(Inputs!$B$13:$B$15,MATCH(G54,Inputs!$A$13:$A$15,0)),0)+IFERROR(INDEX(Inputs!$B$18:$B$24,MATCH(H54,Inputs!$A$18:$A$24,0)),0)) -> 0.08 | AP54: =IF(OR(N(AO54)<=0,N(AG54)=0,N(L54)=0),"",MIN(L54,AG54/AO54)) -> 20.375 | AQ54: =IF(OR(AP54="",N(O54)=0),"",AP54/O54-1) -> -0.20565302 | AR54: =IF(OR(AQ54="",N(O54)=0),"",AQ54+AG54/O54) -> -0.14210526 | AS54: =IF(OR(AR54="",N(AJ54)=0),"",AR54-AJ54) -> 0.088260775 | AT54: 25 | AU54: 1.63 | AV54: =IF(N(AT54)>0,AT54,L54) -> 25 | AW54: =IF(AND(N(M54)>0,N(AV54)>0),M54*AV54,IF(N(AU54)>0,AU54,N54)) -> 1.63 | AX54: =IF(N(AN54)=0,"",AN54+IF(I54="yes",AN54*Inputs!$B$10*Inputs!$B$9,0)+IFERROR(INDEX(Inputs!$B$13:$B$15,MATCH(G54,Inputs!$A$13:$A$15,0)),0)+IFERROR(INDEX(Inputs!$B$18:$B$24,MATCH(H54,Inputs!$A$18:$A$24,0)),0)) -> 0.08 | AY54: =IF(OR(N(AX54)<=0,N(AW54)=0,N(AV54)=0),"",MIN(AV54,AW54/AX54)) -> 20.375 | AZ54: =IF(OR(AY54="",N(O54)=0),"",AY54/O54-1) -> -0.20565302 | BA54: =IF(OR(AZ54="",N(O54)=0),"",AZ54+AW54/O54) -> -0.14210526 | BB54: =IF(OR(BA54="",N(AR54)=0),"",BA54-AR54) -> 0 | BC54: =IF(OR(BA54="",N(U54)=0),"",BA54-U54) -> 0.088260775
A55: A-C | B55: 91 | C55: AGNCP | D55: AGNC | E55: AGNC INVT CORP | F55: 12900 | G55: PREFERRED | H55: FIX_TO_FLOAT | I55: no | J55: Q | K55: 4 | L55: 25 | M55: 0.06125 | N55: 1.53125 | O55: 25.38 | P55: OK | Q55: 0.09 | R55: 0.09 | S55: 17.013889 | T55: -0.32963401 | U55: -0.26930107 | V55: 0 | W55: =IF(N(Q55)=0,"",Q55+IF(I55="yes",Q55*Inputs!$B$10*Inputs!$B$9,0)+V55) -> 0.09 | X55: =IF(OR(N(W55)<=0,N(N55)=0,N(L55)=0),"",MIN(L55,N55/W55)) -> 17.013889 | Y55: =IF(OR(X55="",N(O55)=0),"",X55/O55-1) -> -0.32963401 | Z55: =IF(OR(Y55="",N(O55)=0),"",Y55+N55/O55) -> -0.26930107 | AA55: =IF(OR(Z55="",N(U55)=0),"",Z55-U55) -> 0 | AB55: =IF(N(Q55)=0,"",Q55+IF(I55="yes",Q55*Inputs!$B$10*Inputs!$B$9,0)+IFERROR(INDEX(Inputs!$B$13:$B$15,MATCH(G55,Inputs!$A$13:$A$15,0)),0)+IFERROR(INDEX(Inputs!$B$18:$B$24,MATCH(H55,Inputs!$A$18:$A$24,0)),0)) -> 0.09 | AC55: =IF(OR(N(AB55)<=0,N(N55)=0,N(L55)=0),"",MIN(L55,N55/AB55)) -> 17.013889 | AD55: =IF(OR(AC55="",N(O55)=0),"",AC55/O55-1) -> -0.32963401 | AE55: =IF(OR(AD55="",N(O55)=0),"",AD55+N55/O55) -> -0.26930107 | AF55: =IF(OR(AE55="",N(Z55)=0),"",AE55-Z55) -> 0 | AG55: =IF(AND(N(M55)>0,N(L55)>0),M55*L55,N55) -> 1.53125 | AH55: =IF(OR(N(AB55)<=0,N(AG55)=0,N(L55)=0),"",MIN(L55,AG55/AB55)) -> 17.013889 | AI55: =IF(OR(AH55="",N(O55)=0),"",AH55/O55-1) -> -0.32963401 | AJ55: =IF(OR(AI55="",N(O55)=0),"",AI55+AG55/O55) -> -0.26930107 | AK55: =IF(OR(AJ55="",N(AE55)=0),"",AJ55-AE55) -> 0 | AL55: =IF(N(F55)=0,"",INDEX(Inputs!$B$28:$B$32,IFERROR(MATCH(F55,Inputs!$A$28:$A$32,1),0)+1)) -> 0.08 | AN55: =IF(N(AM55)>0,AM55,AL55) -> 0.08 | AO55: =IF(N(AN55)=0,"",AN55+IF(I55="yes",AN55*Inputs!$B$10*Inputs!$B$9,0)+IFERROR(INDEX(Inputs!$B$13:$B$15,MATCH(G55,Inputs!$A$13:$A$15,0)),0)+IFERROR(INDEX(Inputs!$B$18:$B$24,MATCH(H55,Inputs!$A$18:$A$24,0)),0)) -> 0.08 | AP55: =IF(OR(N(AO55)<=0,N(AG55)=0,N(L55)=0),"",MIN(L55,AG55/AO55)) -> 19.140625 | AQ55: =IF(OR(AP55="",N(O55)=0),"",AP55/O55-1) -> -0.24583826 | AR55: =IF(OR(AQ55="",N(O55)=0),"",AQ55+AG55/O55) -> -0.18550532 | AS55: =IF(OR(AR55="",N(AJ55)=0),"",AR55-AJ55) -> 0.083795749 | AT55: 25 | AU55: 1.53125 | AV55: =IF(N(AT55)>0,AT55,L55) -> 25 | AW55: =IF(AND(N(M55)>0,N(AV55)>0),M55*AV55,IF(N(AU55)>0,AU55,N55)) -> 1.53125 | AX55: =IF(N(AN55)=0,"",AN55+IF(I55="yes",AN55*Inputs!$B$10*Inputs!$B$9,0)+IFERROR(INDEX(Inputs!$B$13:$B$15,MATCH(G55,Inputs!$A$13:$A$15,0)),0)+IFERROR(INDEX(Inputs!$B$18:$B$24,MATCH(H55,Inputs!$A$18:$A$24,0)),0)) -> 0.08 | AY55: =IF(OR(N(AX55)<=0,N(AW55)=0,N(AV55)=0),"",MIN(AV55,AW55/AX55)) -> 19.140625 | AZ55: =IF(OR(AY55="",N(O55)=0),"",AY55/O55-1) -> -0.24583826 | BA55: =IF(OR(AZ55="",N(O55)=0),"",AZ55+AW55/O55) -> -0.18550532 | BB55: =IF(OR(BA55="",N(AR55)=0),"",BA55-AR55) -> 0 | BC55: =IF(OR(BA55="",N(U55)=0),"",BA55-U55) -> 0.083795749
A56: A-C | B56: 94 | C56: CTGSP | D56: AGR | E56: na | G56: PREFERRED | H56: FIXED | I56: yes | J56: Q | K56: 4 | L56: 3.125 | M56: 0.08 | N56: 0.25 | O56: 2.93 | P56: OK | Q56: 0 | R56: 0 | V56: 0 | W56: =IF(N(Q56)=0,"",Q56+IF(I56="yes",Q56*Inputs!$B$10*Inputs!$B$9,0)+V56) | X56: =IF(OR(N(W56)<=0,N(N56)=0,N(L56)=0),"",MIN(L56,N56/W56)) | Y56: =IF(OR(X56="",N(O56)=0),"",X56/O56-1) | Z56: =IF(OR(Y56="",N(O56)=0),"",Y56+N56/O56) | AA56: =IF(OR(Z56="",N(U56)=0),"",Z56-U56) | AB56: =IF(N(Q56)=0,"",Q56+IF(I56="yes",Q56*Inputs!$B$10*Inputs!$B$9,0)+IFERROR(INDEX(Inputs!$B$13:$B$15,MATCH(G56,Inputs!$A$13:$A$15,0)),0)+IFERROR(INDEX(Inputs!$B$18:$B$24,MATCH(H56,Inputs!$A$18:$A$24,0)),0)) | AC56: =IF(OR(N(AB56)<=0,N(N56)=0,N(L56)=0),"",MIN(L56,N56/AB56)) | AD56: =IF(OR(AC56="",N(O56)=0),"",AC56/O56-1) | AE56: =IF(OR(AD56="",N(O56)=0),"",AD56+N56/O56) | AF56: =IF(OR(AE56="",N(Z56)=0),"",AE56-Z56) | AG56: =IF(AND(N(M56)>0,N(L56)>0),M56*L56,N56) -> 0.25 | AH56: =IF(OR(N(AB56)<=0,N(AG56)=0,N(L56)=0),"",MIN(L56,AG56/AB56)) | AI56: =IF(OR(AH56="",N(O56)=0),"",AH56/O56-1) | AJ56: =IF(OR(AI56="",N(O56)=0),"",AI56+AG56/O56) | AK56: =IF(OR(AJ56="",N(AE56)=0),"",AJ56-AE56) | AL56: =IF(N(F56)=0,"",INDEX(Inputs!$B$28:$B$32,IFERROR(MATCH(F56,Inputs!$A$28:$A$32,1),0)+1)) | AN56: =IF(N(AM56)>0,AM56,AL56) | AO56: =IF(N(AN56)=0,"",AN56+IF(I56="yes",AN56*Inputs!$B$10*Inputs!$B$9,0)+IFERROR(INDEX(Inputs!$B$13:$B$15,MATCH(G56,Inputs!$A$13:$A$15,0)),0)+IFERROR(INDEX(Inputs!$B$18:$B$24,MATCH(H56,Inputs!$A$18:$A$24,0)),0)) | AP56: =IF(OR(N(AO56)<=0,N(AG56)=0,N(L56)=0),"",MIN(L56,AG56/AO56)) | AQ56: =IF(OR(AP56="",N(O56)=0),"",AP56/O56-1) | AR56: =IF(OR(AQ56="",N(O56)=0),"",AQ56+AG56/O56) | AS56: =IF(OR(AR56="",N(AJ56)=0),"",AR56-AJ56) | AT56: 3.13 | AU56: 0.25 | AV56: =IF(N(AT56)>0,AT56,L56) -> 3.13 | AW56: =IF(AND(N(M56)>0,N(AV56)>0),M56*AV56,IF(N(AU56)>0,AU56,N56)) -> 0.2504 | AX56: =IF(N(AN56)=0,"",AN56+IF(I56="yes",AN56*Inputs!$B$10*Inputs!$B$9,0)+IFERROR(INDEX(Inputs!$B$13:$B$15,MATCH(G56,Inputs!$A$13:$A$15,0)),0)+IFERROR(INDEX(Inputs!$B$18:$B$24,MATCH(H56,Inputs!$A$18:$A$24,0)),0)) | AY56: =IF(OR(N(AX56)<=0,N(AW56)=0,N(AV56)=0),"",MIN(AV56,AW56/AX56)) | AZ56: =IF(OR(AY56="",N(O56)=0),"",AY56/O56-1) | BA56: =IF(OR(AZ56="",N(O56)=0),"",AZ56+AW56/O56) | BB56: =IF(OR(BA56="",N(AR56)=0),"",BA56-AR56) | BC56: =IF(OR(BA56="",N(U56)=0),"",BA56-U56) | BD56: group base = 0 (parent did not quote)
A57: A-C | B57: 98 | C57: AHH-A | D57: AHH | E57: na | G57: PREFERRED | H57: FIXED | I57: no | J57: Q | K57: 4 | L57: 25 | M57: 0.0675 | N57: 1.6875 | O57: 0 | P57: OK | Q57: 0 | R57: 0 | V57: 0 | W57: =IF(N(Q57)=0,"",Q57+IF(I57="yes",Q57*Inputs!$B$10*Inputs!$B$9,0)+V57) | X57: =IF(OR(N(W57)<=0,N(N57)=0,N(L57)=0),"",MIN(L57,N57/W57)) | Y57: =IF(OR(X57="",N(O57)=0),"",X57/O57-1) | Z57: =IF(OR(Y57="",N(O57)=0),"",Y57+N57/O57) | AA57: =IF(OR(Z57="",N(U57)=0),"",Z57-U57) | AB57: =IF(N(Q57)=0,"",Q57+IF(I57="yes",Q57*Inputs!$B$10*Inputs!$B$9,0)+IFERROR(INDEX(Inputs!$B$13:$B$15,MATCH(G57,Inputs!$A$13:$A$15,0)),0)+IFERROR(INDEX(Inputs!$B$18:$B$24,MATCH(H57,Inputs!$A$18:$A$24,0)),0)) | AC57: =IF(OR(N(AB57)<=0,N(N57)=0,N(L57)=0),"",MIN(L57,N57/AB57)) | AD57: =IF(OR(AC57="",N(O57)=0),"",AC57/O57-1) | AE57: =IF(OR(AD57="",N(O57)=0),"",AD57+N57/O57) | AF57: =IF(OR(AE57="",N(Z57)=0),"",AE57-Z57) | AG57: =IF(AND(N(M57)>0,N(L57)>0),M57*L57,N57) -> 1.6875 | AH57: =IF(OR(N(AB57)<=0,N(AG57)=0,N(L57)=0),"",MIN(L57,AG57/AB57)) | AI57: =IF(OR(AH57="",N(O57)=0),"",AH57/O57-1) | AJ57: =IF(OR(AI57="",N(O57)=0),"",AI57+AG57/O57) | AK57: =IF(OR(AJ57="",N(AE57)=0),"",AJ57-AE57) | AL57: =IF(N(F57)=0,"",INDEX(Inputs!$B$28:$B$32,IFERROR(MATCH(F57,Inputs!$A$28:$A$32,1),0)+1)) | AN57: =IF(N(AM57)>0,AM57,AL57) | AO57: =IF(N(AN57)=0,"",AN57+IF(I57="yes",AN57*Inputs!$B$10*Inputs!$B$9,0)+IFERROR(INDEX(Inputs!$B$13:$B$15,MATCH(G57,Inputs!$A$13:$A$15,0)),0)+IFERROR(INDEX(Inputs!$B$18:$B$24,MATCH(H57,Inputs!$A$18:$A$24,0)),0)) | AP57: =IF(OR(N(AO57)<=0,N(AG57)=0,N(L57)=0),"",MIN(L57,AG57/AO57)) | AQ57: =IF(OR(AP57="",N(O57)=0),"",AP57/O57-1) | AR57: =IF(OR(AQ57="",N(O57)=0),"",AQ57+AG57/O57) | AS57: =IF(OR(AR57="",N(AJ57)=0),"",AR57-AJ57) | AV57: =IF(N(AT57)>0,AT57,L57) -> 25 | AW57: =IF(AND(N(M57)>0,N(AV57)>0),M57*AV57,IF(N(AU57)>0,AU57,N57)) -> 1.6875 | AX57: =IF(N(AN57)=0,"",AN57+IF(I57="yes",AN57*Inputs!$B$10*Inputs!$B$9,0)+IFERROR(INDEX(Inputs!$B$13:$B$15,MATCH(G57,Inputs!$A$13:$A$15,0)),0)+IFERROR(INDEX(Inputs!$B$18:$B$24,MATCH(H57,Inputs!$A$18:$A$24,0)),0)) | AY57: =IF(OR(N(AX57)<=0,N(AW57)=0,N(AV57)=0),"",MIN(AV57,AW57/AX57)) | AZ57: =IF(OR(AY57="",N(O57)=0),"",AY57/O57-1) | BA57: =IF(OR(AZ57="",N(O57)=0),"",AZ57+AW57/O57) | BB57: =IF(OR(BA57="",N(AR57)=0),"",BA57-AR57) | BC57: =IF(OR(BA57="",N(U57)=0),"",BA57-U57) | BD57: NO PRICE; not in QOL paste - retire/rename?; group base = 0 (parent did not quote)
A58: A-C | B58: 102 | C58: AHT-D | D58: AHT | E58: ASHFORD HOSPITALITY TR INC COM NEW | F58: 21 | G58: PREFERRED | H58: FIXED | I58: no | J58: Q | K58: 4 | L58: 25 | M58: 0.0845 | N58: 2.1125 | O58: 7.61 | P58: CONST | Q58: 0.1 | R58: 0.085 | S58: 24.852941 | T58: 2.2658267 | U58: 2.543422 | V58: 0 | W58: =IF(N(Q58)=0,"",Q58+IF(I58="yes",Q58*Inputs!$B$10*Inputs!$B$9,0)+V58) -> 0.1 | X58: =IF(OR(N(W58)<=0,N(N58)=0,N(L58)=0),"",MIN(L58,N58/W58)) -> 21.125 | Y58: =IF(OR(X58="",N(O58)=0),"",X58/O58-1) -> 1.7759527 | Z58: =IF(OR(Y58="",N(O58)=0),"",Y58+N58/O58) -> 2.053548 | AA58: =IF(OR(Z58="",N(U58)=0),"",Z58-U58) -> -0.489874 | AB58: =IF(N(Q58)=0,"",Q58+IF(I58="yes",Q58*Inputs!$B$10*Inputs!$B$9,0)+IFERROR(INDEX(Inputs!$B$13:$B$15,MATCH(G58,Inputs!$A$13:$A$15,0)),0)+IFERROR(INDEX(Inputs!$B$18:$B$24,MATCH(H58,Inputs!$A$18:$A$24,0)),0)) -> 0.1 | AC58: =IF(OR(N(AB58)<=0,N(N58)=0,N(L58)=0),"",MIN(L58,N58/AB58)) -> 21.125 | AD58: =IF(OR(AC58="",N(O58)=0),"",AC58/O58-1) -> 1.7759527 | AE58: =IF(OR(AD58="",N(O58)=0),"",AD58+N58/O58) -> 2.053548 | AF58: =IF(OR(AE58="",N(Z58)=0),"",AE58-Z58) -> 0 | AG58: =IF(AND(N(M58)>0,N(L58)>0),M58*L58,N58) -> 2.1125 | AH58: =IF(OR(N(AB58)<=0,N(AG58)=0,N(L58)=0),"",MIN(L58,AG58/AB58)) -> 21.125 | AI58: =IF(OR(AH58="",N(O58)=0),"",AH58/O58-1) -> 1.7759527 | AJ58: =IF(OR(AI58="",N(O58)=0),"",AI58+AG58/O58) -> 2.053548 | AK58: =IF(OR(AJ58="",N(AE58)=0),"",AJ58-AE58) -> 0 | AL58: =IF(N(F58)=0,"",INDEX(Inputs!$B$28:$B$32,IFERROR(MATCH(F58,Inputs!$A$28:$A$32,1),0)+1)) -> 0.1 | AM58: 0.085 | AN58: =IF(N(AM58)>0,AM58,AL58) -> 0.085 | AO58: =IF(N(AN58)=0,"",AN58+IF(I58="yes",AN58*Inputs!$B$10*Inputs!$B$9,0)+IFERROR(INDEX(Inputs!$B$13:$B$15,MATCH(G58,Inputs!$A$13:$A$15,0)),0)+IFERROR(INDEX(Inputs!$B$18:$B$24,MATCH(H58,Inputs!$A$18:$A$24,0)),0)) -> 0.085 | AP58: =IF(OR(N(AO58)<=0,N(AG58)=0,N(L58)=0),"",MIN(L58,AG58/AO58)) -> 24.852941 | AQ58: =IF(OR(AP58="",N(O58)=0),"",AP58/O58-1) -> 2.2658267 | AR58: =IF(OR(AQ58="",N(O58)=0),"",AQ58+AG58/O58) -> 2.543422 | AS58: =IF(OR(AR58="",N(AJ58)=0),"",AR58-AJ58) -> 0.489874 | AT58: 25 | AU58: 2.11 | AV58: =IF(N(AT58)>0,AT58,L58) -> 25 | AW58: =IF(AND(N(M58)>0,N(AV58)>0),M58*AV58,IF(N(AU58)>0,AU58,N58)) -> 2.1125 | AX58: =IF(N(AN58)=0,"",AN58+IF(I58="yes",AN58*Inputs!$B$10*Inputs!$B$9,0)+IFERROR(INDEX(Inputs!$B$13:$B$15,MATCH(G58,Inputs!$A$13:$A$15,0)),0)+IFERROR(INDEX(Inputs!$B$18:$B$24,MATCH(H58,Inputs!$A$18:$A$24,0)),0)) -> 0.085 | AY58: =IF(OR(N(AX58)<=0,N(AW58)=0,N(AV58)=0),"",MIN(AV58,AW58/AX58)) -> 24.852941 | AZ58: =IF(OR(AY58="",N(O58)=0),"",AY58/O58-1) -> 2.2658267 | BA58: =IF(OR(AZ58="",N(O58)=0),"",AZ58+AW58/O58) -> 2.543422 | BB58: =IF(OR(BA58="",N(AR58)=0),"",BA58-AR58) -> 0 | BC58: =IF(OR(BA58="",N(U58)=0),"",BA58-U58) -> 0 | BD58: R hand-typed (deliberate override?)
A59: A-C | B59: 103 | C59: AHT-F | D59: AHT | E59: ASHFORD HOSPITALITY TR INC COM NEW | F59: 21 | G59: PREFERRED | H59: FIXED | I59: no | J59: Q | K59: 4 | L59: 25 | M59: 0.07375 | N59: 1.84375 | O59: 6.44 | P59: CONST | Q59: 0.1 | R59: 0.085 | S59: 21.691176 | T59: 2.3681951 | U59: 2.6544917 | V59: 0 | W59: =IF(N(Q59)=0,"",Q59+IF(I59="yes",Q59*Inputs!$B$10*Inputs!$B$9,0)+V59) -> 0.1 | X59: =IF(OR(N(W59)<=0,N(N59)=0,N(L59)=0),"",MIN(L59,N59/W59)) -> 18.4375 | Y59: =IF(OR(X59="",N(O59)=0),"",X59/O59-1) -> 1.8629658 | Z59: =IF(OR(Y59="",N(O59)=0),"",Y59+N59/O59) -> 2.1492624 | AA59: =IF(OR(Z59="",N(U59)=0),"",Z59-U59) -> -0.50522927 | AB59: =IF(N(Q59)=0,"",Q59+IF(I59="yes",Q59*Inputs!$B$10*Inputs!$B$9,0)+IFERROR(INDEX(Inputs!$B$13:$B$15,MATCH(G59,Inputs!$A$13:$A$15,0)),0)+IFERROR(INDEX(Inputs!$B$18:$B$24,MATCH(H59,Inputs!$A$18:$A$24,0)),0)) -> 0.1 | AC59: =IF(OR(N(AB59)<=0,N(N59)=0,N(L59)=0),"",MIN(L59,N59/AB59)) -> 18.4375 | AD59: =IF(OR(AC59="",N(O59)=0),"",AC59/O59-1) -> 1.8629658 | AE59: =IF(OR(AD59="",N(O59)=0),"",AD59+N59/O59) -> 2.1492624 | AF59: =IF(OR(AE59="",N(Z59)=0),"",AE59-Z59) -> 0 | AG59: =IF(AND(N(M59)>0,N(L59)>0),M59*L59,N59) -> 1.84375 | AH59: =IF(OR(N(AB59)<=0,N(AG59)=0,N(L59)=0),"",MIN(L59,AG59/AB59)) -> 18.4375 | AI59: =IF(OR(AH59="",N(O59)=0),"",AH59/O59-1) -> 1.8629658 | AJ59: =IF(OR(AI59="",N(O59)=0),"",AI59+AG59/O59) -> 2.1492624 | AK59: =IF(OR(AJ59="",N(AE59)=0),"",AJ59-AE59) -> 0 | AL59: =IF(N(F59)=0,"",INDEX(Inputs!$B$28:$B$32,IFERROR(MATCH(F59,Inputs!$A$28:$A$32,1),0)+1)) -> 0.1 | AM59: 0.085 | AN59: =IF(N(AM59)>0,AM59,AL59) -> 0.085 | AO59: =IF(N(AN59)=0,"",AN59+IF(I59="yes",AN59*Inputs!$B$10*Inputs!$B$9,0)+IFERROR(INDEX(Inputs!$B$13:$B$15,MATCH(G59,Inputs!$A$13:$A$15,0)),0)+IFERROR(INDEX(Inputs!$B$18:$B$24,MATCH(H59,Inputs!$A$18:$A$24,0)),0)) -> 0.085 | AP59: =IF(OR(N(AO59)<=0,N(AG59)=0,N(L59)=0),"",MIN(L59,AG59/AO59)) -> 21.691176 | AQ59: =IF(OR(AP59="",N(O59)=0),"",AP59/O59-1) -> 2.3681951 | AR59: =IF(OR(AQ59="",N(O59)=0),"",AQ59+AG59/O59) -> 2.6544917 | AS59: =IF(OR(AR59="",N(AJ59)=0),"",AR59-AJ59) -> 0.50522927 | AT59: 25 | AU59: 1.84 | AV59: =IF(N(AT59)>0,AT59,L59) -> 25 | AW59: =IF(AND(N(M59)>0,N(AV59)>0),M59*AV59,IF(N(AU59)>0,AU59,N59)) -> 1.84375 | AX59: =IF(N(AN59)=0,"",AN59+IF(I59="yes",AN59*Inputs!$B$10*Inputs!$B$9,0)+IFERROR(INDEX(Inputs!$B$13:$B$15,MATCH(G59,Inputs!$A$13:$A$15,0)),0)+IFERROR(INDEX(Inputs!$B$18:$B$24,MATCH(H59,Inputs!$A$18:$A$24,0)),0)) -> 0.085 | AY59: =IF(OR(N(AX59)<=0,N(AW59)=0,N(AV59)=0),"",MIN(AV59,AW59/AX59)) -> 21.691176 | AZ59: =IF(OR(AY59="",N(O59)=0),"",AY59/O59-1) -> 2.3681951 | BA59: =IF(OR(AZ59="",N(O59)=0),"",AZ59+AW59/O59) -> 2.6544917 | BB59: =IF(OR(BA59="",N(AR59)=0),"",BA59-AR59) -> 0 | BC59: =IF(OR(BA59="",N(U59)=0),"",BA59-U59) -> 0 | BD59: R hand-typed (deliberate override?)
A60: A-C | B60: 104 | C60: AHT-G | D60: AHT | E60: ASHFORD HOSPITALITY TR INC COM NEW | F60: 21 | G60: PREFERRED | H60: FIXED | I60: no | J60: Q | K60: 4 | L60: 25 | M60: 0.07375 | N60: 1.84375 | O60: 6.45 | P60: CONST | Q60: 0.1 | R60: 0.085 | S60: 21.691176 | T60: 2.3629731 | U60: 2.6488258 | V60: 0 | W60: =IF(N(Q60)=0,"",Q60+IF(I60="yes",Q60*Inputs!$B$10*Inputs!$B$9,0)+V60) -> 0.1 | X60: =IF(OR(N(W60)<=0,N(N60)=0,N(L60)=0),"",MIN(L60,N60/W60)) -> 18.4375 | Y60: =IF(OR(X60="",N(O60)=0),"",X60/O60-1) -> 1.8585271 | Z60: =IF(OR(Y60="",N(O60)=0),"",Y60+N60/O60) -> 2.1443798 | AA60: =IF(OR(Z60="",N(U60)=0),"",Z60-U60) -> -0.50444596 | AB60: =IF(N(Q60)=0,"",Q60+IF(I60="yes",Q60*Inputs!$B$10*Inputs!$B$9,0)+IFERROR(INDEX(Inputs!$B$13:$B$15,MATCH(G60,Inputs!$A$13:$A$15,0)),0)+IFERROR(INDEX(Inputs!$B$18:$B$24,MATCH(H60,Inputs!$A$18:$A$24,0)),0)) -> 0.1 | AC60: =IF(OR(N(AB60)<=0,N(N60)=0,N(L60)=0),"",MIN(L60,N60/AB60)) -> 18.4375 | AD60: =IF(OR(AC60="",N(O60)=0),"",AC60/O60-1) -> 1.8585271 | AE60: =IF(OR(AD60="",N(O60)=0),"",AD60+N60/O60) -> 2.1443798 | AF60: =IF(OR(AE60="",N(Z60)=0),"",AE60-Z60) -> 0 | AG60: =IF(AND(N(M60)>0,N(L60)>0),M60*L60,N60) -> 1.84375 | AH60: =IF(OR(N(AB60)<=0,N(AG60)=0,N(L60)=0),"",MIN(L60,AG60/AB60)) -> 18.4375 | AI60: =IF(OR(AH60="",N(O60)=0),"",AH60/O60-1) -> 1.8585271 | AJ60: =IF(OR(AI60="",N(O60)=0),"",AI60+AG60/O60) -> 2.1443798 | AK60: =IF(OR(AJ60="",N(AE60)=0),"",AJ60-AE60) -> 0 | AL60: =IF(N(F60)=0,"",INDEX(Inputs!$B$28:$B$32,IFERROR(MATCH(F60,Inputs!$A$28:$A$32,1),0)+1)) -> 0.1 | AM60: 0.085 | AN60: =IF(N(AM60)>0,AM60,AL60) -> 0.085 | AO60: =IF(N(AN60)=0,"",AN60+IF(I60="yes",AN60*Inputs!$B$10*Inputs!$B$9,0)+IFERROR(INDEX(Inputs!$B$13:$B$15,MATCH(G60,Inputs!$A$13:$A$15,0)),0)+IFERROR(INDEX(Inputs!$B$18:$B$24,MATCH(H60,Inputs!$A$18:$A$24,0)),0)) -> 0.085 | AP60: =IF(OR(N(AO60)<=0,N(AG60)=0,N(L60)=0),"",MIN(L60,AG60/AO60)) -> 21.691176 | AQ60: =IF(OR(AP60="",N(O60)=0),"",AP60/O60-1) -> 2.3629731 | AR60: =IF(OR(AQ60="",N(O60)=0),"",AQ60+AG60/O60) -> 2.6488258 | AS60: =IF(OR(AR60="",N(AJ60)=0),"",AR60-AJ60) -> 0.50444596 | AT60: 25 | AU60: 1.84 | AV60: =IF(N(AT60)>0,AT60,L60) -> 25 | AW60: =IF(AND(N(M60)>0,N(AV60)>0),M60*AV60,IF(N(AU60)>0,AU60,N60)) -> 1.84375 | AX60: =IF(N(AN60)=0,"",AN60+IF(I60="yes",AN60*Inputs!$B$10*Inputs!$B$9,0)+IFERROR(INDEX(Inputs!$B$13:$B$15,MATCH(G60,Inputs!$A$13:$A$15,0)),0)+IFERROR(INDEX(Inputs!$B$18:$B$24,MATCH(H60,Inputs!$A$18:$A$24,0)),0)) -> 0.085 | AY60: =IF(OR(N(AX60)<=0,N(AW60)=0,N(AV60)=0),"",MIN(AV60,AW60/AX60)) -> 21.691176 | AZ60: =IF(OR(AY60="",N(O60)=0),"",AY60/O60-1) -> 2.3629731 | BA60: =IF(OR(AZ60="",N(O60)=0),"",AZ60+AW60/O60) -> 2.6488258 | BB60: =IF(OR(BA60="",N(AR60)=0),"",BA60-AR60) -> 0 | BC60: =IF(OR(BA60="",N(U60)=0),"",BA60-U60) -> 0 | BD60: R hand-typed (deliberate override?)
A61: A-C | B61: 105 | C61: AHT-H | D61: AHT | E61: ASHFORD HOSPITALITY TR INC COM NEW | F61: 21 | G61: PREFERRED | H61: FIXED | I61: no | J61: Q | K61: 4 | L61: 25 | M61: 0.075 | N61: 1.875 | O61: 6.4 | P61: CONST | Q61: 0.1 | R61: 0.085 | S61: 22.058824 | T61: 2.4466912 | U61: 2.7396599 | V61: 0 | W61: =IF(N(Q61)=0,"",Q61+IF(I61="yes",Q61*Inputs!$B$10*Inputs!$B$9,0)+V61) -> 0.1 | X61: =IF(OR(N(W61)<=0,N(N61)=0,N(L61)=0),"",MIN(L61,N61/W61)) -> 18.75 | Y61: =IF(OR(X61="",N(O61)=0),"",X61/O61-1) -> 1.9296875 | Z61: =IF(OR(Y61="",N(O61)=0),"",Y61+N61/O61) -> 2.2226562 | AA61: =IF(OR(Z61="",N(U61)=0),"",Z61-U61) -> -0.51700368 | AB61: =IF(N(Q61)=0,"",Q61+IF(I61="yes",Q61*Inputs!$B$10*Inputs!$B$9,0)+IFERROR(INDEX(Inputs!$B$13:$B$15,MATCH(G61,Inputs!$A$13:$A$15,0)),0)+IFERROR(INDEX(Inputs!$B$18:$B$24,MATCH(H61,Inputs!$A$18:$A$24,0)),0)) -> 0.1 | AC61: =IF(OR(N(AB61)<=0,N(N61)=0,N(L61)=0),"",MIN(L61,N61/AB61)) -> 18.75 | AD61: =IF(OR(AC61="",N(O61)=0),"",AC61/O61-1) -> 1.9296875 | AE61: =IF(OR(AD61="",N(O61)=0),"",AD61+N61/O61) -> 2.2226562 | AF61: =IF(OR(AE61="",N(Z61)=0),"",AE61-Z61) -> 0 | AG61: =IF(AND(N(M61)>0,N(L61)>0),M61*L61,N61) -> 1.875 | AH61: =IF(OR(N(AB61)<=0,N(AG61)=0,N(L61)=0),"",MIN(L61,AG61/AB61)) -> 18.75 | AI61: =IF(OR(AH61="",N(O61)=0),"",AH61/O61-1) -> 1.9296875 | AJ61: =IF(OR(AI61="",N(O61)=0),"",AI61+AG61/O61) -> 2.2226562 | AK61: =IF(OR(AJ61="",N(AE61)=0),"",AJ61-AE61) -> 0 | AL61: =IF(N(F61)=0,"",INDEX(Inputs!$B$28:$B$32,IFERROR(MATCH(F61,Inputs!$A$28:$A$32,1),0)+1)) -> 0.1 | AM61: 0.085 | AN61: =IF(N(AM61)>0,AM61,AL61) -> 0.085 | AO61: =IF(N(AN61)=0,"",AN61+IF(I61="yes",AN61*Inputs!$B$10*Inputs!$B$9,0)+IFERROR(INDEX(Inputs!$B$13:$B$15,MATCH(G61,Inputs!$A$13:$A$15,0)),0)+IFERROR(INDEX(Inputs!$B$18:$B$24,MATCH(H61,Inputs!$A$18:$A$24,0)),0)) -> 0.085 | AP61: =IF(OR(N(AO61)<=0,N(AG61)=0,N(L61)=0),"",MIN(L61,AG61/AO61)) -> 22.058824 | AQ61: =IF(OR(AP61="",N(O61)=0),"",AP61/O61-1) -> 2.4466912 | AR61: =IF(OR(AQ61="",N(O61)=0),"",AQ61+AG61/O61) -> 2.7396599 | AS61: =IF(OR(AR61="",N(AJ61)=0),"",AR61-AJ61) -> 0.51700368 | AT61: 25 | AU61: 1.88 | AV61: =IF(N(AT61)>0,AT61,L61) -> 25 | AW61: =IF(AND(N(M61)>0,N(AV61)>0),M61*AV61,IF(N(AU61)>0,AU61,N61)) -> 1.875 | AX61: =IF(N(AN61)=0,"",AN61+IF(I61="yes",AN61*Inputs!$B$10*Inputs!$B$9,0)+IFERROR(INDEX(Inputs!$B$13:$B$15,MATCH(G61,Inputs!$A$13:$A$15,0)),0)+IFERROR(INDEX(Inputs!$B$18:$B$24,MATCH(H61,Inputs!$A$18:$A$24,0)),0)) -> 0.085 | AY61: =IF(OR(N(AX61)<=0,N(AW61)=0,N(AV61)=0),"",MIN(AV61,AW61/AX61)) -> 22.058824 | AZ61: =IF(OR(AY61="",N(O61)=0),"",AY61/O61-1) -> 2.4466912 | BA61: =IF(OR(AZ61="",N(O61)=0),"",AZ61+AW61/O61) -> 2.7396599 | BB61: =IF(OR(BA61="",N(AR61)=0),"",BA61-AR61) -> 0 | BC61: =IF(OR(BA61="",N(U61)=0),"",BA61-U61) -> 0 | BD61: R hand-typed (deliberate override?)
A62: A-C | B62: 106 | C62: AHT-I | D62: AHT | E62: ASHFORD HOSPITALITY TR INC COM NEW | F62: 21 | G62: PREFERRED | H62: FIXED | I62: no | J62: Q | K62: 4 | L62: 25 | M62: 0.075 | N62: 1.875 | O62: 6.7 | P62: CONST | Q62: 0.1 | R62: 0.085 | S62: 22.058824 | T62: 2.2923617 | U62: 2.5722125 | V62: 0 | W62: =IF(N(Q62)=0,"",Q62+IF(I62="yes",Q62*Inputs!$B$10*Inputs!$B$9,0)+V62) -> 0.1 | X62: =IF(OR(N(W62)<=0,N(N62)=0,N(L62)=0),"",MIN(L62,N62/W62)) -> 18.75 | Y62: =IF(OR(X62="",N(O62)=0),"",X62/O62-1) -> 1.7985075 | Z62: =IF(OR(Y62="",N(O62)=0),"",Y62+N62/O62) -> 2.0783582 | AA62: =IF(OR(Z62="",N(U62)=0),"",Z62-U62) -> -0.49385426 | AB62: =IF(N(Q62)=0,"",Q62+IF(I62="yes",Q62*Inputs!$B$10*Inputs!$B$9,0)+IFERROR(INDEX(Inputs!$B$13:$B$15,MATCH(G62,Inputs!$A$13:$A$15,0)),0)+IFERROR(INDEX(Inputs!$B$18:$B$24,MATCH(H62,Inputs!$A$18:$A$24,0)),0)) -> 0.1 | AC62: =IF(OR(N(AB62)<=0,N(N62)=0,N(L62)=0),"",MIN(L62,N62/AB62)) -> 18.75 | AD62: =IF(OR(AC62="",N(O62)=0),"",AC62/O62-1) -> 1.7985075 | AE62: =IF(OR(AD62="",N(O62)=0),"",AD62+N62/O62) -> 2.0783582 | AF62: =IF(OR(AE62="",N(Z62)=0),"",AE62-Z62) -> 0 | AG62: =IF(AND(N(M62)>0,N(L62)>0),M62*L62,N62) -> 1.875 | AH62: =IF(OR(N(AB62)<=0,N(AG62)=0,N(L62)=0),"",MIN(L62,AG62/AB62)) -> 18.75 | AI62: =IF(OR(AH62="",N(O62)=0),"",AH62/O62-1) -> 1.7985075 | AJ62: =IF(OR(AI62="",N(O62)=0),"",AI62+AG62/O62) -> 2.0783582 | AK62: =IF(OR(AJ62="",N(AE62)=0),"",AJ62-AE62) -> 0 | AL62: =IF(N(F62)=0,"",INDEX(Inputs!$B$28:$B$32,IFERROR(MATCH(F62,Inputs!$A$28:$A$32,1),0)+1)) -> 0.1 | AM62: 0.085 | AN62: =IF(N(AM62)>0,AM62,AL62) -> 0.085 | AO62: =IF(N(AN62)=0,"",AN62+IF(I62="yes",AN62*Inputs!$B$10*Inputs!$B$9,0)+IFERROR(INDEX(Inputs!$B$13:$B$15,MATCH(G62,Inputs!$A$13:$A$15,0)),0)+IFERROR(INDEX(Inputs!$B$18:$B$24,MATCH(H62,Inputs!$A$18:$A$24,0)),0)) -> 0.085 | AP62: =IF(OR(N(AO62)<=0,N(AG62)=0,N(L62)=0),"",MIN(L62,AG62/AO62)) -> 22.058824 | AQ62: =IF(OR(AP62="",N(O62)=0),"",AP62/O62-1) -> 2.2923617 | AR62: =IF(OR(AQ62="",N(O62)=0),"",AQ62+AG62/O62) -> 2.5722125 | AS62: =IF(OR(AR62="",N(AJ62)=0),"",AR62-AJ62) -> 0.49385426 | AT62: 25 | AU62: 1.88 | AV62: =IF(N(AT62)>0,AT62,L62) -> 25 | AW62: =IF(AND(N(M62)>0,N(AV62)>0),M62*AV62,IF(N(AU62)>0,AU62,N62)) -> 1.875 | AX62: =IF(N(AN62)=0,"",AN62+IF(I62="yes",AN62*Inputs!$B$10*Inputs!$B$9,0)+IFERROR(INDEX(Inputs!$B$13:$B$15,MATCH(G62,Inputs!$A$13:$A$15,0)),0)+IFERROR(INDEX(Inputs!$B$18:$B$24,MATCH(H62,Inputs!$A$18:$A$24,0)),0)) -> 0.085 | AY62: =IF(OR(N(AX62)<=0,N(AW62)=0,N(AV62)=0),"",MIN(AV62,AW62/AX62)) -> 22.058824 | AZ62: =IF(OR(AY62="",N(O62)=0),"",AY62/O62-1) -> 2.2923617 | BA62: =IF(OR(AZ62="",N(O62)=0),"",AZ62+AW62/O62) -> 2.5722125 | BB62: =IF(OR(BA62="",N(AR62)=0),"",BA62-AR62) -> 0 | BC62: =IF(OR(BA62="",N(U62)=0),"",BA62-U62) -> 0 | BD62: R hand-typed (deliberate override?)
A63: A-C | B63: 109 | C63: AIG-A | D63: AIG | E63: AMERICAN INTL GROUP INC COM NEW | F63: 39600 | G63: PREFERRED | H63: FIXED | I63: yes | J63: Q | K63: 4 | L63: 25 | M63: 0.0585 | N63: 1.4625 | O63: 0 | P63: OK | Q63: 0.08 | R63: 0.076 | S63: 19.243421 | V63: 0 | W63: =IF(N(Q63)=0,"",Q63+IF(I63="yes",Q63*Inputs!$B$10*Inputs!$B$9,0)+V63) -> 0.076 | X63: =IF(OR(N(W63)<=0,N(N63)=0,N(L63)=0),"",MIN(L63,N63/W63)) -> 19.243421 | Y63: =IF(OR(X63="",N(O63)=0),"",X63/O63-1) | Z63: =IF(OR(Y63="",N(O63)=0),"",Y63+N63/O63) | AA63: =IF(OR(Z63="",N(U63)=0),"",Z63-U63) | AB63: =IF(N(Q63)=0,"",Q63+IF(I63="yes",Q63*Inputs!$B$10*Inputs!$B$9,0)+IFERROR(INDEX(Inputs!$B$13:$B$15,MATCH(G63,Inputs!$A$13:$A$15,0)),0)+IFERROR(INDEX(Inputs!$B$18:$B$24,MATCH(H63,Inputs!$A$18:$A$24,0)),0)) -> 0.076 | AC63: =IF(OR(N(AB63)<=0,N(N63)=0,N(L63)=0),"",MIN(L63,N63/AB63)) -> 19.243421 | AD63: =IF(OR(AC63="",N(O63)=0),"",AC63/O63-1) | AE63: =IF(OR(AD63="",N(O63)=0),"",AD63+N63/O63) | AF63: =IF(OR(AE63="",N(Z63)=0),"",AE63-Z63) | AG63: =IF(AND(N(M63)>0,N(L63)>0),M63*L63,N63) -> 1.4625 | AH63: =IF(OR(N(AB63)<=0,N(AG63)=0,N(L63)=0),"",MIN(L63,AG63/AB63)) -> 19.243421 | AI63: =IF(OR(AH63="",N(O63)=0),"",AH63/O63-1) | AJ63: =IF(OR(AI63="",N(O63)=0),"",AI63+AG63/O63) | AK63: =IF(OR(AJ63="",N(AE63)=0),"",AJ63-AE63) | AL63: =IF(N(F63)=0,"",INDEX(Inputs!$B$28:$B$32,IFERROR(MATCH(F63,Inputs!$A$28:$A$32,1),0)+1)) -> 0.075 | AN63: =IF(N(AM63)>0,AM63,AL63) -> 0.075 | AO63: =IF(N(AN63)=0,"",AN63+IF(I63="yes",AN63*Inputs!$B$10*Inputs!$B$9,0)+IFERROR(INDEX(Inputs!$B$13:$B$15,MATCH(G63,Inputs!$A$13:$A$15,0)),0)+IFERROR(INDEX(Inputs!$B$18:$B$24,MATCH(H63,Inputs!$A$18:$A$24,0)),0)) -> 0.07125 | AP63: =IF(OR(N(AO63)<=0,N(AG63)=0,N(L63)=0),"",MIN(L63,AG63/AO63)) -> 20.526316 | AQ63: =IF(OR(AP63="",N(O63)=0),"",AP63/O63-1) | AR63: =IF(OR(AQ63="",N(O63)=0),"",AQ63+AG63/O63) | AS63: =IF(OR(AR63="",N(AJ63)=0),"",AR63-AJ63) | AV63: =IF(N(AT63)>0,AT63,L63) -> 25 | AW63: =IF(AND(N(M63)>0,N(AV63)>0),M63*AV63,IF(N(AU63)>0,AU63,N63)) -> 1.4625 | AX63: =IF(N(AN63)=0,"",AN63+IF(I63="yes",AN63*Inputs!$B$10*Inputs!$B$9,0)+IFERROR(INDEX(Inputs!$B$13:$B$15,MATCH(G63,Inputs!$A$13:$A$15,0)),0)+IFERROR(INDEX(Inputs!$B$18:$B$24,MATCH(H63,Inputs!$A$18:$A$24,0)),0)) -> 0.07125 | AY63: =IF(OR(N(AX63)<=0,N(AW63)=0,N(AV63)=0),"",MIN(AV63,AW63/AX63)) -> 20.526316 | AZ63: =IF(OR(AY63="",N(O63)=0),"",AY63/O63-1) | BA63: =IF(OR(AZ63="",N(O63)=0),"",AZ63+AW63/O63) | BB63: =IF(OR(BA63="",N(AR63)=0),"",BA63-AR63) | BC63: =IF(OR(BA63="",N(U63)=0),"",BA63-U63) | BD63: NO PRICE; not in QOL paste - retire/rename?
A64: A-C | B64: 113 | C64: AIRTP | D64: AIRT | E64: AIR T INC | F64: 78 | G64: TRUPS | H64: FIXED | I64: no | J64: Q | K64: 4 | L64: 2.5 | M64: 0.08 | N64: 0.2 | O64: 18.81 | P64: OK | Q64: 0.08 | R64: 0.08 | S64: 2.5 | T64: -0.86709197 | U64: -0.85645933 | V64: -0.005 | W64: =IF(N(Q64)=0,"",Q64+IF(I64="yes",Q64*Inputs!$B$10*Inputs!$B$9,0)+V64) -> 0.075 | X64: =IF(OR(N(W64)<=0,N(N64)=0,N(L64)=0),"",MIN(L64,N64/W64)) -> 2.5 | Y64: =IF(OR(X64="",N(O64)=0),"",X64/O64-1) -> -0.86709197 | Z64: =IF(OR(Y64="",N(O64)=0),"",Y64+N64/O64) -> -0.85645933 | AA64: =IF(OR(Z64="",N(U64)=0),"",Z64-U64) -> 0 | AB64: =IF(N(Q64)=0,"",Q64+IF(I64="yes",Q64*Inputs!$B$10*Inputs!$B$9,0)+IFERROR(INDEX(Inputs!$B$13:$B$15,MATCH(G64,Inputs!$A$13:$A$15,0)),0)+IFERROR(INDEX(Inputs!$B$18:$B$24,MATCH(H64,Inputs!$A$18:$A$24,0)),0)) -> 0.075 | AC64: =IF(OR(N(AB64)<=0,N(N64)=0,N(L64)=0),"",MIN(L64,N64/AB64)) -> 2.5 | AD64: =IF(OR(AC64="",N(O64)=0),"",AC64/O64-1) -> -0.86709197 | AE64: =IF(OR(AD64="",N(O64)=0),"",AD64+N64/O64) -> -0.85645933 | AF64: =IF(OR(AE64="",N(Z64)=0),"",AE64-Z64) -> 0 | AG64: =IF(AND(N(M64)>0,N(L64)>0),M64*L64,N64) -> 0.2 | AH64: =IF(OR(N(AB64)<=0,N(AG64)=0,N(L64)=0),"",MIN(L64,AG64/AB64)) -> 2.5 | AI64: =IF(OR(AH64="",N(O64)=0),"",AH64/O64-1) -> -0.86709197 | AJ64: =IF(OR(AI64="",N(O64)=0),"",AI64+AG64/O64) -> -0.85645933 | AK64: =IF(OR(AJ64="",N(AE64)=0),"",AJ64-AE64) -> 0 | AL64: =IF(N(F64)=0,"",INDEX(Inputs!$B$28:$B$32,IFERROR(MATCH(F64,Inputs!$A$28:$A$32,1),0)+1)) -> 0.1 | AN64: =IF(N(AM64)>0,AM64,AL64) -> 0.1 | AO64: =IF(N(AN64)=0,"",AN64+IF(I64="yes",AN64*Inputs!$B$10*Inputs!$B$9,0)+IFERROR(INDEX(Inputs!$B$13:$B$15,MATCH(G64,Inputs!$A$13:$A$15,0)),0)+IFERROR(INDEX(Inputs!$B$18:$B$24,MATCH(H64,Inputs!$A$18:$A$24,0)),0)) -> 0.095 | AP64: =IF(OR(N(AO64)<=0,N(AG64)=0,N(L64)=0),"",MIN(L64,AG64/AO64)) -> 2.1052632 | AQ64: =IF(OR(AP64="",N(O64)=0),"",AP64/O64-1) -> -0.88807745 | AR64: =IF(OR(AQ64="",N(O64)=0),"",AQ64+AG64/O64) -> -0.87744481 | AS64: =IF(OR(AR64="",N(AJ64)=0),"",AR64-AJ64) -> -0.020985478 | AT64: 25 | AU64: 2 | AV64: =IF(N(AT64)>0,AT64,L64) -> 25 | AW64: =IF(AND(N(M64)>0,N(AV64)>0),M64*AV64,IF(N(AU64)>0,AU64,N64)) -> 2 | AX64: =IF(N(AN64)=0,"",AN64+IF(I64="yes",AN64*Inputs!$B$10*Inputs!$B$9,0)+IFERROR(INDEX(Inputs!$B$13:$B$15,MATCH(G64,Inputs!$A$13:$A$15,0)),0)+IFERROR(INDEX(Inputs!$B$18:$B$24,MATCH(H64,Inputs!$A$18:$A$24,0)),0)) -> 0.095 | AY64: =IF(OR(N(AX64)<=0,N(AW64)=0,N(AV64)=0),"",MIN(AV64,AW64/AX64)) -> 21.052632 | AZ64: =IF(OR(AY64="",N(O64)=0),"",AY64/O64-1) -> 0.1192255 | BA64: =IF(OR(AZ64="",N(O64)=0),"",AZ64+AW64/O64) -> 0.22555192 | BB64: =IF(OR(BA64="",N(AR64)=0),"",BA64-AR64) -> 1.1029967 | BC64: =IF(OR(BA64="",N(U64)=0),"",BA64-U64) -> 1.0820112 | BD64: PAR MISMATCH
A65: A-C | B65: 117 | C65: AIZN | D65: AIZ | E65: ASSURANT INC | F65: 13900 | G65: BABY_BOND | H65: FIXED | I65: no | J65: Q | K65: 4 | L65: 25 | M65: 0.0525 | N65: 1.3125 | O65: 18.39 | P65: OK | Q65: 0.08 | R65: 0.075 | S65: 17.5 | T65: -0.048395867 | U65: 0.022974443 | V65: -0.005 | W65: =IF(N(Q65)=0,"",Q65+IF(I65="yes",Q65*Inputs!$B$10*Inputs!$B$9,0)+V65) -> 0.075 | X65: =IF(OR(N(W65)<=0,N(N65)=0,N(L65)=0),"",MIN(L65,N65/W65)) -> 17.5 | Y65: =IF(OR(X65="",N(O65)=0),"",X65/O65-1) -> -0.048395867 | Z65: =IF(OR(Y65="",N(O65)=0),"",Y65+N65/O65) -> 0.022974443 | AA65: =IF(OR(Z65="",N(U65)=0),"",Z65-U65) -> 0 | AB65: =IF(N(Q65)=0,"",Q65+IF(I65="yes",Q65*Inputs!$B$10*Inputs!$B$9,0)+IFERROR(INDEX(Inputs!$B$13:$B$15,MATCH(G65,Inputs!$A$13:$A$15,0)),0)+IFERROR(INDEX(Inputs!$B$18:$B$24,MATCH(H65,Inputs!$A$18:$A$24,0)),0)) -> 0.075 | AC65: =IF(OR(N(AB65)<=0,N(N65)=0,N(L65)=0),"",MIN(L65,N65/AB65)) -> 17.5 | AD65: =IF(OR(AC65="",N(O65)=0),"",AC65/O65-1) -> -0.048395867 | AE65: =IF(OR(AD65="",N(O65)=0),"",AD65+N65/O65) -> 0.022974443 | AF65: =IF(OR(AE65="",N(Z65)=0),"",AE65-Z65) -> 0 | AG65: =IF(AND(N(M65)>0,N(L65)>0),M65*L65,N65) -> 1.3125 | AH65: =IF(OR(N(AB65)<=0,N(AG65)=0,N(L65)=0),"",MIN(L65,AG65/AB65)) -> 17.5 | AI65: =IF(OR(AH65="",N(O65)=0),"",AH65/O65-1) -> -0.048395867 | AJ65: =IF(OR(AI65="",N(O65)=0),"",AI65+AG65/O65) -> 0.022974443 | AK65: =IF(OR(AJ65="",N(AE65)=0),"",AJ65-AE65) -> 0 | AL65: =IF(N(F65)=0,"",INDEX(Inputs!$B$28:$B$32,IFERROR(MATCH(F65,Inputs!$A$28:$A$32,1),0)+1)) -> 0.08 | AN65: =IF(N(AM65)>0,AM65,AL65) -> 0.08 | AO65: =IF(N(AN65)=0,"",AN65+IF(I65="yes",AN65*Inputs!$B$10*Inputs!$B$9,0)+IFERROR(INDEX(Inputs!$B$13:$B$15,MATCH(G65,Inputs!$A$13:$A$15,0)),0)+IFERROR(INDEX(Inputs!$B$18:$B$24,MATCH(H65,Inputs!$A$18:$A$24,0)),0)) -> 0.075 | AP65: =IF(OR(N(AO65)<=0,N(AG65)=0,N(L65)=0),"",MIN(L65,AG65/AO65)) -> 17.5 | AQ65: =IF(OR(AP65="",N(O65)=0),"",AP65/O65-1) -> -0.048395867 | AR65: =IF(OR(AQ65="",N(O65)=0),"",AQ65+AG65/O65) -> 0.022974443 | AS65: =IF(OR(AR65="",N(AJ65)=0),"",AR65-AJ65) -> 0 | AT65: 25 | AU65: 1.3125 | AV65: =IF(N(AT65)>0,AT65,L65) -> 25 | AW65: =IF(AND(N(M65)>0,N(AV65)>0),M65*AV65,IF(N(AU65)>0,AU65,N65)) -> 1.3125 | AX65: =IF(N(AN65)=0,"",AN65+IF(I65="yes",AN65*Inputs!$B$10*Inputs!$B$9,0)+IFERROR(INDEX(Inputs!$B$13:$B$15,MATCH(G65,Inputs!$A$13:$A$15,0)),0)+IFERROR(INDEX(Inputs!$B$18:$B$24,MATCH(H65,Inputs!$A$18:$A$24,0)),0)) -> 0.075 | AY65: =IF(OR(N(AX65)<=0,N(AW65)=0,N(AV65)=0),"",MIN(AV65,AW65/AX65)) -> 17.5 | AZ65: =IF(OR(AY65="",N(O65)=0),"",AY65/O65-1) -> -0.048395867 | BA65: =IF(OR(AZ65="",N(O65)=0),"",AZ65+AW65/O65) -> 0.022974443 | BB65: =IF(OR(BA65="",N(AR65)=0),"",BA65-AR65) -> 0 | BC65: =IF(OR(BA65="",N(U65)=0),"",BA65-U65) -> 0
A66: A-C | B66: 121 | C66: AJXA | D66: AJX | E66: na | G66: BABY_BOND | H66: FIXED | I66: no | J66: Q | K66: 4 | L66: 25 | M66: 0.0725 | N66: 1.8125 | O66: 0 | P66: OK | Q66: 0 | R66: -0.0075 | S66: -241.66667 | V66: -0.0075 | W66: =IF(N(Q66)=0,"",Q66+IF(I66="yes",Q66*Inputs!$B$10*Inputs!$B$9,0)+V66) | X66: =IF(OR(N(W66)<=0,N(N66)=0,N(L66)=0),"",MIN(L66,N66/W66)) | Y66: =IF(OR(X66="",N(O66)=0),"",X66/O66-1) | Z66: =IF(OR(Y66="",N(O66)=0),"",Y66+N66/O66) | AA66: =IF(OR(Z66="",N(U66)=0),"",Z66-U66) | AB66: =IF(N(Q66)=0,"",Q66+IF(I66="yes",Q66*Inputs!$B$10*Inputs!$B$9,0)+IFERROR(INDEX(Inputs!$B$13:$B$15,MATCH(G66,Inputs!$A$13:$A$15,0)),0)+IFERROR(INDEX(Inputs!$B$18:$B$24,MATCH(H66,Inputs!$A$18:$A$24,0)),0)) | AC66: =IF(OR(N(AB66)<=0,N(N66)=0,N(L66)=0),"",MIN(L66,N66/AB66)) | AD66: =IF(OR(AC66="",N(O66)=0),"",AC66/O66-1) | AE66: =IF(OR(AD66="",N(O66)=0),"",AD66+N66/O66) | AF66: =IF(OR(AE66="",N(Z66)=0),"",AE66-Z66) | AG66: =IF(AND(N(M66)>0,N(L66)>0),M66*L66,N66) -> 1.8125 | AH66: =IF(OR(N(AB66)<=0,N(AG66)=0,N(L66)=0),"",MIN(L66,AG66/AB66)) | AI66: =IF(OR(AH66="",N(O66)=0),"",AH66/O66-1) | AJ66: =IF(OR(AI66="",N(O66)=0),"",AI66+AG66/O66) | AK66: =IF(OR(AJ66="",N(AE66)=0),"",AJ66-AE66) | AL66: =IF(N(F66)=0,"",INDEX(Inputs!$B$28:$B$32,IFERROR(MATCH(F66,Inputs!$A$28:$A$32,1),0)+1)) | AN66: =IF(N(AM66)>0,AM66,AL66) | AO66: =IF(N(AN66)=0,"",AN66+IF(I66="yes",AN66*Inputs!$B$10*Inputs!$B$9,0)+IFERROR(INDEX(Inputs!$B$13:$B$15,MATCH(G66,Inputs!$A$13:$A$15,0)),0)+IFERROR(INDEX(Inputs!$B$18:$B$24,MATCH(H66,Inputs!$A$18:$A$24,0)),0)) | AP66: =IF(OR(N(AO66)<=0,N(AG66)=0,N(L66)=0),"",MIN(L66,AG66/AO66)) | AQ66: =IF(OR(AP66="",N(O66)=0),"",AP66/O66-1) | AR66: =IF(OR(AQ66="",N(O66)=0),"",AQ66+AG66/O66) | AS66: =IF(OR(AR66="",N(AJ66)=0),"",AR66-AJ66) | AV66: =IF(N(AT66)>0,AT66,L66) -> 25 | AW66: =IF(AND(N(M66)>0,N(AV66)>0),M66*AV66,IF(N(AU66)>0,AU66,N66)) -> 1.8125 | AX66: =IF(N(AN66)=0,"",AN66+IF(I66="yes",AN66*Inputs!$B$10*Inputs!$B$9,0)+IFERROR(INDEX(Inputs!$B$13:$B$15,MATCH(G66,Inputs!$A$13:$A$15,0)),0)+IFERROR(INDEX(Inputs!$B$18:$B$24,MATCH(H66,Inputs!$A$18:$A$24,0)),0)) | AY66: =IF(OR(N(AX66)<=0,N(AW66)=0,N(AV66)=0),"",MIN(AV66,AW66/AX66)) | AZ66: =IF(OR(AY66="",N(O66)=0),"",AY66/O66-1) | BA66: =IF(OR(AZ66="",N(O66)=0),"",AZ66+AW66/O66) | BB66: =IF(OR(BA66="",N(AR66)=0),"",BA66-AR66) | BC66: =IF(OR(BA66="",N(U66)=0),"",BA66-U66) | BD66: NO PRICE; not in QOL paste - retire/rename?; group base = 0 (parent did not quote)
A67: A-C | B67: 125 | C67: AL-A | D67: AL | E67: na | G67: PREFERRED | H67: FIX_TO_FLOAT | I67: yes | J67: Q | K67: 4 | L67: 25 | M67: 0.0615 | N67: 1.5375 | O67: 0 | P67: OK | Q67: 0 | R67: 0 | V67: 0 | W67: =IF(N(Q67)=0,"",Q67+IF(I67="yes",Q67*Inputs!$B$10*Inputs!$B$9,0)+V67) | X67: =IF(OR(N(W67)<=0,N(N67)=0,N(L67)=0),"",MIN(L67,N67/W67)) | Y67: =IF(OR(X67="",N(O67)=0),"",X67/O67-1) | Z67: =IF(OR(Y67="",N(O67)=0),"",Y67+N67/O67) | AA67: =IF(OR(Z67="",N(U67)=0),"",Z67-U67) | AB67: =IF(N(Q67)=0,"",Q67+IF(I67="yes",Q67*Inputs!$B$10*Inputs!$B$9,0)+IFERROR(INDEX(Inputs!$B$13:$B$15,MATCH(G67,Inputs!$A$13:$A$15,0)),0)+IFERROR(INDEX(Inputs!$B$18:$B$24,MATCH(H67,Inputs!$A$18:$A$24,0)),0)) | AC67: =IF(OR(N(AB67)<=0,N(N67)=0,N(L67)=0),"",MIN(L67,N67/AB67)) | AD67: =IF(OR(AC67="",N(O67)=0),"",AC67/O67-1) | AE67: =IF(OR(AD67="",N(O67)=0),"",AD67+N67/O67) | AF67: =IF(OR(AE67="",N(Z67)=0),"",AE67-Z67) | AG67: =IF(AND(N(M67)>0,N(L67)>0),M67*L67,N67) -> 1.5375 | AH67: =IF(OR(N(AB67)<=0,N(AG67)=0,N(L67)=0),"",MIN(L67,AG67/AB67)) | AI67: =IF(OR(AH67="",N(O67)=0),"",AH67/O67-1) | AJ67: =IF(OR(AI67="",N(O67)=0),"",AI67+AG67/O67) | AK67: =IF(OR(AJ67="",N(AE67)=0),"",AJ67-AE67) | AL67: =IF(N(F67)=0,"",INDEX(Inputs!$B$28:$B$32,IFERROR(MATCH(F67,Inputs!$A$28:$A$32,1),0)+1)) | AN67: =IF(N(AM67)>0,AM67,AL67) | AO67: =IF(N(AN67)=0,"",AN67+IF(I67="yes",AN67*Inputs!$B$10*Inputs!$B$9,0)+IFERROR(INDEX(Inputs!$B$13:$B$15,MATCH(G67,Inputs!$A$13:$A$15,0)),0)+IFERROR(INDEX(Inputs!$B$18:$B$24,MATCH(H67,Inputs!$A$18:$A$24,0)),0)) | AP67: =IF(OR(N(AO67)<=0,N(AG67)=0,N(L67)=0),"",MIN(L67,AG67/AO67)) | AQ67: =IF(OR(AP67="",N(O67)=0),"",AP67/O67-1) | AR67: =IF(OR(AQ67="",N(O67)=0),"",AQ67+AG67/O67) | AS67: =IF(OR(AR67="",N(AJ67)=0),"",AR67-AJ67) | AV67: =IF(N(AT67)>0,AT67,L67) -> 25 | AW67: =IF(AND(N(M67)>0,N(AV67)>0),M67*AV67,IF(N(AU67)>0,AU67,N67)) -> 1.5375 | AX67: =IF(N(AN67)=0,"",AN67+IF(I67="yes",AN67*Inputs!$B$10*Inputs!$B$9,0)+IFERROR(INDEX(Inputs!$B$13:$B$15,MATCH(G67,Inputs!$A$13:$A$15,0)),0)+IFERROR(INDEX(Inputs!$B$18:$B$24,MATCH(H67,Inputs!$A$18:$A$24,0)),0)) | AY67: =IF(OR(N(AX67)<=0,N(AW67)=0,N(AV67)=0),"",MIN(AV67,AW67/AX67)) | AZ67: =IF(OR(AY67="",N(O67)=0),"",AY67/O67-1) | BA67: =IF(OR(AZ67="",N(O67)=0),"",AZ67+AW67/O67) | BB67: =IF(OR(BA67="",N(AR67)=0),"",BA67-AR67) | BC67: =IF(OR(BA67="",N(U67)=0),"",BA67-U67) | BD67: NO PRICE; not in QOL paste - retire/rename?; group base = 0 (parent did not quote)
A68: A-C | B68: 129 | C68: ALL-B | D68: ALL | E68: ALLSTATE CORP | F68: 64400 | G68: BABY_BOND | H68: FIXED | I68: no | J68: Q | K68: 4 | L68: 25 | M68: 0.051 | N68: 1.275 | O68: 25.57 | P68: OK | Q68: 0.08 | R68: 0.0725 | S68: 17.586207 | T68: -0.31223282 | U68: -0.2623697 | V68: -0.0075 | W68: =IF(N(Q68)=0,"",Q68+IF(I68="yes",Q68*Inputs!$B$10*Inputs!$B$9,0)+V68) -> 0.0725 | X68: =IF(OR(N(W68)<=0,N(N68)=0,N(L68)=0),"",MIN(L68,N68/W68)) -> 17.586207 | Y68: =IF(OR(X68="",N(O68)=0),"",X68/O68-1) -> -0.31223282 | Z68: =IF(OR(Y68="",N(O68)=0),"",Y68+N68/O68) -> -0.2623697 | AA68: =IF(OR(Z68="",N(U68)=0),"",Z68-U68) -> 0 | AB68: =IF(N(Q68)=0,"",Q68+IF(I68="yes",Q68*Inputs!$B$10*Inputs!$B$9,0)+IFERROR(INDEX(Inputs!$B$13:$B$15,MATCH(G68,Inputs!$A$13:$A$15,0)),0)+IFERROR(INDEX(Inputs!$B$18:$B$24,MATCH(H68,Inputs!$A$18:$A$24,0)),0)) -> 0.075 | AC68: =IF(OR(N(AB68)<=0,N(N68)=0,N(L68)=0),"",MIN(L68,N68/AB68)) -> 17 | AD68: =IF(OR(AC68="",N(O68)=0),"",AC68/O68-1) -> -0.33515839 | AE68: =IF(OR(AD68="",N(O68)=0),"",AD68+N68/O68) -> -0.28529527 | AF68: =IF(OR(AE68="",N(Z68)=0),"",AE68-Z68) -> -0.022925573 | AG68: =IF(AND(N(M68)>0,N(L68)>0),M68*L68,N68) -> 1.275 | AH68: =IF(OR(N(AB68)<=0,N(AG68)=0,N(L68)=0),"",MIN(L68,AG68/AB68)) -> 17 | AI68: =IF(OR(AH68="",N(O68)=0),"",AH68/O68-1) -> -0.33515839 | AJ68: =IF(OR(AI68="",N(O68)=0),"",AI68+AG68/O68) -> -0.28529527 | AK68: =IF(OR(AJ68="",N(AE68)=0),"",AJ68-AE68) -> 0 | AL68: =IF(N(F68)=0,"",INDEX(Inputs!$B$28:$B$32,IFERROR(MATCH(F68,Inputs!$A$28:$A$32,1),0)+1)) -> 0.075 | AN68: =IF(N(AM68)>0,AM68,AL68) -> 0.075 | AO68: =IF(N(AN68)=0,"",AN68+IF(I68="yes",AN68*Inputs!$B$10*Inputs!$B$9,0)+IFERROR(INDEX(Inputs!$B$13:$B$15,MATCH(G68,Inputs!$A$13:$A$15,0)),0)+IFERROR(INDEX(Inputs!$B$18:$B$24,MATCH(H68,Inputs!$A$18:$A$24,0)),0)) -> 0.07 | AP68: =IF(OR(N(AO68)<=0,N(AG68)=0,N(L68)=0),"",MIN(L68,AG68/AO68)) -> 18.214286 | AQ68: =IF(OR(AP68="",N(O68)=0),"",AP68/O68-1) -> -0.2876697 | AR68: =IF(OR(AQ68="",N(O68)=0),"",AQ68+AG68/O68) -> -0.23780658 | AS68: =IF(OR(AR68="",N(AJ68)=0),"",AR68-AJ68) -> 0.047488687 | AT68: 25 | AV68: =IF(N(AT68)>0,AT68,L68) -> 25 | AW68: =IF(AND(N(M68)>0,N(AV68)>0),M68*AV68,IF(N(AU68)>0,AU68,N68)) -> 1.275 | AX68: =IF(N(AN68)=0,"",AN68+IF(I68="yes",AN68*Inputs!$B$10*Inputs!$B$9,0)+IFERROR(INDEX(Inputs!$B$13:$B$15,MATCH(G68,Inputs!$A$13:$A$15,0)),0)+IFERROR(INDEX(Inputs!$B$18:$B$24,MATCH(H68,Inputs!$A$18:$A$24,0)),0)) -> 0.07 | AY68: =IF(OR(N(AX68)<=0,N(AW68)=0,N(AV68)=0),"",MIN(AV68,AW68/AX68)) -> 18.214286 | AZ68: =IF(OR(AY68="",N(O68)=0),"",AY68/O68-1) -> -0.2876697 | BA68: =IF(OR(AZ68="",N(O68)=0),"",AZ68+AW68/O68) -> -0.23780658 | BB68: =IF(OR(BA68="",N(AR68)=0),"",BA68-AR68) -> 0 | BC68: =IF(OR(BA68="",N(U68)=0),"",BA68-U68) -> 0.024563114
A69: A-C | B69: 130 | C69: ALL-H | D69: ALL | E69: ALLSTATE CORP | F69: 64400 | G69: PREFERRED | H69: FIXED | I69: yes | J69: Q | K69: 4 | L69: 25 | M69: 0.0512 | N69: 1.28 | O69: 18.75 | P69: OK | Q69: 0.08 | R69: 0.076 | S69: 16.842105 | T69: -0.10175439 | U69: -0.033487719 | V69: 0 | W69: =IF(N(Q69)=0,"",Q69+IF(I69="yes",Q69*Inputs!$B$10*Inputs!$B$9,0)+V69) -> 0.076 | X69: =IF(OR(N(W69)<=0,N(N69)=0,N(L69)=0),"",MIN(L69,N69/W69)) -> 16.842105 | Y69: =IF(OR(X69="",N(O69)=0),"",X69/O69-1) -> -0.10175439 | Z69: =IF(OR(Y69="",N(O69)=0),"",Y69+N69/O69) -> -0.033487719 | AA69: =IF(OR(Z69="",N(U69)=0),"",Z69-U69) -> 0 | AB69: =IF(N(Q69)=0,"",Q69+IF(I69="yes",Q69*Inputs!$B$10*Inputs!$B$9,0)+IFERROR(INDEX(Inputs!$B$13:$B$15,MATCH(G69,Inputs!$A$13:$A$15,0)),0)+IFERROR(INDEX(Inputs!$B$18:$B$24,MATCH(H69,Inputs!$A$18:$A$24,0)),0)) -> 0.076 | AC69: =IF(OR(N(AB69)<=0,N(N69)=0,N(L69)=0),"",MIN(L69,N69/AB69)) -> 16.842105 | AD69: =IF(OR(AC69="",N(O69)=0),"",AC69/O69-1) -> -0.10175439 | AE69: =IF(OR(AD69="",N(O69)=0),"",AD69+N69/O69) -> -0.033487719 | AF69: =IF(OR(AE69="",N(Z69)=0),"",AE69-Z69) -> 0 | AG69: =IF(AND(N(M69)>0,N(L69)>0),M69*L69,N69) -> 1.28 | AH69: =IF(OR(N(AB69)<=0,N(AG69)=0,N(L69)=0),"",MIN(L69,AG69/AB69)) -> 16.842105 | AI69: =IF(OR(AH69="",N(O69)=0),"",AH69/O69-1) -> -0.10175439 | AJ69: =IF(OR(AI69="",N(O69)=0),"",AI69+AG69/O69) -> -0.033487719 | AK69: =IF(OR(AJ69="",N(AE69)=0),"",AJ69-AE69) -> 0 | AL69: =IF(N(F69)=0,"",INDEX(Inputs!$B$28:$B$32,IFERROR(MATCH(F69,Inputs!$A$28:$A$32,1),0)+1)) -> 0.075 | AN69: =IF(N(AM69)>0,AM69,AL69) -> 0.075 | AO69: =IF(N(AN69)=0,"",AN69+IF(I69="yes",AN69*Inputs!$B$10*Inputs!$B$9,0)+IFERROR(INDEX(Inputs!$B$13:$B$15,MATCH(G69,Inputs!$A$13:$A$15,0)),0)+IFERROR(INDEX(Inputs!$B$18:$B$24,MATCH(H69,Inputs!$A$18:$A$24,0)),0)) -> 0.07125 | AP69: =IF(OR(N(AO69)<=0,N(AG69)=0,N(L69)=0),"",MIN(L69,AG69/AO69)) -> 17.964912 | AQ69: =IF(OR(AP69="",N(O69)=0),"",AP69/O69-1) -> -0.041871345 | AR69: =IF(OR(AQ69="",N(O69)=0),"",AQ69+AG69/O69) -> 0.026395322 | AS69: =IF(OR(AR69="",N(AJ69)=0),"",AR69-AJ69) -> 0.059883041 | AT69: 25 | AU69: 1.28 | AV69: =IF(N(AT69)>0,AT69,L69) -> 25 | AW69: =IF(AND(N(M69)>0,N(AV69)>0),M69*AV69,IF(N(AU69)>0,AU69,N69)) -> 1.28 | AX69: =IF(N(AN69)=0,"",AN69+IF(I69="yes",AN69*Inputs!$B$10*Inputs!$B$9,0)+IFERROR(INDEX(Inputs!$B$13:$B$15,MATCH(G69,Inputs!$A$13:$A$15,0)),0)+IFERROR(INDEX(Inputs!$B$18:$B$24,MATCH(H69,Inputs!$A$18:$A$24,0)),0)) -> 0.07125 | AY69: =IF(OR(N(AX69)<=0,N(AW69)=0,N(AV69)=0),"",MIN(AV69,AW69/AX69)) -> 17.964912 | AZ69: =IF(OR(AY69="",N(O69)=0),"",AY69/O69-1) -> -0.041871345 | BA69: =IF(OR(AZ69="",N(O69)=0),"",AZ69+AW69/O69) -> 0.026395322 | BB69: =IF(OR(BA69="",N(AR69)=0),"",BA69-AR69) -> 0 | BC69: =IF(OR(BA69="",N(U69)=0),"",BA69-U69) -> 0.059883041
A70: A-C | B70: 131 | C70: ALL-I | D70: ALL | E70: ALLSTATE CORP | F70: 64400 | G70: PREFERRED | H70: FIXED | I70: yes | J70: Q | K70: 4 | L70: 25 | M70: 0.0475 | N70: 1.1875 | O70: 17.59 | P70: OK | Q70: 0.08 | R70: 0.076 | S70: 15.625 | T70: -0.1117112 | U70: -0.044201251 | V70: 0 | W70: =IF(N(Q70)=0,"",Q70+IF(I70="yes",Q70*Inputs!$B$10*Inputs!$B$9,0)+V70) -> 0.076 | X70: =IF(OR(N(W70)<=0,N(N70)=0,N(L70)=0),"",MIN(L70,N70/W70)) -> 15.625 | Y70: =IF(OR(X70="",N(O70)=0),"",X70/O70-1) -> -0.1117112 | Z70: =IF(OR(Y70="",N(O70)=0),"",Y70+N70/O70) -> -0.044201251 | AA70: =IF(OR(Z70="",N(U70)=0),"",Z70-U70) -> 0 | AB70: =IF(N(Q70)=0,"",Q70+IF(I70="yes",Q70*Inputs!$B$10*Inputs!$B$9,0)+IFERROR(INDEX(Inputs!$B$13:$B$15,MATCH(G70,Inputs!$A$13:$A$15,0)),0)+IFERROR(INDEX(Inputs!$B$18:$B$24,MATCH(H70,Inputs!$A$18:$A$24,0)),0)) -> 0.076 | AC70: =IF(OR(N(AB70)<=0,N(N70)=0,N(L70)=0),"",MIN(L70,N70/AB70)) -> 15.625 | AD70: =IF(OR(AC70="",N(O70)=0),"",AC70/O70-1) -> -0.1117112 | AE70: =IF(OR(AD70="",N(O70)=0),"",AD70+N70/O70) -> -0.044201251 | AF70: =IF(OR(AE70="",N(Z70)=0),"",AE70-Z70) -> 0 | AG70: =IF(AND(N(M70)>0,N(L70)>0),M70*L70,N70) -> 1.1875 | AH70: =IF(OR(N(AB70)<=0,N(AG70)=0,N(L70)=0),"",MIN(L70,AG70/AB70)) -> 15.625 | AI70: =IF(OR(AH70="",N(O70)=0),"",AH70/O70-1) -> -0.1117112 | AJ70: =IF(OR(AI70="",N(O70)=0),"",AI70+AG70/O70) -> -0.044201251 | AK70: =IF(OR(AJ70="",N(AE70)=0),"",AJ70-AE70) -> 0 | AL70: =IF(N(F70)=0,"",INDEX(Inputs!$B$28:$B$32,IFERROR(MATCH(F70,Inputs!$A$28:$A$32,1),0)+1)) -> 0.075 | AN70: =IF(N(AM70)>0,AM70,AL70) -> 0.075 | AO70: =IF(N(AN70)=0,"",AN70+IF(I70="yes",AN70*Inputs!$B$10*Inputs!$B$9,0)+IFERROR(INDEX(Inputs!$B$13:$B$15,MATCH(G70,Inputs!$A$13:$A$15,0)),0)+IFERROR(INDEX(Inputs!$B$18:$B$24,MATCH(H70,Inputs!$A$18:$A$24,0)),0)) -> 0.07125 | AP70: =IF(OR(N(AO70)<=0,N(AG70)=0,N(L70)=0),"",MIN(L70,AG70/AO70)) -> 16.666667 | AQ70: =IF(OR(AP70="",N(O70)=0),"",AP70/O70-1) -> -0.052491946 | AR70: =IF(OR(AQ70="",N(O70)=0),"",AQ70+AG70/O70) -> 0.015018003 | AS70: =IF(OR(AR70="",N(AJ70)=0),"",AR70-AJ70) -> 0.059219253 | AT70: 25 | AU70: 1.19 | AV70: =IF(N(AT70)>0,AT70,L70) -> 25 | AW70: =IF(AND(N(M70)>0,N(AV70)>0),M70*AV70,IF(N(AU70)>0,AU70,N70)) -> 1.1875 | AX70: =IF(N(AN70)=0,"",AN70+IF(I70="yes",AN70*Inputs!$B$10*Inputs!$B$9,0)+IFERROR(INDEX(Inputs!$B$13:$B$15,MATCH(G70,Inputs!$A$13:$A$15,0)),0)+IFERROR(INDEX(Inputs!$B$18:$B$24,MATCH(H70,Inputs!$A$18:$A$24,0)),0)) -> 0.07125 | AY70: =IF(OR(N(AX70)<=0,N(AW70)=0,N(AV70)=0),"",MIN(AV70,AW70/AX70)) -> 16.666667 | AZ70: =IF(OR(AY70="",N(O70)=0),"",AY70/O70-1) -> -0.052491946 | BA70: =IF(OR(AZ70="",N(O70)=0),"",AZ70+AW70/O70) -> 0.015018003 | BB70: =IF(OR(BA70="",N(AR70)=0),"",BA70-AR70) -> 0 | BC70: =IF(OR(BA70="",N(U70)=0),"",BA70-U70) -> 0.059219253
A71: A-C | B71: 132 | C71: ALL-J | D71: ALL | E71: ALLSTATE CORP | F71: 64400 | G71: PREFERRED | H71: FIXED | I71: yes | J71: Q | K71: 4 | L71: 25 | M71: 0.07375 | N71: 1.84375 | O71: 25.81 | P71: MISWIRED_CD | Q71: 0.08 | R71: 0.08 | S71: 23.046875 | T71: -0.10705637 | U71: -0.035620883 | V71: 0 | W71: =IF(N(Q71)=0,"",Q71+IF(I71="yes",Q71*Inputs!$B$10*Inputs!$B$9,0)+V71) -> 0.076 | X71: =IF(OR(N(W71)<=0,N(N71)=0,N(L71)=0),"",MIN(L71,N71/W71)) -> 24.259868 | Y71: =IF(OR(X71="",N(O71)=0),"",X71/O71-1) -> -0.060059341 | Z71: =IF(OR(Y71="",N(O71)=0),"",Y71+N71/O71) -> 0.01137615 | AA71: =IF(OR(Z71="",N(U71)=0),"",Z71-U71) -> 0.046997033 | AB71: =IF(N(Q71)=0,"",Q71+IF(I71="yes",Q71*Inputs!$B$10*Inputs!$B$9,0)+IFERROR(INDEX(Inputs!$B$13:$B$15,MATCH(G71,Inputs!$A$13:$A$15,0)),0)+IFERROR(INDEX(Inputs!$B$18:$B$24,MATCH(H71,Inputs!$A$18:$A$24,0)),0)) -> 0.076 | AC71: =IF(OR(N(AB71)<=0,N(N71)=0,N(L71)=0),"",MIN(L71,N71/AB71)) -> 24.259868 | AD71: =IF(OR(AC71="",N(O71)=0),"",AC71/O71-1) -> -0.060059341 | AE71: =IF(OR(AD71="",N(O71)=0),"",AD71+N71/O71) -> 0.01137615 | AF71: =IF(OR(AE71="",N(Z71)=0),"",AE71-Z71) -> 0 | AG71: =IF(AND(N(M71)>0,N(L71)>0),M71*L71,N71) -> 1.84375 | AH71: =IF(OR(N(AB71)<=0,N(AG71)=0,N(L71)=0),"",MIN(L71,AG71/AB71)) -> 24.259868 | AI71: =IF(OR(AH71="",N(O71)=0),"",AH71/O71-1) -> -0.060059341 | AJ71: =IF(OR(AI71="",N(O71)=0),"",AI71+AG71/O71) -> 0.01137615 | AK71: =IF(OR(AJ71="",N(AE71)=0),"",AJ71-AE71) -> 0 | AL71: =IF(N(F71)=0,"",INDEX(Inputs!$B$28:$B$32,IFERROR(MATCH(F71,Inputs!$A$28:$A$32,1),0)+1)) -> 0.075 | AN71: =IF(N(AM71)>0,AM71,AL71) -> 0.075 | AO71: =IF(N(AN71)=0,"",AN71+IF(I71="yes",AN71*Inputs!$B$10*Inputs!$B$9,0)+IFERROR(INDEX(Inputs!$B$13:$B$15,MATCH(G71,Inputs!$A$13:$A$15,0)),0)+IFERROR(INDEX(Inputs!$B$18:$B$24,MATCH(H71,Inputs!$A$18:$A$24,0)),0)) -> 0.07125 | AP71: =IF(OR(N(AO71)<=0,N(AG71)=0,N(L71)=0),"",MIN(L71,AG71/AO71)) -> 25 | AQ71: =IF(OR(AP71="",N(O71)=0),"",AP71/O71-1) -> -0.031383185 | AR71: =IF(OR(AQ71="",N(O71)=0),"",AQ71+AG71/O71) -> 0.040052305 | AS71: =IF(OR(AR71="",N(AJ71)=0),"",AR71-AJ71) -> 0.028676156 | AT71: 25 | AU71: 1.84375 | AV71: =IF(N(AT71)>0,AT71,L71) -> 25 | AW71: =IF(AND(N(M71)>0,N(AV71)>0),M71*AV71,IF(N(AU71)>0,AU71,N71)) -> 1.84375 | AX71: =IF(N(AN71)=0,"",AN71+IF(I71="yes",AN71*Inputs!$B$10*Inputs!$B$9,0)+IFERROR(INDEX(Inputs!$B$13:$B$15,MATCH(G71,Inputs!$A$13:$A$15,0)),0)+IFERROR(INDEX(Inputs!$B$18:$B$24,MATCH(H71,Inputs!$A$18:$A$24,0)),0)) -> 0.07125 | AY71: =IF(OR(N(AX71)<=0,N(AW71)=0,N(AV71)=0),"",MIN(AV71,AW71/AX71)) -> 25 | AZ71: =IF(OR(AY71="",N(O71)=0),"",AY71/O71-1) -> -0.031383185 | BA71: =IF(OR(AZ71="",N(O71)=0),"",AZ71+AW71/O71) -> 0.040052305 | BB71: =IF(OR(BA71="",N(AR71)=0),"",BA71-AR71) -> 0 | BC71: =IF(OR(BA71="",N(U71)=0),"",BA71-U71) -> 0.075673189 | BD71: wiring: reads C/D not D/E - no adjustments fired
A72: A-C | B72: 135 | C72: ALTG-A | D72: ALTG | E72: ALTA EQUIPMENT GROUP INC COMMON STOCK | F72: 209 | G72: PREFERRED | H72: FIXED | I72: yes | J72: Q | K72: 4 | L72: 25 | M72: 0.1 | N72: 2.5 | O72: 26.14 | P72: OK | Q72: 0.1 | R72: 0.095 | S72: 25 | T72: -0.043611324 | U72: 0.052027544 | V72: 0 | W72: =IF(N(Q72)=0,"",Q72+IF(I72="yes",Q72*Inputs!$B$10*Inputs!$B$9,0)+V72) -> 0.095 | X72: =IF(OR(N(W72)<=0,N(N72)=0,N(L72)=0),"",MIN(L72,N72/W72)) -> 25 | Y72: =IF(OR(X72="",N(O72)=0),"",X72/O72-1) -> -0.043611324 | Z72: =IF(OR(Y72="",N(O72)=0),"",Y72+N72/O72) -> 0.052027544 | AA72: =IF(OR(Z72="",N(U72)=0),"",Z72-U72) -> 0 | AB72: =IF(N(Q72)=0,"",Q72+IF(I72="yes",Q72*Inputs!$B$10*Inputs!$B$9,0)+IFERROR(INDEX(Inputs!$B$13:$B$15,MATCH(G72,Inputs!$A$13:$A$15,0)),0)+IFERROR(INDEX(Inputs!$B$18:$B$24,MATCH(H72,Inputs!$A$18:$A$24,0)),0)) -> 0.095 | AC72: =IF(OR(N(AB72)<=0,N(N72)=0,N(L72)=0),"",MIN(L72,N72/AB72)) -> 25 | AD72: =IF(OR(AC72="",N(O72)=0),"",AC72/O72-1) -> -0.043611324 | AE72: =IF(OR(AD72="",N(O72)=0),"",AD72+N72/O72) -> 0.052027544 | AF72: =IF(OR(AE72="",N(Z72)=0),"",AE72-Z72) -> 0 | AG72: =IF(AND(N(M72)>0,N(L72)>0),M72*L72,N72) -> 2.5 | AH72: =IF(OR(N(AB72)<=0,N(AG72)=0,N(L72)=0),"",MIN(L72,AG72/AB72)) -> 25 | AI72: =IF(OR(AH72="",N(O72)=0),"",AH72/O72-1) -> -0.043611324 | AJ72: =IF(OR(AI72="",N(O72)=0),"",AI72+AG72/O72) -> 0.052027544 | AK72: =IF(OR(AJ72="",N(AE72)=0),"",AJ72-AE72) -> 0 | AL72: =IF(N(F72)=0,"",INDEX(Inputs!$B$28:$B$32,IFERROR(MATCH(F72,Inputs!$A$28:$A$32,1),0)+1)) -> 0.1 | AN72: =IF(N(AM72)>0,AM72,AL72) -> 0.1 | AO72: =IF(N(AN72)=0,"",AN72+IF(I72="yes",AN72*Inputs!$B$10*Inputs!$B$9,0)+IFERROR(INDEX(Inputs!$B$13:$B$15,MATCH(G72,Inputs!$A$13:$A$15,0)),0)+IFERROR(INDEX(Inputs!$B$18:$B$24,MATCH(H72,Inputs!$A$18:$A$24,0)),0)) -> 0.095 | AP72: =IF(OR(N(AO72)<=0,N(AG72)=0,N(L72)=0),"",MIN(L72,AG72/AO72)) -> 25 | AQ72: =IF(OR(AP72="",N(O72)=0),"",AP72/O72-1) -> -0.043611324 | AR72: =IF(OR(AQ72="",N(O72)=0),"",AQ72+AG72/O72) -> 0.052027544 | AS72: =IF(OR(AR72="",N(AJ72)=0),"",AR72-AJ72) -> 0 | AT72: 25 | AU72: 2.5 | AV72: =IF(N(AT72)>0,AT72,L72) -> 25 | AW72: =IF(AND(N(M72)>0,N(AV72)>0),M72*AV72,IF(N(AU72)>0,AU72,N72)) -> 2.5 | AX72: =IF(N(AN72)=0,"",AN72+IF(I72="yes",AN72*Inputs!$B$10*Inputs!$B$9,0)+IFERROR(INDEX(Inputs!$B$13:$B$15,MATCH(G72,Inputs!$A$13:$A$15,0)),0)+IFERROR(INDEX(Inputs!$B$18:$B$24,MATCH(H72,Inputs!$A$18:$A$24,0)),0)) -> 0.095 | AY72: =IF(OR(N(AX72)<=0,N(AW72)=0,N(AV72)=0),"",MIN(AV72,AW72/AX72)) -> 25 | AZ72: =IF(OR(AY72="",N(O72)=0),"",AY72/O72-1) -> -0.043611324 | BA72: =IF(OR(AZ72="",N(O72)=0),"",AZ72+AW72/O72) -> 0.052027544 | BB72: =IF(OR(BA72="",N(AR72)=0),"",BA72-AR72) -> 0 | BC72: =IF(OR(BA72="",N(U72)=0),"",BA72-U72) -> 0
A73: A-C | B73: 139 | C73: MGR | D73: AMG | E73: AFFILIATED MANAGERS GROUP | F73: 9100 | G73: BABY_BOND | H73: FIXED | I73: no | J73: Q | K73: 4 | L73: 25 | M73: 0.05875 | N73: 1.46875 | O73: 19.72 | P73: OK | Q73: 0.08 | R73: 0.075 | S73: 19.583333 | T73: -0.0069303584 | U73: 0.067549865 | V73: -0.005 | W73: =IF(N(Q73)=0,"",Q73+IF(I73="yes",Q73*Inputs!$B$10*Inputs!$B$9,0)+V73) -> 0.075 | X73: =IF(OR(N(W73)<=0,N(N73)=0,N(L73)=0),"",MIN(L73,N73/W73)) -> 19.583333 | Y73: =IF(OR(X73="",N(O73)=0),"",X73/O73-1) -> -0.0069303584 | Z73: =IF(OR(Y73="",N(O73)=0),"",Y73+N73/O73) -> 0.067549865 | AA73: =IF(OR(Z73="",N(U73)=0),"",Z73-U73) -> 0 | AB73: =IF(N(Q73)=0,"",Q73+IF(I73="yes",Q73*Inputs!$B$10*Inputs!$B$9,0)+IFERROR(INDEX(Inputs!$B$13:$B$15,MATCH(G73,Inputs!$A$13:$A$15,0)),0)+IFERROR(INDEX(Inputs!$B$18:$B$24,MATCH(H73,Inputs!$A$18:$A$24,0)),0)) -> 0.075 | AC73: =IF(OR(N(AB73)<=0,N(N73)=0,N(L73)=0),"",MIN(L73,N73/AB73)) -> 19.583333 | AD73: =IF(OR(AC73="",N(O73)=0),"",AC73/O73-1) -> -0.0069303584 | AE73: =IF(OR(AD73="",N(O73)=0),"",AD73+N73/O73) -> 0.067549865 | AF73: =IF(OR(AE73="",N(Z73)=0),"",AE73-Z73) -> 0 | AG73: =IF(AND(N(M73)>0,N(L73)>0),M73*L73,N73) -> 1.46875 | AH73: =IF(OR(N(AB73)<=0,N(AG73)=0,N(L73)=0),"",MIN(L73,AG73/AB73)) -> 19.583333 | AI73: =IF(OR(AH73="",N(O73)=0),"",AH73/O73-1) -> -0.0069303584 | AJ73: =IF(OR(AI73="",N(O73)=0),"",AI73+AG73/O73) -> 0.067549865 | AK73: =IF(OR(AJ73="",N(AE73)=0),"",AJ73-AE73) -> 0 | AL73: =IF(N(F73)=0,"",INDEX(Inputs!$B$28:$B$32,IFERROR(MATCH(F73,Inputs!$A$28:$A$32,1),0)+1)) -> 0.08 | AN73: =IF(N(AM73)>0,AM73,AL73) -> 0.08 | AO73: =IF(N(AN73)=0,"",AN73+IF(I73="yes",AN73*Inputs!$B$10*Inputs!$B$9,0)+IFERROR(INDEX(Inputs!$B$13:$B$15,MATCH(G73,Inputs!$A$13:$A$15,0)),0)+IFERROR(INDEX(Inputs!$B$18:$B$24,MATCH(H73,Inputs!$A$18:$A$24,0)),0)) -> 0.075 | AP73: =IF(OR(N(AO73)<=0,N(AG73)=0,N(L73)=0),"",MIN(L73,AG73/AO73)) -> 19.583333 | AQ73: =IF(OR(AP73="",N(O73)=0),"",AP73/O73-1) -> -0.0069303584 | AR73: =IF(OR(AQ73="",N(O73)=0),"",AQ73+AG73/O73) -> 0.067549865 | AS73: =IF(OR(AR73="",N(AJ73)=0),"",AR73-AJ73) -> 0 | AT73: 25 | AU73: 1.47 | AV73: =IF(N(AT73)>0,AT73,L73) -> 25 | AW73: =IF(AND(N(M73)>0,N(AV73)>0),M73*AV73,IF(N(AU73)>0,AU73,N73)) -> 1.46875 | AX73: =IF(N(AN73)=0,"",AN73+IF(I73="yes",AN73*Inputs!$B$10*Inputs!$B$9,0)+IFERROR(INDEX(Inputs!$B$13:$B$15,MATCH(G73,Inputs!$A$13:$A$15,0)),0)+IFERROR(INDEX(Inputs!$B$18:$B$24,MATCH(H73,Inputs!$A$18:$A$24,0)),0)) -> 0.075 | AY73: =IF(OR(N(AX73)<=0,N(AW73)=0,N(AV73)=0),"",MIN(AV73,AW73/AX73)) -> 19.583333 | AZ73: =IF(OR(AY73="",N(O73)=0),"",AY73/O73-1) -> -0.0069303584 | BA73: =IF(OR(AZ73="",N(O73)=0),"",AZ73+AW73/O73) -> 0.067549865 | BB73: =IF(OR(BA73="",N(AR73)=0),"",BA73-AR73) -> 0 | BC73: =IF(OR(BA73="",N(U73)=0),"",BA73-U73) -> 0
A74: A-C | B74: 140 | C74: MGRB | D74: AMG | E74: AFFILIATED MANAGERS GROUP | F74: 9100 | G74: BABY_BOND | H74: FIXED | I74: no | J74: Q | K74: 4 | L74: 25 | M74: 0.0475 | N74: 1.1875 | O74: 16.15 | P74: OK | Q74: 0.08 | R74: 0.075 | S74: 15.833333 | T74: -0.019607843 | U74: 0.053921569 | V74: -0.005 | W74: =IF(N(Q74)=0,"",Q74+IF(I74="yes",Q74*Inputs!$B$10*Inputs!$B$9,0)+V74) -> 0.075 | X74: =IF(OR(N(W74)<=0,N(N74)=0,N(L74)=0),"",MIN(L74,N74/W74)) -> 15.833333 | Y74: =IF(OR(X74="",N(O74)=0),"",X74/O74-1) -> -0.019607843 | Z74: =IF(OR(Y74="",N(O74)=0),"",Y74+N74/O74) -> 0.053921569 | AA74: =IF(OR(Z74="",N(U74)=0),"",Z74-U74) -> 0 | AB74: =IF(N(Q74)=0,"",Q74+IF(I74="yes",Q74*Inputs!$B$10*Inputs!$B$9,0)+IFERROR(INDEX(Inputs!$B$13:$B$15,MATCH(G74,Inputs!$A$13:$A$15,0)),0)+IFERROR(INDEX(Inputs!$B$18:$B$24,MATCH(H74,Inputs!$A$18:$A$24,0)),0)) -> 0.075 | AC74: =IF(OR(N(AB74)<=0,N(N74)=0,N(L74)=0),"",MIN(L74,N74/AB74)) -> 15.833333 | AD74: =IF(OR(AC74="",N(O74)=0),"",AC74/O74-1) -> -0.019607843 | AE74: =IF(OR(AD74="",N(O74)=0),"",AD74+N74/O74) -> 0.053921569 | AF74: =IF(OR(AE74="",N(Z74)=0),"",AE74-Z74) -> 0 | AG74: =IF(AND(N(M74)>0,N(L74)>0),M74*L74,N74) -> 1.1875 | AH74: =IF(OR(N(AB74)<=0,N(AG74)=0,N(L74)=0),"",MIN(L74,AG74/AB74)) -> 15.833333 | AI74: =IF(OR(AH74="",N(O74)=0),"",AH74/O74-1) -> -0.019607843 | AJ74: =IF(OR(AI74="",N(O74)=0),"",AI74+AG74/O74) -> 0.053921569 | AK74: =IF(OR(AJ74="",N(AE74)=0),"",AJ74-AE74) -> 0 | AL74: =IF(N(F74)=0,"",INDEX(Inputs!$B$28:$B$32,IFERROR(MATCH(F74,Inputs!$A$28:$A$32,1),0)+1)) -> 0.08 | AN74: =IF(N(AM74)>0,AM74,AL74) -> 0.08 | AO74: =IF(N(AN74)=0,"",AN74+IF(I74="yes",AN74*Inputs!$B$10*Inputs!$B$9,0)+IFERROR(INDEX(Inputs!$B$13:$B$15,MATCH(G74,Inputs!$A$13:$A$15,0)),0)+IFERROR(INDEX(Inputs!$B$18:$B$24,MATCH(H74,Inputs!$A$18:$A$24,0)),0)) -> 0.075 | AP74: =IF(OR(N(AO74)<=0,N(AG74)=0,N(L74)=0),"",MIN(L74,AG74/AO74)) -> 15.833333 | AQ74: =IF(OR(AP74="",N(O74)=0),"",AP74/O74-1) -> -0.019607843 | AR74: =IF(OR(AQ74="",N(O74)=0),"",AQ74+AG74/O74) -> 0.053921569 | AS74: =IF(OR(AR74="",N(AJ74)=0),"",AR74-AJ74) -> 0 | AT74: 25 | AU74: 1.1875 | AV74: =IF(N(AT74)>0,AT74,L74) -> 25 | AW74: =IF(AND(N(M74)>0,N(AV74)>0),M74*AV74,IF(N(AU74)>0,AU74,N74)) -> 1.1875 | AX74: =IF(N(AN74)=0,"",AN74+IF(I74="yes",AN74*Inputs!$B$10*Inputs!$B$9,0)+IFERROR(INDEX(Inputs!$B$13:$B$15,MATCH(G74,Inputs!$A$13:$A$15,0)),0)+IFERROR(INDEX(Inputs!$B$18:$B$24,MATCH(H74,Inputs!$A$18:$A$24,0)),0)) -> 0.075 | AY74: =IF(OR(N(AX74)<=0,N(AW74)=0,N(AV74)=0),"",MIN(AV74,AW74/AX74)) -> 15.833333 | AZ74: =IF(OR(AY74="",N(O74)=0),"",AY74/O74-1) -> -0.019607843 | BA74: =IF(OR(AZ74="",N(O74)=0),"",AZ74+AW74/O74) -> 0.053921569 | BB74: =IF(OR(BA74="",N(AR74)=0),"",BA74-AR74) -> 0 | BC74: =IF(OR(BA74="",N(U74)=0),"",BA74-U74) -> 0
A75: A-C | B75: 141 | C75: MGRD | D75: AMG | E75: AFFILIATED MANAGERS GROUP | F75: 9100 | G75: BABY_BOND | H75: FIXED | I75: no | J75: Q | K75: 4 | L75: 25 | M75: 0.042 | N75: 1.05 | O75: 14.58 | P75: OK | Q75: 0.08 | R75: 0.075 | S75: 14 | T75: -0.039780521 | U75: 0.03223594 | V75: -0.005 | W75: =IF(N(Q75)=0,"",Q75+IF(I75="yes",Q75*Inputs!$B$10*Inputs!$B$9,0)+V75) -> 0.075 | X75: =IF(OR(N(W75)<=0,N(N75)=0,N(L75)=0),"",MIN(L75,N75/W75)) -> 14 | Y75: =IF(OR(X75="",N(O75)=0),"",X75/O75-1) -> -0.039780521 | Z75: =IF(OR(Y75="",N(O75)=0),"",Y75+N75/O75) -> 0.03223594 | AA75: =IF(OR(Z75="",N(U75)=0),"",Z75-U75) -> 0 | AB75: =IF(N(Q75)=0,"",Q75+IF(I75="yes",Q75*Inputs!$B$10*Inputs!$B$9,0)+IFERROR(INDEX(Inputs!$B$13:$B$15,MATCH(G75,Inputs!$A$13:$A$15,0)),0)+IFERROR(INDEX(Inputs!$B$18:$B$24,MATCH(H75,Inputs!$A$18:$A$24,0)),0)) -> 0.075 | AC75: =IF(OR(N(AB75)<=0,N(N75)=0,N(L75)=0),"",MIN(L75,N75/AB75)) -> 14 | AD75: =IF(OR(AC75="",N(O75)=0),"",AC75/O75-1) -> -0.039780521 | AE75: =IF(OR(AD75="",N(O75)=0),"",AD75+N75/O75) -> 0.03223594 | AF75: =IF(OR(AE75="",N(Z75)=0),"",AE75-Z75) -> 0 | AG75: =IF(AND(N(M75)>0,N(L75)>0),M75*L75,N75) -> 1.05 | AH75: =IF(OR(N(AB75)<=0,N(AG75)=0,N(L75)=0),"",MIN(L75,AG75/AB75)) -> 14 | AI75: =IF(OR(AH75="",N(O75)=0),"",AH75/O75-1) -> -0.039780521 | AJ75: =IF(OR(AI75="",N(O75)=0),"",AI75+AG75/O75) -> 0.03223594 | AK75: =IF(OR(AJ75="",N(AE75)=0),"",AJ75-AE75) -> 0 | AL75: =IF(N(F75)=0,"",INDEX(Inputs!$B$28:$B$32,IFERROR(MATCH(F75,Inputs!$A$28:$A$32,1),0)+1)) -> 0.08 | AN75: =IF(N(AM75)>0,AM75,AL75) -> 0.08 | AO75: =IF(N(AN75)=0,"",AN75+IF(I75="yes",AN75*Inputs!$B$10*Inputs!$B$9,0)+IFERROR(INDEX(Inputs!$B$13:$B$15,MATCH(G75,Inputs!$A$13:$A$15,0)),0)+IFERROR(INDEX(Inputs!$B$18:$B$24,MATCH(H75,Inputs!$A$18:$A$24,0)),0)) -> 0.075 | AP75: =IF(OR(N(AO75)<=0,N(AG75)=0,N(L75)=0),"",MIN(L75,AG75/AO75)) -> 14 | AQ75: =IF(OR(AP75="",N(O75)=0),"",AP75/O75-1) -> -0.039780521 | AR75: =IF(OR(AQ75="",N(O75)=0),"",AQ75+AG75/O75) -> 0.03223594 | AS75: =IF(OR(AR75="",N(AJ75)=0),"",AR75-AJ75) -> 0 | AT75: 25 | AU75: 1.05 | AV75: =IF(N(AT75)>0,AT75,L75) -> 25 | AW75: =IF(AND(N(M75)>0,N(AV75)>0),M75*AV75,IF(N(AU75)>0,AU75,N75)) -> 1.05 | AX75: =IF(N(AN75)=0,"",AN75+IF(I75="yes",AN75*Inputs!$B$10*Inputs!$B$9,0)+IFERROR(INDEX(Inputs!$B$13:$B$15,MATCH(G75,Inputs!$A$13:$A$15,0)),0)+IFERROR(INDEX(Inputs!$B$18:$B$24,MATCH(H75,Inputs!$A$18:$A$24,0)),0)) -> 0.075 | AY75: =IF(OR(N(AX75)<=0,N(AW75)=0,N(AV75)=0),"",MIN(AV75,AW75/AX75)) -> 14 | AZ75: =IF(OR(AY75="",N(O75)=0),"",AY75/O75-1) -> -0.039780521 | BA75: =IF(OR(AZ75="",N(O75)=0),"",AZ75+AW75/O75) -> 0.03223594 | BB75: =IF(OR(BA75="",N(AR75)=0),"",BA75-AR75) -> 0 | BC75: =IF(OR(BA75="",N(U75)=0),"",BA75-U75) -> 0
